Workbook

Sheet Portfolio Input
A1: AI Moat Risk Analyzer — Portfolio Input
A2: Enter tickers in column A. Bloomberg BDP formulas auto-populate. Blue cells = manual inputs.
A3: HOW IT WORKS: Type ticker → Bloomberg populates financials → Score in Moat Scoring & BM Risk tabs → Dashboard auto-calculates.
A4: Ticker | B4: Company Name | C4: GICS Sector | D4: GICS Sub-Industry | E4: Price ($) | F4: Mkt Cap ($B) | G4: Beta | H4: Fwd P/E (x) | I4: ROIC (%) | J4: ROE (%) | K4: Gross Margin (%) | L4: Op. Margin (%) | M4: Net Margin (%) | N4: FCF Yield (%) | O4: D/E (x) | P4: Div Yield (%) | Q4: EV/EBITDA (x) | R4: P/B (x) | S4: R&D/Rev (%) | T4: 5yr Rev CAGR (%) | U4: WACC Est (%)
A5: AAPL | B5: =IF(A5="","",_xll.BDP(A5&" US Equity","NAME")) -> APPLE INC | C5: =IF(A5="","",_xll.BDP(A5&" US Equity","GICS_SECTOR_NAME")) -> Information Technology | D5: =IF(A5="","",_xll.BDP(A5&" US Equity","GICS_SUB_INDUSTRY_NAME")) -> Technology Hardware, Storage & | E5: =IF(A5="","",_xll.BDP(A5&" US Equity","PX_LAST")) -> 259.445 | F5: =IF(A5="","",_xll.BDP(A5&" US Equity","CUR_MKT_CAP")/1000000000) -> 3808.9484 | G5: =IF(A5="","",_xll.BDP(A5&" US Equity","BETA_RAW_OVERRIDABLE")) -> 1.1099219 | H5: =IF(A5="","",_xll.BDP(A5&" US Equity","BEST_PE_RATIO")) -> 30.052705 | I5: =IF(A5="","",_xll.BDP(A5&" US Equity","RETURN_ON_INV_CAPITAL")) -> 68.788493 | J5: =IF(A5="","",_xll.BDP(A5&" US Equity","RETURN_COM_EQY")) -> 152.02132 | K5: =IF(A5="","",_xll.BDP(A5&" US Equity","GROSS_MARGIN")) -> 46.905164 | L5: =IF(A5="","",_xll.BDP(A5&" US Equity","OPER_MARGIN")) -> 31.9708 | M5: =IF(A5="","",_xll.BDP(A5&" US Equity","NET_INCOME_MARGIN")) -> #N/A Invalid Field | N5: =IF(A5="","",_xll.BDP(A5&" US Equity","FREE_CASH_FLOW_YIELD")) -> 3.2043212 | O5: =IF(A5="","",_xll.BDP(A5&" US Equity","TOT_DEBT_TO_TOT_EQY")) -> 152.41073 | P5: =IF(A5="","",_xll.BDP(A5&" US Equity","EQY_DVD_YLD_IND")) -> 0.40085566 | Q5: =IF(A5="","",_xll.BDP(A5&" US Equity","BEST_CUR_EV_TO_EBITDA")) -> 22.607475 | R5: =IF(A5="","",_xll.BDP(A5&" US Equity","PX_TO_BOOK_RATIO")) -> 43.25369 | S5: =IF(A5="","",_xll.BDP(A5&" US Equity","RESEARCH_AND_DEV_TO_REVENUE")) -> #N/A Invalid Field | T5: =IF(A5="","",_xll.BDP(A5&" US Equity","REVENUE_5YR_CAGR")) -> #N/A Invalid Field | U5: =IF(A5="","",0.045+G5*0.05) -> 0.1004961
A6: MSFT | B6: =IF(A6="","",_xll.BDP(A6&" US Equity","NAME")) -> MICROSOFT CORP | C6: =IF(A6="","",_xll.BDP(A6&" US Equity","GICS_SECTOR_NAME")) -> Information Technology | D6: =IF(A6="","",_xll.BDP(A6&" US Equity","GICS_SUB_INDUSTRY_NAME")) -> Systems Software | E6: =IF(A6="","",_xll.BDP(A6&" US Equity","PX_LAST")) -> 402.795 | F6: =IF(A6="","",_xll.BDP(A6&" US Equity","CUR_MKT_CAP")/1000000000) -> 2991.0063 | G6: =IF(A6="","",_xll.BDP(A6&" US Equity","BETA_RAW_OVERRIDABLE")) -> 1.0233857 | H6: =IF(A6="","",_xll.BDP(A6&" US Equity","BEST_PE_RATIO")) -> 22.88608 | I6: =IF(A6="","",_xll.BDP(A6&" US Equity","RETURN_ON_INV_CAPITAL")) -> 25.012015 | J6: =IF(A6="","",_xll.BDP(A6&" US Equity","RETURN_COM_EQY")) -> 34.390761 | K6: =IF(A6="","",_xll.BDP(A6&" US Equity","GROSS_MARGIN")) -> 68.823742 | L6: =IF(A6="","",_xll.BDP(A6&" US Equity","OPER_MARGIN")) -> 45.621956 | M6: =IF(A6="","",_xll.BDP(A6&" US Equity","NET_INCOME_MARGIN")) -> #N/A Invalid Field | N6: =IF(A6="","",_xll.BDP(A6&" US Equity","FREE_CASH_FLOW_YIELD")) -> 2.585669 | O6: =IF(A6="","",_xll.BDP(A6&" US Equity","TOT_DEBT_TO_TOT_EQY")) -> 32.661094 | P6: =IF(A6="","",_xll.BDP(A6&" US Equity","EQY_DVD_YLD_IND")) -> 0.90368552 | Q6: =IF(A6="","",_xll.BDP(A6&" US Equity","BEST_CUR_EV_TO_EBITDA")) -> 14.170161 | R6: =IF(A6="","",_xll.BDP(A6&" US Equity","PX_TO_BOOK_RATIO")) -> 7.6555527 | S6: =IF(A6="","",_xll.BDP(A6&" US Equity","RESEARCH_AND_DEV_TO_REVENUE")) -> #N/A Invalid Field | T6: =IF(A6="","",_xll.BDP(A6&" US Equity","REVENUE_5YR_CAGR")) -> #N/A Invalid Field | U6: =IF(A6="","",0.045+G6*0.05) -> 0.096169286
A7: GOOGL | B7: =IF(A7="","",_xll.BDP(A7&" US Equity","NAME")) -> ALPHABET INC-CL A | C7: =IF(A7="","",_xll.BDP(A7&" US Equity","GICS_SECTOR_NAME")) -> Communication Services | D7: =IF(A7="","",_xll.BDP(A7&" US Equity","GICS_SUB_INDUSTRY_NAME")) -> Interactive Media & Services | E7: =IF(A7="","",_xll.BDP(A7&" US Equity","PX_LAST")) -> 306.735 | F7: =IF(A7="","",_xll.BDP(A7&" US Equity","CUR_MKT_CAP")/1000000000) -> 3712.828 | G7: =IF(A7="","",_xll.BDP(A7&" US Equity","BETA_RAW_OVERRIDABLE")) -> 1.065303 | H7: =IF(A7="","",_xll.BDP(A7&" US Equity","BEST_PE_RATIO")) -> 25.162838 | I7: =IF(A7="","",_xll.BDP(A7&" US Equity","RETURN_ON_INV_CAPITAL")) -> 25.130867 | J7: =IF(A7="","",_xll.BDP(A7&" US Equity","RETURN_COM_EQY")) -> 35.704782 | K7: =IF(A7="","",_xll.BDP(A7&" US Equity","GROSS_MARGIN")) -> 59.652315 | L7: =IF(A7="","",_xll.BDP(A7&" US Equity","OPER_MARGIN")) -> 32.032639 | M7: =IF(A7="","",_xll.BDP(A7&" US Equity","NET_INCOME_MARGIN")) -> #N/A Invalid Field | N7: =IF(A7="","",_xll.BDP(A7&" US Equity","FREE_CASH_FLOW_YIELD")) -> 1.9725348 | O7: =IF(A7="","",_xll.BDP(A7&" US Equity","TOT_DEBT_TO_TOT_EQY")) -> 15.156828 | P7: =IF(A7="","",_xll.BDP(A7&" US Equity","EQY_DVD_YLD_IND")) -> 0.27385201 | Q7: =IF(A7="","",_xll.BDP(A7&" US Equity","BEST_CUR_EV_TO_EBITDA")) -> 16.449676 | R7: =IF(A7="","",_xll.BDP(A7&" US Equity","PX_TO_BOOK_RATIO")) -> 9.0196402 | S7: =IF(A7="","",_xll.BDP(A7&" US Equity","RESEARCH_AND_DEV_TO_REVENUE")) -> #N/A Invalid Field | T7: =IF(A7="","",_xll.BDP(A7&" US Equity","REVENUE_5YR_CAGR")) -> #N/A Invalid Field | U7: =IF(A7="","",0.045+G7*0.05) -> 0.098265152
A8: NVDA | B8: =IF(A8="","",_xll.BDP(A8&" US Equity","NAME")) -> NVIDIA CORP | C8: =IF(A8="","",_xll.BDP(A8&" US Equity","GICS_SECTOR_NAME")) -> Information Technology | D8: =IF(A8="","",_xll.BDP(A8&" US Equity","GICS_SUB_INDUSTRY_NAME")) -> Semiconductors | E8: =IF(A8="","",_xll.BDP(A8&" US Equity","PX_LAST")) -> 184.0799 | F8: =IF(A8="","",_xll.BDP(A8&" US Equity","CUR_MKT_CAP")/1000000000) -> 4473.1416 | G8: =IF(A8="","",_xll.BDP(A8&" US Equity","BETA_RAW_OVERRIDABLE")) -> 2.2647578 | H8: =IF(A8="","",_xll.BDP(A8&" US Equity","BEST_PE_RATIO")) -> 26.136575 | I8: =IF(A8="","",_xll.BDP(A8&" US Equity","RETURN_ON_INV_CAPITAL")) -> 99.6596 | J8: =IF(A8="","",_xll.BDP(A8&" US Equity","RETURN_COM_EQY")) -> 107.35947 | K8: =IF(A8="","",_xll.BDP(A8&" US Equity","GROSS_MARGIN")) -> 74.988697 | L8: =IF(A8="","",_xll.BDP(A8&" US Equity","OPER_MARGIN")) -> 62.417527 | M8: =IF(A8="","",_xll.BDP(A8&" US Equity","NET_INCOME_MARGIN")) -> #N/A Invalid Field | N8: =IF(A8="","",_xll.BDP(A8&" US Equity","FREE_CASH_FLOW_YIELD")) -> 1.7211146 | O8: =IF(A8="","",_xll.BDP(A8&" US Equity","TOT_DEBT_TO_TOT_EQY")) -> 12.946412 | P8: =IF(A8="","",_xll.BDP(A8&" US Equity","EQY_DVD_YLD_IND")) -> 0.021729694 | Q8: =IF(A8="","",_xll.BDP(A8&" US Equity","BEST_CUR_EV_TO_EBITDA")) -> 20.715651 | R8: =IF(A8="","",_xll.BDP(A8&" US Equity","PX_TO_BOOK_RATIO")) -> 37.629729 | S8: =IF(A8="","",_xll.BDP(A8&" US Equity","RESEARCH_AND_DEV_TO_REVENUE")) -> #N/A Invalid Field | T8: =IF(A8="","",_xll.BDP(A8&" US Equity","REVENUE_5YR_CAGR")) -> #N/A Invalid Field | U8: =IF(A8="","",0.045+G8*0.05) -> 0.15823789
A9: AMZN | B9: =IF(A9="","",_xll.BDP(A9&" US Equity","NAME")) -> AMAZON.COM INC | C9: =IF(A9="","",_xll.BDP(A9&" US Equity","GICS_SECTOR_NAME")) -> Consumer Discretionary | D9: =IF(A9="","",_xll.BDP(A9&" US Equity","GICS_SUB_INDUSTRY_NAME")) -> Broadline Retail | E9: =IF(A9="","",_xll.BDP(A9&" US Equity","PX_LAST")) -> 200.51 | F9: =IF(A9="","",_xll.BDP(A9&" US Equity","CUR_MKT_CAP")/1000000000) -> 2152.459 | G9: =IF(A9="","",_xll.BDP(A9&" US Equity","BETA_RAW_OVERRIDABLE")) -> 1.4213262 | H9: =IF(A9="","",_xll.BDP(A9&" US Equity","BEST_PE_RATIO")) -> 21.155307 | I9: =IF(A9="","",_xll.BDP(A9&" US Equity","RETURN_ON_INV_CAPITAL")) -> 12.435293 | J9: =IF(A9="","",_xll.BDP(A9&" US Equity","RETURN_COM_EQY")) -> 22.285825 | K9: =IF(A9="","",_xll.BDP(A9&" US Equity","GROSS_MARGIN")) -> 50.285665 | L9: =IF(A9="","",_xll.BDP(A9&" US Equity","OPER_MARGIN")) -> 11.155297 | M9: =IF(A9="","",_xll.BDP(A9&" US Equity","NET_INCOME_MARGIN")) -> #N/A Invalid Field | N9: =IF(A9="","",_xll.BDP(A9&" US Equity","FREE_CASH_FLOW_YIELD")) -> 0.35480726 | O9: =IF(A9="","",_xll.BDP(A9&" US Equity","TOT_DEBT_TO_TOT_EQY")) -> 41.339934 | P9: =IF(A9="","",_xll.BDP(A9&" US Equity","EQY_DVD_YLD_IND")) -> #N/A N/A | Q9: =IF(A9="","",_xll.BDP(A9&" US Equity","BEST_CUR_EV_TO_EBITDA")) -> 10.152692 | R9: =IF(A9="","",_xll.BDP(A9&" US Equity","PX_TO_BOOK_RATIO")) -> 5.2343857 | S9: =IF(A9="","",_xll.BDP(A9&" US Equity","RESEARCH_AND_DEV_TO_REVENUE")) -> #N/A Invalid Field | T9: =IF(A9="","",_xll.BDP(A9&" US Equity","REVENUE_5YR_CAGR")) -> #N/A Invalid Field | U9: =IF(A9="","",0.045+G9*0.05) -> 0.11606631
A10: META | B10: =IF(A10="","",_xll.BDP(A10&" US Equity","NAME")) -> META PLATFORMS INC-CLASS A | C10: =IF(A10="","",_xll.BDP(A10&" US Equity","GICS_SECTOR_NAME")) -> Communication Services | D10: =IF(A10="","",_xll.BDP(A10&" US Equity","GICS_SUB_INDUSTRY_NAME")) -> Interactive Media & Services | E10: =IF(A10="","",_xll.BDP(A10&" US Equity","PX_LAST")) -> 650.47 | F10: =IF(A10="","",_xll.BDP(A10&" US Equity","CUR_MKT_CAP")/1000000000) -> 1645.9212 | G10: =IF(A10="","",_xll.BDP(A10&" US Equity","BETA_RAW_OVERRIDABLE")) -> 1.2868528 | H10: =IF(A10="","",_xll.BDP(A10&" US Equity","BEST_PE_RATIO")) -> 19.2612 | I10: =IF(A10="","",_xll.BDP(A10&" US Equity","RETURN_ON_INV_CAPITAL")) -> 22.027166 | J10: =IF(A10="","",_xll.BDP(A10&" US Equity","RETURN_COM_EQY")) -> 30.238071 | K10: =IF(A10="","",_xll.BDP(A10&" US Equity","GROSS_MARGIN")) -> 81.999443 | L10: =IF(A10="","",_xll.BDP(A10&" US Equity","OPER_MARGIN")) -> 41.437855 | M10: =IF(A10="","",_xll.BDP(A10&" US Equity","NET_INCOME_MARGIN")) -> #N/A Invalid Field | N10: =IF(A10="","",_xll.BDP(A10&" US Equity","FREE_CASH_FLOW_YIELD")) -> 2.8105079 | O10: =IF(A10="","",_xll.BDP(A10&" US Equity","TOT_DEBT_TO_TOT_EQY")) -> 39.163978 | P10: =IF(A10="","",_xll.BDP(A10&" US Equity","EQY_DVD_YLD_IND")) -> 0.32284347 | Q10: =IF(A10="","",_xll.BDP(A10&" US Equity","BEST_CUR_EV_TO_EBITDA")) -> 13.35076 | R10: =IF(A10="","",_xll.BDP(A10&" US Equity","PX_TO_BOOK_RATIO")) -> 7.58432 | S10: =IF(A10="","",_xll.BDP(A10&" US Equity","RESEARCH_AND_DEV_TO_REVENUE")) -> #N/A Invalid Field | T10: =IF(A10="","",_xll.BDP(A10&" US Equity","REVENUE_5YR_CAGR")) -> #N/A Invalid Field | U10: =IF(A10="","",0.045+G10*0.05) -> 0.10934264
A11: V | B11: =IF(A11="","",_xll.BDP(A11&" US Equity","NAME")) -> VISA INC-CLASS A SHARES | C11: =IF(A11="","",_xll.BDP(A11&" US Equity","GICS_SECTOR_NAME")) -> Financials | D11: =IF(A11="","",_xll.BDP(A11&" US Equity","GICS_SUB_INDUSTRY_NAME")) -> Transaction & Payment Processi | E11: =IF(A11="","",_xll.BDP(A11&" US Equity","PX_LAST")) -> 318.855 | F11: =IF(A11="","",_xll.BDP(A11&" US Equity","CUR_MKT_CAP")/1000000000) -> 622.39816 | G11: =IF(A11="","",_xll.BDP(A11&" US Equity","BETA_RAW_OVERRIDABLE")) -> 0.75626543 | H11: =IF(A11="","",_xll.BDP(A11&" US Equity","BEST_PE_RATIO")) -> 24.073613 | I11: =IF(A11="","",_xll.BDP(A11&" US Equity","RETURN_ON_INV_CAPITAL")) -> 34.676108 | J11: =IF(A11="","",_xll.BDP(A11&" US Equity","RETURN_COM_EQY")) -> 54.992198 | K11: =IF(A11="","",_xll.BDP(A11&" US Equity","GROSS_MARGIN")) -> #N/A N/A | L11: =IF(A11="","",_xll.BDP(A11&" US Equity","OPER_MARGIN")) -> 59.985 | M11: =IF(A11="","",_xll.BDP(A11&" US Equity","NET_INCOME_MARGIN")) -> #N/A Invalid Field | N11: =IF(A11="","",_xll.BDP(A11&" US Equity","FREE_CASH_FLOW_YIELD")) -> 3.9170674 | O11: =IF(A11="","",_xll.BDP(A11&" US Equity","TOT_DEBT_TO_TOT_EQY")) -> 68.80688 | P11: =IF(A11="","",_xll.BDP(A11&" US Equity","EQY_DVD_YLD_IND")) -> 0.84050746 | Q11: =IF(A11="","",_xll.BDP(A11&" US Equity","BEST_CUR_EV_TO_EBITDA")) -> 19.368512 | R11: =IF(A11="","",_xll.BDP(A11&" US Equity","PX_TO_BOOK_RATIO")) -> 15.156165 | S11: =IF(A11="","",_xll.BDP(A11&" US Equity","RESEARCH_AND_DEV_TO_REVENUE")) -> #N/A Invalid Field | T11: =IF(A11="","",_xll.BDP(A11&" US Equity","REVENUE_5YR_CAGR")) -> #N/A Invalid Field | U11: =IF(A11="","",0.045+G11*0.05) -> 0.082813272
A12: MA | B12: =IF(A12="","",_xll.BDP(A12&" US Equity","NAME")) -> MASTERCARD INC - A | C12: =IF(A12="","",_xll.BDP(A12&" US Equity","GICS_SECTOR_NAME")) -> Financials | D12: =IF(A12="","",_xll.BDP(A12&" US Equity","GICS_SUB_INDUSTRY_NAME")) -> Transaction & Payment Processi | E12: =IF(A12="","",_xll.BDP(A12&" US Equity","PX_LAST")) -> 525.28 | F12: =IF(A12="","",_xll.BDP(A12&" US Equity","CUR_MKT_CAP")/1000000000) -> 468.52562 | G12: =IF(A12="","",_xll.BDP(A12&" US Equity","BETA_RAW_OVERRIDABLE")) -> 0.78531752 | H12: =IF(A12="","",_xll.BDP(A12&" US Equity","BEST_PE_RATIO")) -> 26.849315 | I12: =IF(A12="","",_xll.BDP(A12&" US Equity","RETURN_ON_INV_CAPITAL")) -> 58.677643 | J12: =IF(A12="","",_xll.BDP(A12&" US Equity","RETURN_COM_EQY")) -> 210.49079 | K12: =IF(A12="","",_xll.BDP(A12&" US Equity","GROSS_MARGIN")) -> #N/A N/A | L12: =IF(A12="","",_xll.BDP(A12&" US Equity","OPER_MARGIN")) -> 57.628618 | M12: =IF(A12="","",_xll.BDP(A12&" US Equity","NET_INCOME_MARGIN")) -> #N/A Invalid Field | N12: =IF(A12="","",_xll.BDP(A12&" US Equity","FREE_CASH_FLOW_YIELD")) -> 3.6145177 | O12: =IF(A12="","",_xll.BDP(A12&" US Equity","TOT_DEBT_TO_TOT_EQY")) -> 256.04183 | P12: =IF(A12="","",_xll.BDP(A12&" US Equity","EQY_DVD_YLD_IND")) -> 0.66250381 | Q12: =IF(A12="","",_xll.BDP(A12&" US Equity","BEST_CUR_EV_TO_EBITDA")) -> 20.444834 | R12: =IF(A12="","",_xll.BDP(A12&" US Equity","PX_TO_BOOK_RATIO")) -> 60.695405 | S12: =IF(A12="","",_xll.BDP(A12&" US Equity","RESEARCH_AND_DEV_TO_REVENUE")) -> #N/A Invalid Field | T12: =IF(A12="","",_xll.BDP(A12&" US Equity","REVENUE_5YR_CAGR")) -> #N/A Invalid Field | U12: =IF(A12="","",0.045+G12*0.05) -> 0.084265876
A13: ACN | B13: =IF(A13="","",_xll.BDP(A13&" US Equity","NAME")) -> ACCENTURE PLC-CL A | C13: =IF(A13="","",_xll.BDP(A13&" US Equity","GICS_SECTOR_NAME")) -> Information Technology | D13: =IF(A13="","",_xll.BDP(A13&" US Equity","GICS_SUB_INDUSTRY_NAME")) -> IT Consulting & Other Services | E13: =IF(A13="","",_xll.BDP(A13&" US Equity","PX_LAST")) -> 223.92 | F13: =IF(A13="","",_xll.BDP(A13&" US Equity","CUR_MKT_CAP")/1000000000) -> 148.0408 | G13: =IF(A13="","",_xll.BDP(A13&" US Equity","BETA_RAW_OVERRIDABLE")) -> 0.60246106 | H13: =IF(A13="","",_xll.BDP(A13&" US Equity","BEST_PE_RATIO")) -> 16.010296 | I13: =IF(A13="","",_xll.BDP(A13&" US Equity","RETURN_ON_INV_CAPITAL")) -> 20.961927 | J13: =IF(A13="","",_xll.BDP(A13&" US Equity","RETURN_COM_EQY")) -> 25.345833 | K13: =IF(A13="","",_xll.BDP(A13&" US Equity","GROSS_MARGIN")) -> 31.913953 | L13: =IF(A13="","",_xll.BDP(A13&" US Equity","OPER_MARGIN")) -> 14.676657 | M13: =IF(A13="","",_xll.BDP(A13&" US Equity","NET_INCOME_MARGIN")) -> #N/A Invalid Field | N13: =IF(A13="","",_xll.BDP(A13&" US Equity","FREE_CASH_FLOW_YIELD")) -> 8.2427933 | O13: =IF(A13="","",_xll.BDP(A13&" US Equity","TOT_DEBT_TO_TOT_EQY")) -> 25.380337 | P13: =IF(A13="","",_xll.BDP(A13&" US Equity","EQY_DVD_YLD_IND")) -> 2.9117542 | Q13: =IF(A13="","",_xll.BDP(A13&" US Equity","BEST_CUR_EV_TO_EBITDA")) -> 10.090769 | R13: =IF(A13="","",_xll.BDP(A13&" US Equity","PX_TO_BOOK_RATIO")) -> 4.4661246 | S13: =IF(A13="","",_xll.BDP(A13&" US Equity","RESEARCH_AND_DEV_TO_REVENUE")) -> #N/A Invalid Field | T13: =IF(A13="","",_xll.BDP(A13&" US Equity","REVENUE_5YR_CAGR")) -> #N/A Invalid Field | U13: =IF(A13="","",0.045+G13*0.05) -> 0.075123053
A14: CRM | B14: =IF(A14="","",_xll.BDP(A14&" US Equity","NAME")) -> SALESFORCE INC | C14: =IF(A14="","",_xll.BDP(A14&" US Equity","GICS_SECTOR_NAME")) -> Information Technology | D14: =IF(A14="","",_xll.BDP(A14&" US Equity","GICS_SUB_INDUSTRY_NAME")) -> Application Software | E14: =IF(A14="","",_xll.BDP(A14&" US Equity","PX_LAST")) -> 190.84 | F14: =IF(A14="","",_xll.BDP(A14&" US Equity","CUR_MKT_CAP")/1000000000) -> 178.81708 | G14: =IF(A14="","",_xll.BDP(A14&" US Equity","BETA_RAW_OVERRIDABLE")) -> 1.334756 | H14: =IF(A14="","",_xll.BDP(A14&" US Equity","BEST_PE_RATIO")) -> 15.093325 | I14: =IF(A14="","",_xll.BDP(A14&" US Equity","RETURN_ON_INV_CAPITAL")) -> 9.4487734 | J14: =IF(A14="","",_xll.BDP(A14&" US Equity","RETURN_COM_EQY")) -> 12.1843 | K14: =IF(A14="","",_xll.BDP(A14&" US Equity","GROSS_MARGIN")) -> 77.192242 | L14: =IF(A14="","",_xll.BDP(A14&" US Equity","OPER_MARGIN")) -> 19.013062 | M14: =IF(A14="","",_xll.BDP(A14&" US Equity","NET_INCOME_MARGIN")) -> #N/A Invalid Field | N14: =IF(A14="","",_xll.BDP(A14&" US Equity","FREE_CASH_FLOW_YIELD")) -> 7.0500016 | O14: =IF(A14="","",_xll.BDP(A14&" US Equity","TOT_DEBT_TO_TOT_EQY")) -> 19.730927 | P14: =IF(A14="","",_xll.BDP(A14&" US Equity","EQY_DVD_YLD_IND")) -> 0.87193462 | Q14: =IF(A14="","",_xll.BDP(A14&" US Equity","BEST_CUR_EV_TO_EBITDA")) -> 9.3342945 | R14: =IF(A14="","",_xll.BDP(A14&" US Equity","PX_TO_BOOK_RATIO")) -> 2.9951396 | S14: =IF(A14="","",_xll.BDP(A14&" US Equity","RESEARCH_AND_DEV_TO_REVENUE")) -> #N/A Invalid Field | T14: =IF(A14="","",_xll.BDP(A14&" US Equity","REVENUE_5YR_CAGR")) -> #N/A Invalid Field | U14: =IF(A14="","",0.045+G14*0.05) -> 0.1117378
A15: ADBE | B15: =IF(A15="","",_xll.BDP(A15&" US Equity","NAME")) -> ADOBE INC | C15: =IF(A15="","",_xll.BDP(A15&" US Equity","GICS_SECTOR_NAME")) -> Information Technology | D15: =IF(A15="","",_xll.BDP(A15&" US Equity","GICS_SUB_INDUSTRY_NAME")) -> Application Software | E15: =IF(A15="","",_xll.BDP(A15&" US Equity","PX_LAST")) -> 264.165 | F15: =IF(A15="","",_xll.BDP(A15&" US Equity","CUR_MKT_CAP")/1000000000) -> 108.43973 | G15: =IF(A15="","",_xll.BDP(A15&" US Equity","BETA_RAW_OVERRIDABLE")) -> 1.0078306 | H15: =IF(A15="","",_xll.BDP(A15&" US Equity","BEST_PE_RATIO")) -> 11.231983 | I15: =IF(A15="","",_xll.BDP(A15&" US Equity","RETURN_ON_INV_CAPITAL")) -> 33.222853 | J15: =IF(A15="","",_xll.BDP(A15&" US Equity","RETURN_COM_EQY")) -> 55.425995 | K15: =IF(A15="","",_xll.BDP(A15&" US Equity","GROSS_MARGIN")) -> 89.267533 | L15: =IF(A15="","",_xll.BDP(A15&" US Equity","OPER_MARGIN")) -> 36.62754 | M15: =IF(A15="","",_xll.BDP(A15&" US Equity","NET_INCOME_MARGIN")) -> #N/A Invalid Field | N15: =IF(A15="","",_xll.BDP(A15&" US Equity","FREE_CASH_FLOW_YIELD")) -> 8.7690573 | O15: =IF(A15="","",_xll.BDP(A15&" US Equity","TOT_DEBT_TO_TOT_EQY")) -> 57.196937 | P15: =IF(A15="","",_xll.BDP(A15&" US Equity","EQY_DVD_YLD_IND")) -> #N/A N/A | Q15: =IF(A15="","",_xll.BDP(A15&" US Equity","BEST_CUR_EV_TO_EBITDA")) -> 8.6890312 | R15: =IF(A15="","",_xll.BDP(A15&" US Equity","PX_TO_BOOK_RATIO")) -> 9.3865739 | S15: =IF(A15="","",_xll.BDP(A15&" US Equity","RESEARCH_AND_DEV_TO_REVENUE")) -> #N/A Invalid Field | T15: =IF(A15="","",_xll.BDP(A15&" US Equity","REVENUE_5YR_CAGR")) -> #N/A Invalid Field | U15: =IF(A15="","",0.045+G15*0.05) -> 0.095391531
A16: NOW | B16: =IF(A16="","",_xll.BDP(A16&" US Equity","NAME")) -> SERVICENOW INC | C16: =IF(A16="","",_xll.BDP(A16&" US Equity","GICS_SECTOR_NAME")) -> Information Technology | D16: =IF(A16="","",_xll.BDP(A16&" US Equity","GICS_SUB_INDUSTRY_NAME")) -> Systems Software | E16: =IF(A16="","",_xll.BDP(A16&" US Equity","PX_LAST")) -> 107 | F16: =IF(A16="","",_xll.BDP(A16&" US Equity","CUR_MKT_CAP")/1000000000) -> 111.9219 | G16: =IF(A16="","",_xll.BDP(A16&" US Equity","BETA_RAW_OVERRIDABLE")) -> 1.4089862 | H16: =IF(A16="","",_xll.BDP(A16&" US Equity","BEST_PE_RATIO")) -> 25.665627 | I16: =IF(A16="","",_xll.BDP(A16&" US Equity","RETURN_ON_INV_CAPITAL")) -> 10.202797 | J16: =IF(A16="","",_xll.BDP(A16&" US Equity","RETURN_COM_EQY")) -> 15.487529 | K16: =IF(A16="","",_xll.BDP(A16&" US Equity","GROSS_MARGIN")) -> 77.534267 | L16: =IF(A16="","",_xll.BDP(A16&" US Equity","OPER_MARGIN")) -> 13.737009 | M16: =IF(A16="","",_xll.BDP(A16&" US Equity","NET_INCOME_MARGIN")) -> #N/A Invalid Field | N16: =IF(A16="","",_xll.BDP(A16&" US Equity","FREE_CASH_FLOW_YIELD")) -> 4.1242633 | O16: =IF(A16="","",_xll.BDP(A16&" US Equity","TOT_DEBT_TO_TOT_EQY")) -> 18.535946 | P16: =IF(A16="","",_xll.BDP(A16&" US Equity","EQY_DVD_YLD_IND")) -> #N/A N/A | Q16: =IF(A16="","",_xll.BDP(A16&" US Equity","BEST_CUR_EV_TO_EBITDA")) -> 17.148487 | R16: =IF(A16="","",_xll.BDP(A16&" US Equity","PX_TO_BOOK_RATIO")) -> 8.6438323 | S16: =IF(A16="","",_xll.BDP(A16&" US Equity","RESEARCH_AND_DEV_TO_REVENUE")) -> #N/A Invalid Field | T16: =IF(A16="","",_xll.BDP(A16&" US Equity","REVENUE_5YR_CAGR")) -> #N/A Invalid Field | U16: =IF(A16="","",0.045+G16*0.05) -> 0.11544931
... A25: GAP | B25: =IF(A25="","",_xll.BDP(A25&" US Equity","NAME")) -> GAP INC/THE | C25: =IF(A25="","",_xll.BDP(A25&" US Equity","GICS_SECTOR_NAME")) -> Consumer Discretionary | D25: =IF(A25="","",_xll.BDP(A25&" US Equity","GICS_SUB_INDUSTRY_NAME")) -> Apparel Retail | E25: =IF(A25="","",_xll.BDP(A25&" US Equity","PX_LAST")) -> 27.675 | F25: =IF(A25="","",_xll.BDP(A25&" US Equity","CUR_MKT_CAP")/1000000000) -> 10.292934 | G25: =IF(A25="","",_xll.BDP(A25&" US Equity","BETA_RAW_OVERRIDABLE")) -> 1.2394717 | H25: =IF(A25="","",_xll.BDP(A25&" US Equity","BEST_PE_RATIO")) -> 12.37148 | I25: =IF(A25="","",_xll.BDP(A25&" US Equity","RETURN_ON_INV_CAPITAL")) -> 9.3427412 | J25: =IF(A25="","",_xll.BDP(A25&" US Equity","RETURN_COM_EQY")) -> 25.095842 | K25: =IF(A25="","",_xll.BDP(A25&" US Equity","GROSS_MARGIN")) -> 41.27668 | L25: =IF(A25="","",_xll.BDP(A25&" US Equity","OPER_MARGIN")) -> 7.3710725 | M25: =IF(A25="","",_xll.BDP(A25&" US Equity","NET_INCOME_MARGIN")) -> #N/A Invalid Field | N25: =IF(A25="","",_xll.BDP(A25&" US Equity","FREE_CASH_FLOW_YIELD")) -> 7.5106375 | O25: =IF(A25="","",_xll.BDP(A25&" US Equity","TOT_DEBT_TO_TOT_EQY")) -> 167.73897 | P25: =IF(A25="","",_xll.BDP(A25&" US Equity","EQY_DVD_YLD_IND")) -> 2.3848239 | Q25: =IF(A25="","",_xll.BDP(A25&" US Equity","BEST_CUR_EV_TO_EBITDA")) -> 5.6313987 | R25: =IF(A25="","",_xll.BDP(A25&" US Equity","PX_TO_BOOK_RATIO")) -> 2.8228955 | S25: =IF(A25="","",_xll.BDP(A25&" US Equity","RESEARCH_AND_DEV_TO_REVENUE")) -> #N/A Invalid Field | T25: =IF(A25="","",_xll.BDP(A25&" US Equity","REVENUE_5YR_CAGR")) -> #N/A Invalid Field | U25: =IF(A25="","",0.045+G25*0.05) -> 0.10697359
B26: =IF(A26="","",_xll.BDP(A26&" US Equity","NAME")) | C26: =IF(A26="","",_xll.BDP(A26&" US Equity","GICS_SECTOR_NAME")) | D26: =IF(A26="","",_xll.BDP(A26&" US Equity","GICS_SUB_INDUSTRY_NAME")) | E26: =IF(A26="","",_xll.BDP(A26&" US Equity","PX_LAST")) | F26: =IF(A26="","",_xll.BDP(A26&" US Equity","CUR_MKT_CAP")/1000000000) | G26: =IF(A26="","",_xll.BDP(A26&" US Equity","BETA_RAW_OVERRIDABLE")) | H26: =IF(A26="","",_xll.BDP(A26&" US Equity","BEST_PE_RATIO")) | I26: =IF(A26="","",_xll.BDP(A26&" US Equity","RETURN_ON_INV_CAPITAL")) | J26: =IF(A26="","",_xll.BDP(A26&" US Equity","RETURN_COM_EQY")) | K26: =IF(A26="","",_xll.BDP(A26&" US Equity","GROSS_MARGIN")) | L26: =IF(A26="","",_xll.BDP(A26&" US Equity","OPER_MARGIN")) | M26: =IF(A26="","",_xll.BDP(A26&" US Equity","NET_INCOME_MARGIN")) | N26: =IF(A26="","",_xll.BDP(A26&" US Equity","FREE_CASH_FLOW_YIELD")) | O26: =IF(A26="","",_xll.BDP(A26&" US Equity","TOT_DEBT_TO_TOT_EQY")) | P26: =IF(A26="","",_xll.BDP(A26&" US Equity","EQY_DVD_YLD_IND")) | Q26: =IF(A26="","",_xll.BDP(A26&" US Equity","BEST_CUR_EV_TO_EBITDA")) | R26: =IF(A26="","",_xll.BDP(A26&" US Equity","PX_TO_BOOK_RATIO")) | S26: =IF(A26="","",_xll.BDP(A26&" US Equity","RESEARCH_AND_DEV_TO_REVENUE")) | T26: =IF(A26="","",_xll.BDP(A26&" US Equity","REVENUE_5YR_CAGR")) | U26: =IF(A26="","",0.045+G26*0.05)
B27: =IF(A27="","",_xll.BDP(A27&" US Equity","NAME")) | C27: =IF(A27="","",_xll.BDP(A27&" US Equity","GICS_SECTOR_NAME")) | D27: =IF(A27="","",_xll.BDP(A27&" US Equity","GICS_SUB_INDUSTRY_NAME")) | E27: =IF(A27="","",_xll.BDP(A27&" US Equity","PX_LAST")) | F27: =IF(A27="","",_xll.BDP(A27&" US Equity","CUR_MKT_CAP")/1000000000) | G27: =IF(A27="","",_xll.BDP(A27&" US Equity","BETA_RAW_OVERRIDABLE")) | H27: =IF(A27="","",_xll.BDP(A27&" US Equity","BEST_PE_RATIO")) | I27: =IF(A27="","",_xll.BDP(A27&" US Equity","RETURN_ON_INV_CAPITAL")) | J27: =IF(A27="","",_xll.BDP(A27&" US Equity","RETURN_COM_EQY")) | K27: =IF(A27="","",_xll.BDP(A27&" US Equity","GROSS_MARGIN")) | L27: =IF(A27="","",_xll.BDP(A27&" US Equity","OPER_MARGIN")) | M27: =IF(A27="","",_xll.BDP(A27&" US Equity","NET_INCOME_MARGIN")) | N27: =IF(A27="","",_xll.BDP(A27&" US Equity","FREE_CASH_FLOW_YIELD")) | O27: =IF(A27="","",_xll.BDP(A27&" US Equity","TOT_DEBT_TO_TOT_EQY")) | P27: =IF(A27="","",_xll.BDP(A27&" US Equity","EQY_DVD_YLD_IND")) | Q27: =IF(A27="","",_xll.BDP(A27&" US Equity","BEST_CUR_EV_TO_EBITDA")) | R27: =IF(A27="","",_xll.BDP(A27&" US Equity","PX_TO_BOOK_RATIO")) | S27: =IF(A27="","",_xll.BDP(A27&" US Equity","RESEARCH_AND_DEV_TO_REVENUE")) | T27: =IF(A27="","",_xll.BDP(A27&" US Equity","REVENUE_5YR_CAGR")) | U27: =IF(A27="","",0.045+G27*0.05)
B28: =IF(A28="","",_xll.BDP(A28&" US Equity","NAME")) | C28: =IF(A28="","",_xll.BDP(A28&" US Equity","GICS_SECTOR_NAME")) | D28: =IF(A28="","",_xll.BDP(A28&" US Equity","GICS_SUB_INDUSTRY_NAME")) | E28: =IF(A28="","",_xll.BDP(A28&" US Equity","PX_LAST")) | F28: =IF(A28="","",_xll.BDP(A28&" US Equity","CUR_MKT_CAP")/1000000000) | G28: =IF(A28="","",_xll.BDP(A28&" US Equity","BETA_RAW_OVERRIDABLE")) | H28: =IF(A28="","",_xll.BDP(A28&" US Equity","BEST_PE_RATIO")) | I28: =IF(A28="","",_xll.BDP(A28&" US Equity","RETURN_ON_INV_CAPITAL")) | J28: =IF(A28="","",_xll.BDP(A28&" US Equity","RETURN_COM_EQY")) | K28: =IF(A28="","",_xll.BDP(A28&" US Equity","GROSS_MARGIN")) | L28: =IF(A28="","",_xll.BDP(A28&" US Equity","OPER_MARGIN")) | M28: =IF(A28="","",_xll.BDP(A28&" US Equity","NET_INCOME_MARGIN")) | N28: =IF(A28="","",_xll.BDP(A28&" US Equity","FREE_CASH_FLOW_YIELD")) | O28: =IF(A28="","",_xll.BDP(A28&" US Equity","TOT_DEBT_TO_TOT_EQY")) | P28: =IF(A28="","",_xll.BDP(A28&" US Equity","EQY_DVD_YLD_IND")) | Q28: =IF(A28="","",_xll.BDP(A28&" US Equity","BEST_CUR_EV_TO_EBITDA")) | R28: =IF(A28="","",_xll.BDP(A28&" US Equity","PX_TO_BOOK_RATIO")) | S28: =IF(A28="","",_xll.BDP(A28&" US Equity","RESEARCH_AND_DEV_TO_REVENUE")) | T28: =IF(A28="","",_xll.BDP(A28&" US Equity","REVENUE_5YR_CAGR")) | U28: =IF(A28="","",0.045+G28*0.05)
B29: =IF(A29="","",_xll.BDP(A29&" US Equity","NAME")) | C29: =IF(A29="","",_xll.BDP(A29&" US Equity","GICS_SECTOR_NAME")) | D29: =IF(A29="","",_xll.BDP(A29&" US Equity","GICS_SUB_INDUSTRY_NAME")) | E29: =IF(A29="","",_xll.BDP(A29&" US Equity","PX_LAST")) | F29: =IF(A29="","",_xll.BDP(A29&" US Equity","CUR_MKT_CAP")/1000000000) | G29: =IF(A29="","",_xll.BDP(A29&" US Equity","BETA_RAW_OVERRIDABLE")) | H29: =IF(A29="","",_xll.BDP(A29&" US Equity","BEST_PE_RATIO")) | I29: =IF(A29="","",_xll.BDP(A29&" US Equity","RETURN_ON_INV_CAPITAL")) | J29: =IF(A29="","",_xll.BDP(A29&" US Equity","RETURN_COM_EQY")) | K29: =IF(A29="","",_xll.BDP(A29&" US Equity","GROSS_MARGIN")) | L29: =IF(A29="","",_xll.BDP(A29&" US Equity","OPER_MARGIN")) | M29: =IF(A29="","",_xll.BDP(A29&" US Equity","NET_INCOME_MARGIN")) | N29: =IF(A29="","",_xll.BDP(A29&" US Equity","FREE_CASH_FLOW_YIELD")) | O29: =IF(A29="","",_xll.BDP(A29&" US Equity","TOT_DEBT_TO_TOT_EQY")) | P29: =IF(A29="","",_xll.BDP(A29&" US Equity","EQY_DVD_YLD_IND")) | Q29: =IF(A29="","",_xll.BDP(A29&" US Equity","BEST_CUR_EV_TO_EBITDA")) | R29: =IF(A29="","",_xll.BDP(A29&" US Equity","PX_TO_BOOK_RATIO")) | S29: =IF(A29="","",_xll.BDP(A29&" US Equity","RESEARCH_AND_DEV_TO_REVENUE")) | T29: =IF(A29="","",_xll.BDP(A29&" US Equity","REVENUE_5YR_CAGR")) | U29: =IF(A29="","",0.045+G29*0.05)
B30: =IF(A30="","",_xll.BDP(A30&" US Equity","NAME")) | C30: =IF(A30="","",_xll.BDP(A30&" US Equity","GICS_SECTOR_NAME")) | D30: =IF(A30="","",_xll.BDP(A30&" US Equity","GICS_SUB_INDUSTRY_NAME")) | E30: =IF(A30="","",_xll.BDP(A30&" US Equity","PX_LAST")) | F30: =IF(A30="","",_xll.BDP(A30&" US Equity","CUR_MKT_CAP")/1000000000) | G30: =IF(A30="","",_xll.BDP(A30&" US Equity","BETA_RAW_OVERRIDABLE")) | H30: =IF(A30="","",_xll.BDP(A30&" US Equity","BEST_PE_RATIO")) | I30: =IF(A30="","",_xll.BDP(A30&" US Equity","RETURN_ON_INV_CAPITAL")) | J30: =IF(A30="","",_xll.BDP(A30&" US Equity","RETURN_COM_EQY")) | K30: =IF(A30="","",_xll.BDP(A30&" US Equity","GROSS_MARGIN")) | L30: =IF(A30="","",_xll.BDP(A30&" US Equity","OPER_MARGIN")) | M30: =IF(A30="","",_xll.BDP(A30&" US Equity","NET_INCOME_MARGIN")) | N30: =IF(A30="","",_xll.BDP(A30&" US Equity","FREE_CASH_FLOW_YIELD")) | O30: =IF(A30="","",_xll.BDP(A30&" US Equity","TOT_DEBT_TO_TOT_EQY")) | P30: =IF(A30="","",_xll.BDP(A30&" US Equity","EQY_DVD_YLD_IND")) | Q30: =IF(A30="","",_xll.BDP(A30&" US Equity","BEST_CUR_EV_TO_EBITDA")) | R30: =IF(A30="","",_xll.BDP(A30&" US Equity","PX_TO_BOOK_RATIO")) | S30: =IF(A30="","",_xll.BDP(A30&" US Equity","RESEARCH_AND_DEV_TO_REVENUE")) | T30: =IF(A30="","",_xll.BDP(A30&" US Equity","REVENUE_5YR_CAGR")) | U30: =IF(A30="","",0.045+G30*0.05)
B31: =IF(A31="","",_xll.BDP(A31&" US Equity","NAME")) | C31: =IF(A31="","",_xll.BDP(A31&" US Equity","GICS_SECTOR_NAME")) | D31: =IF(A31="","",_xll.BDP(A31&" US Equity","GICS_SUB_INDUSTRY_NAME")) | E31: =IF(A31="","",_xll.BDP(A31&" US Equity","PX_LAST")) | F31: =IF(A31="","",_xll.BDP(A31&" US Equity","CUR_MKT_CAP")/1000000000) | G31: =IF(A31="","",_xll.BDP(A31&" US Equity","BETA_RAW_OVERRIDABLE")) | H31: =IF(A31="","",_xll.BDP(A31&" US Equity","BEST_PE_RATIO")) | I31: =IF(A31="","",_xll.BDP(A31&" US Equity","RETURN_ON_INV_CAPITAL")) | J31: =IF(A31="","",_xll.BDP(A31&" US Equity","RETURN_COM_EQY")) | K31: =IF(A31="","",_xll.BDP(A31&" US Equity","GROSS_MARGIN")) | L31: =IF(A31="","",_xll.BDP(A31&" US Equity","OPER_MARGIN")) | M31: =IF(A31="","",_xll.BDP(A31&" US Equity","NET_INCOME_MARGIN")) | N31: =IF(A31="","",_xll.BDP(A31&" US Equity","FREE_CASH_FLOW_YIELD")) | O31: =IF(A31="","",_xll.BDP(A31&" US Equity","TOT_DEBT_TO_TOT_EQY")) | P31: =IF(A31="","",_xll.BDP(A31&" US Equity","EQY_DVD_YLD_IND")) | Q31: =IF(A31="","",_xll.BDP(A31&" US Equity","BEST_CUR_EV_TO_EBITDA")) | R31: =IF(A31="","",_xll.BDP(A31&" US Equity","PX_TO_BOOK_RATIO")) | S31: =IF(A31="","",_xll.BDP(A31&" US Equity","RESEARCH_AND_DEV_TO_REVENUE")) | T31: =IF(A31="","",_xll.BDP(A31&" US Equity","REVENUE_5YR_CAGR")) | U31: =IF(A31="","",0.045+G31*0.05)
B32: =IF(A32="","",_xll.BDP(A32&" US Equity","NAME")) | C32: =IF(A32="","",_xll.BDP(A32&" US Equity","GICS_SECTOR_NAME")) | D32: =IF(A32="","",_xll.BDP(A32&" US Equity","GICS_SUB_INDUSTRY_NAME")) | E32: =IF(A32="","",_xll.BDP(A32&" US Equity","PX_LAST")) | F32: =IF(A32="","",_xll.BDP(A32&" US Equity","CUR_MKT_CAP")/1000000000) | G32: =IF(A32="","",_xll.BDP(A32&" US Equity","BETA_RAW_OVERRIDABLE")) | H32: =IF(A32="","",_xll.BDP(A32&" US Equity","BEST_PE_RATIO")) | I32: =IF(A32="","",_xll.BDP(A32&" US Equity","RETURN_ON_INV_CAPITAL")) | J32: =IF(A32="","",_xll.BDP(A32&" US Equity","RETURN_COM_EQY")) | K32: =IF(A32="","",_xll.BDP(A32&" US Equity","GROSS_MARGIN")) | L32: =IF(A32="","",_xll.BDP(A32&" US Equity","OPER_MARGIN")) | M32: =IF(A32="","",_xll.BDP(A32&" US Equity","NET_INCOME_MARGIN")) | N32: =IF(A32="","",_xll.BDP(A32&" US Equity","FREE_CASH_FLOW_YIELD")) | O32: =IF(A32="","",_xll.BDP(A32&" US Equity","TOT_DEBT_TO_TOT_EQY")) | P32: =IF(A32="","",_xll.BDP(A32&" US Equity","EQY_DVD_YLD_IND")) | Q32: =IF(A32="","",_xll.BDP(A32&" US Equity","BEST_CUR_EV_TO_EBITDA")) | R32: =IF(A32="","",_xll.BDP(A32&" US Equity","PX_TO_BOOK_RATIO")) | S32: =IF(A32="","",_xll.BDP(A32&" US Equity","RESEARCH_AND_DEV_TO_REVENUE")) | T32: =IF(A32="","",_xll.BDP(A32&" US Equity","REVENUE_5YR_CAGR")) | U32: =IF(A32="","",0.045+G32*0.05)
B33: =IF(A33="","",_xll.BDP(A33&" US Equity","NAME")) | C33: =IF(A33="","",_xll.BDP(A33&" US Equity","GICS_SECTOR_NAME")) | D33: =IF(A33="","",_xll.BDP(A33&" US Equity","GICS_SUB_INDUSTRY_NAME")) | E33: =IF(A33="","",_xll.BDP(A33&" US Equity","PX_LAST")) | F33: =IF(A33="","",_xll.BDP(A33&" US Equity","CUR_MKT_CAP")/1000000000) | G33: =IF(A33="","",_xll.BDP(A33&" US Equity","BETA_RAW_OVERRIDABLE")) | H33: =IF(A33="","",_xll.BDP(A33&" US Equity","BEST_PE_RATIO")) | I33: =IF(A33="","",_xll.BDP(A33&" US Equity","RETURN_ON_INV_CAPITAL")) | J33: =IF(A33="","",_xll.BDP(A33&" US Equity","RETURN_COM_EQY")) | K33: =IF(A33="","",_xll.BDP(A33&" US Equity","GROSS_MARGIN")) | L33: =IF(A33="","",_xll.BDP(A33&" US Equity","OPER_MARGIN")) | M33: =IF(A33="","",_xll.BDP(A33&" US Equity","NET_INCOME_MARGIN")) | N33: =IF(A33="","",_xll.BDP(A33&" US Equity","FREE_CASH_FLOW_YIELD")) | O33: =IF(A33="","",_xll.BDP(A33&" US Equity","TOT_DEBT_TO_TOT_EQY")) | P33: =IF(A33="","",_xll.BDP(A33&" US Equity","EQY_DVD_YLD_IND")) | Q33: =IF(A33="","",_xll.BDP(A33&" US Equity","BEST_CUR_EV_TO_EBITDA")) | R33: =IF(A33="","",_xll.BDP(A33&" US Equity","PX_TO_BOOK_RATIO")) | S33: =IF(A33="","",_xll.BDP(A33&" US Equity","RESEARCH_AND_DEV_TO_REVENUE")) | T33: =IF(A33="","",_xll.BDP(A33&" US Equity","REVENUE_5YR_CAGR")) | U33: =IF(A33="","",0.045+G33*0.05)
B34: =IF(A34="","",_xll.BDP(A34&" US Equity","NAME")) | C34: =IF(A34="","",_xll.BDP(A34&" US Equity","GICS_SECTOR_NAME")) | D34: =IF(A34="","",_xll.BDP(A34&" US Equity","GICS_SUB_INDUSTRY_NAME")) | E34: =IF(A34="","",_xll.BDP(A34&" US Equity","PX_LAST")) | F34: =IF(A34="","",_xll.BDP(A34&" US Equity","CUR_MKT_CAP")/1000000000) | G34: =IF(A34="","",_xll.BDP(A34&" US Equity","BETA_RAW_OVERRIDABLE")) | H34: =IF(A34="","",_xll.BDP(A34&" US Equity","BEST_PE_RATIO")) | I34: =IF(A34="","",_xll.BDP(A34&" US Equity","RETURN_ON_INV_CAPITAL")) | J34: =IF(A34="","",_xll.BDP(A34&" US Equity","RETURN_COM_EQY")) | K34: =IF(A34="","",_xll.BDP(A34&" US Equity","GROSS_MARGIN")) | L34: =IF(A34="","",_xll.BDP(A34&" US Equity","OPER_MARGIN")) | M34: =IF(A34="","",_xll.BDP(A34&" US Equity","NET_INCOME_MARGIN")) | N34: =IF(A34="","",_xll.BDP(A34&" US Equity","FREE_CASH_FLOW_YIELD")) | O34: =IF(A34="","",_xll.BDP(A34&" US Equity","TOT_DEBT_TO_TOT_EQY")) | P34: =IF(A34="","",_xll.BDP(A34&" US Equity","EQY_DVD_YLD_IND")) | Q34: =IF(A34="","",_xll.BDP(A34&" US Equity","BEST_CUR_EV_TO_EBITDA")) | R34: =IF(A34="","",_xll.BDP(A34&" US Equity","PX_TO_BOOK_RATIO")) | S34: =IF(A34="","",_xll.BDP(A34&" US Equity","RESEARCH_AND_DEV_TO_REVENUE")) | T34: =IF(A34="","",_xll.BDP(A34&" US Equity","REVENUE_5YR_CAGR")) | U34: =IF(A34="","",0.045+G34*0.05)
B35: =IF(A35="","",_xll.BDP(A35&" US Equity","NAME")) | C35: =IF(A35="","",_xll.BDP(A35&" US Equity","GICS_SECTOR_NAME")) | D35: =IF(A35="","",_xll.BDP(A35&" US Equity","GICS_SUB_INDUSTRY_NAME")) | E35: =IF(A35="","",_xll.BDP(A35&" US Equity","PX_LAST")) | F35: =IF(A35="","",_xll.BDP(A35&" US Equity","CUR_MKT_CAP")/1000000000) | G35: =IF(A35="","",_xll.BDP(A35&" US Equity","BETA_RAW_OVERRIDABLE")) | H35: =IF(A35="","",_xll.BDP(A35&" US Equity","BEST_PE_RATIO")) | I35: =IF(A35="","",_xll.BDP(A35&" US Equity","RETURN_ON_INV_CAPITAL")) | J35: =IF(A35="","",_xll.BDP(A35&" US Equity","RETURN_COM_EQY")) | K35: =IF(A35="","",_xll.BDP(A35&" US Equity","GROSS_MARGIN")) | L35: =IF(A35="","",_xll.BDP(A35&" US Equity","OPER_MARGIN")) | M35: =IF(A35="","",_xll.BDP(A35&" US Equity","NET_INCOME_MARGIN")) | N35: =IF(A35="","",_xll.BDP(A35&" US Equity","FREE_CASH_FLOW_YIELD")) | O35: =IF(A35="","",_xll.BDP(A35&" US Equity","TOT_DEBT_TO_TOT_EQY")) | P35: =IF(A35="","",_xll.BDP(A35&" US Equity","EQY_DVD_YLD_IND")) | Q35: =IF(A35="","",_xll.BDP(A35&" US Equity","BEST_CUR_EV_TO_EBITDA")) | R35: =IF(A35="","",_xll.BDP(A35&" US Equity","PX_TO_BOOK_RATIO")) | S35: =IF(A35="","",_xll.BDP(A35&" US Equity","RESEARCH_AND_DEV_TO_REVENUE")) | T35: =IF(A35="","",_xll.BDP(A35&" US Equity","REVENUE_5YR_CAGR")) | U35: =IF(A35="","",0.045+G35*0.05)
B36: =IF(A36="","",_xll.BDP(A36&" US Equity","NAME")) | C36: =IF(A36="","",_xll.BDP(A36&" US Equity","GICS_SECTOR_NAME")) | D36: =IF(A36="","",_xll.BDP(A36&" US Equity","GICS_SUB_INDUSTRY_NAME")) | E36: =IF(A36="","",_xll.BDP(A36&" US Equity","PX_LAST")) | F36: =IF(A36="","",_xll.BDP(A36&" US Equity","CUR_MKT_CAP")/1000000000) | G36: =IF(A36="","",_xll.BDP(A36&" US Equity","BETA_RAW_OVERRIDABLE")) | H36: =IF(A36="","",_xll.BDP(A36&" US Equity","BEST_PE_RATIO")) | I36: =IF(A36="","",_xll.BDP(A36&" US Equity","RETURN_ON_INV_CAPITAL")) | J36: =IF(A36="","",_xll.BDP(A36&" US Equity","RETURN_COM_EQY")) | K36: =IF(A36="","",_xll.BDP(A36&" US Equity","GROSS_MARGIN")) | L36: =IF(A36="","",_xll.BDP(A36&" US Equity","OPER_MARGIN")) | M36: =IF(A36="","",_xll.BDP(A36&" US Equity","NET_INCOME_MARGIN")) | N36: =IF(A36="","",_xll.BDP(A36&" US Equity","FREE_CASH_FLOW_YIELD")) | O36: =IF(A36="","",_xll.BDP(A36&" US Equity","TOT_DEBT_TO_TOT_EQY")) | P36: =IF(A36="","",_xll.BDP(A36&" US Equity","EQY_DVD_YLD_IND")) | Q36: =IF(A36="","",_xll.BDP(A36&" US Equity","BEST_CUR_EV_TO_EBITDA")) | R36: =IF(A36="","",_xll.BDP(A36&" US Equity","PX_TO_BOOK_RATIO")) | S36: =IF(A36="","",_xll.BDP(A36&" US Equity","RESEARCH_AND_DEV_TO_REVENUE")) | T36: =IF(A36="","",_xll.BDP(A36&" US Equity","REVENUE_5YR_CAGR")) | U36: =IF(A36="","",0.045+G36*0.05)
B37: =IF(A37="","",_xll.BDP(A37&" US Equity","NAME")) | C37: =IF(A37="","",_xll.BDP(A37&" US Equity","GICS_SECTOR_NAME")) | D37: =IF(A37="","",_xll.BDP(A37&" US Equity","GICS_SUB_INDUSTRY_NAME")) | E37: =IF(A37="","",_xll.BDP(A37&" US Equity","PX_LAST")) | F37: =IF(A37="","",_xll.BDP(A37&" US Equity","CUR_MKT_CAP")/1000000000) | G37: =IF(A37="","",_xll.BDP(A37&" US Equity","BETA_RAW_OVERRIDABLE")) | H37: =IF(A37="","",_xll.BDP(A37&" US Equity","BEST_PE_RATIO")) | I37: =IF(A37="","",_xll.BDP(A37&" US Equity","RETURN_ON_INV_CAPITAL")) | J37: =IF(A37="","",_xll.BDP(A37&" US Equity","RETURN_COM_EQY")) | K37: =IF(A37="","",_xll.BDP(A37&" US Equity","GROSS_MARGIN")) | L37: =IF(A37="","",_xll.BDP(A37&" US Equity","OPER_MARGIN")) | M37: =IF(A37="","",_xll.BDP(A37&" US Equity","NET_INCOME_MARGIN")) | N37: =IF(A37="","",_xll.BDP(A37&" US Equity","FREE_CASH_FLOW_YIELD")) | O37: =IF(A37="","",_xll.BDP(A37&" US Equity","TOT_DEBT_TO_TOT_EQY")) | P37: =IF(A37="","",_xll.BDP(A37&" US Equity","EQY_DVD_YLD_IND")) | Q37: =IF(A37="","",_xll.BDP(A37&" US Equity","BEST_CUR_EV_TO_EBITDA")) | R37: =IF(A37="","",_xll.BDP(A37&" US Equity","PX_TO_BOOK_RATIO")) | S37: =IF(A37="","",_xll.BDP(A37&" US Equity","RESEARCH_AND_DEV_TO_REVENUE")) | T37: =IF(A37="","",_xll.BDP(A37&" US Equity","REVENUE_5YR_CAGR")) | U37: =IF(A37="","",0.045+G37*0.05)
... B54: =IF(A54="","",_xll.BDP(A54&" US Equity","NAME")) | C54: =IF(A54="","",_xll.BDP(A54&" US Equity","GICS_SECTOR_NAME")) | D54: =IF(A54="","",_xll.BDP(A54&" US Equity","GICS_SUB_INDUSTRY_NAME")) | E54: =IF(A54="","",_xll.BDP(A54&" US Equity","PX_LAST")) | F54: =IF(A54="","",_xll.BDP(A54&" US Equity","CUR_MKT_CAP")/1000000000) | G54: =IF(A54="","",_xll.BDP(A54&" US Equity","BETA_RAW_OVERRIDABLE")) | H54: =IF(A54="","",_xll.BDP(A54&" US Equity","BEST_PE_RATIO")) | I54: =IF(A54="","",_xll.BDP(A54&" US Equity","RETURN_ON_INV_CAPITAL")) | J54: =IF(A54="","",_xll.BDP(A54&" US Equity","RETURN_COM_EQY")) | K54: =IF(A54="","",_xll.BDP(A54&" US Equity","GROSS_MARGIN")) | L54: =IF(A54="","",_xll.BDP(A54&" US Equity","OPER_MARGIN")) | M54: =IF(A54="","",_xll.BDP(A54&" US Equity","NET_INCOME_MARGIN")) | N54: =IF(A54="","",_xll.BDP(A54&" US Equity","FREE_CASH_FLOW_YIELD")) | O54: =IF(A54="","",_xll.BDP(A54&" US Equity","TOT_DEBT_TO_TOT_EQY")) | P54: =IF(A54="","",_xll.BDP(A54&" US Equity","EQY_DVD_YLD_IND")) | Q54: =IF(A54="","",_xll.BDP(A54&" US Equity","BEST_CUR_EV_TO_EBITDA")) | R54: =IF(A54="","",_xll.BDP(A54&" US Equity","PX_TO_BOOK_RATIO")) | S54: =IF(A54="","",_xll.BDP(A54&" US Equity","RESEARCH_AND_DEV_TO_REVENUE")) | T54: =IF(A54="","",_xll.BDP(A54&" US Equity","REVENUE_5YR_CAGR")) | U54: =IF(A54="","",0.045+G54*0.05)

Sheet Moat Scoring
A1: Moat & AI Risk Scoring
A2: Scores AUTO-POPULATE from sector defaults via VLOOKUP. Type over any cell to override with your own assessment. Blue cells = sector defaults; type to override.
A3: NOTE: When you add a ticker in Portfolio Input and Bloomberg fills the GICS Sector, these scores auto-fill. Override by simply typing a new value.
A4: Ticker | B4: SC (25%) | C4: NE (20%) | D4: IA (25%) | E4: CA (15%) | F4: ES (15%) | G4: Moat | H4: LS (25%) | I4: VCD (25%) | J4: DME (15%) | K4: ANC (20%) | L4: CIR (15%) | M4: AI Risk | N4: Net Moat | O4: Tier | P4: Base CAP | Q4: Adj CAP | R4: WACC+ (bp) | S4: Base P/E | T4: Adj P/E | U4: Haircut (%)
A5: ='Portfolio Input'!A5 -> AAPL | B5: =IF('Portfolio Input'!C5="","",IFERROR(VLOOKUP('Portfolio Input'!C5,'Sector Analysis'!$A$4:$O$15,2,FALSE()),"")) -> 4 | C5: =IF('Portfolio Input'!C5="","",IFERROR(VLOOKUP('Portfolio Input'!C5,'Sector Analysis'!$A$4:$O$15,3,FALSE()),"")) -> 4 | D5: =IF('Portfolio Input'!C5="","",IFERROR(VLOOKUP('Portfolio Input'!C5,'Sector Analysis'!$A$4:$O$15,4,FALSE()),"")) -> 4 | E5: =IF('Portfolio Input'!C5="","",IFERROR(VLOOKUP('Portfolio Input'!C5,'Sector Analysis'!$A$4:$O$15,5,FALSE()),"")) -> 3 | F5: =IF('Portfolio Input'!C5="","",IFERROR(VLOOKUP('Portfolio Input'!C5,'Sector Analysis'!$A$4:$O$15,6,FALSE()),"")) -> 2 | G5: =IF(A5="","",B5*0.25+C5*0.2+D5*0.25+E5*0.15+F5*0.15) -> 3.55 | H5: =IF('Portfolio Input'!C5="","",IFERROR(VLOOKUP('Portfolio Input'!C5,'Sector Analysis'!$A$4:$O$15,8,FALSE()),"")) -> 3 | I5: =IF('Portfolio Input'!C5="","",IFERROR(VLOOKUP('Portfolio Input'!C5,'Sector Analysis'!$A$4:$O$15,9,FALSE()),"")) -> 2 | J5: =IF('Portfolio Input'!C5="","",IFERROR(VLOOKUP('Portfolio Input'!C5,'Sector Analysis'!$A$4:$O$15,10,FALSE()),"")) -> 3 | K5: =IF('Portfolio Input'!C5="","",IFERROR(VLOOKUP('Portfolio Input'!C5,'Sector Analysis'!$A$4:$O$15,11,FALSE()),"")) -> 4 | L5: =IF('Portfolio Input'!C5="","",IFERROR(VLOOKUP('Portfolio Input'!C5,'Sector Analysis'!$A$4:$O$15,12,FALSE()),"")) -> 3 | M5: =IF(A5="","",H5*0.25+I5*0.25+J5*0.15+K5*0.2+L5*0.15) -> 2.95 | N5: =IF(A5="","",G5-M5) -> 0.6 | O5: =IF(A5="","",IF(N5<=-2,"CRITICAL",IF(N5<=-0.5,"HIGH",IF(N5<=0.5,"MEDIUM",IF(N5<=1.5,"LOW-MEDIUM","LOW"))))) -> LOW-MEDIUM | P5: =IF(A5="","",IF(G5>=4,22,IF(G5>=3.5,18,IF(G5>=3,14,IF(G5>=2.5,10,IF(G5>=2,7,4)))))) -> 18 | Q5: =IF(A5="","",MAX(2,ROUND(P5*(1-MAX(0,(M5-1.5)*0.15)),0))) -> 14 | R5: =IF(A5="","",MIN(400,IF(M5>=4,300,IF(M5>=3.5,225,IF(M5>=3,150,IF(M5>=2.5,100,IF(M5>=2,50,0))))))) -> 100 | S5: =IF(A5="","",IF('Portfolio Input'!U5<=0.02,30,MIN(50,MAX(5,(1/('Portfolio Input'!U5-0.02))*(1-((1.02)/(1+'Portfolio Input'!U5))^P5)+((1.02)/(1+'Portfolio Input'!U5))^P5*(1/('Portfolio Input'!U5-0.02)))))) -> 12.422963 | T5: =IF(A5="","",IF(('Portfolio Input'!U5+R5/10000)<=0.02,30,MIN(50,MAX(5,(1/(('Portfolio Input'!U5+R5/10000)-0.02))*(1-((1.02)/(1+('Portfolio Input'!U5+R5/10000)))^Q5)+((1.02)/(1+('Portfolio Input'!U5+R5/10000)))^Q5*(1/(('Portfolio Input'!U5+R5/10000)-0.02)))))) -> 11.0502 | U5: =IF(A5="","",IF(S5>0,(S5-T5)/S5*100,0)) -> 11.0502
A6: ='Portfolio Input'!A6 -> MSFT | B6: =IF('Portfolio Input'!C6="","",IFERROR(VLOOKUP('Portfolio Input'!C6,'Sector Analysis'!$A$4:$O$15,2,FALSE()),"")) -> 4 | C6: =IF('Portfolio Input'!C6="","",IFERROR(VLOOKUP('Portfolio Input'!C6,'Sector Analysis'!$A$4:$O$15,3,FALSE()),"")) -> 4 | D6: =IF('Portfolio Input'!C6="","",IFERROR(VLOOKUP('Portfolio Input'!C6,'Sector Analysis'!$A$4:$O$15,4,FALSE()),"")) -> 4 | E6: =IF('Portfolio Input'!C6="","",IFERROR(VLOOKUP('Portfolio Input'!C6,'Sector Analysis'!$A$4:$O$15,5,FALSE()),"")) -> 3 | F6: =IF('Portfolio Input'!C6="","",IFERROR(VLOOKUP('Portfolio Input'!C6,'Sector Analysis'!$A$4:$O$15,6,FALSE()),"")) -> 2 | G6: =IF(A6="","",B6*0.25+C6*0.2+D6*0.25+E6*0.15+F6*0.15) -> 3.55 | H6: =IF('Portfolio Input'!C6="","",IFERROR(VLOOKUP('Portfolio Input'!C6,'Sector Analysis'!$A$4:$O$15,8,FALSE()),"")) -> 3 | I6: =IF('Portfolio Input'!C6="","",IFERROR(VLOOKUP('Portfolio Input'!C6,'Sector Analysis'!$A$4:$O$15,9,FALSE()),"")) -> 2 | J6: =IF('Portfolio Input'!C6="","",IFERROR(VLOOKUP('Portfolio Input'!C6,'Sector Analysis'!$A$4:$O$15,10,FALSE()),"")) -> 3 | K6: =IF('Portfolio Input'!C6="","",IFERROR(VLOOKUP('Portfolio Input'!C6,'Sector Analysis'!$A$4:$O$15,11,FALSE()),"")) -> 4 | L6: =IF('Portfolio Input'!C6="","",IFERROR(VLOOKUP('Portfolio Input'!C6,'Sector Analysis'!$A$4:$O$15,12,FALSE()),"")) -> 3 | M6: =IF(A6="","",H6*0.25+I6*0.25+J6*0.15+K6*0.2+L6*0.15) -> 2.95 | N6: =IF(A6="","",G6-M6) -> 0.6 | O6: =IF(A6="","",IF(N6<=-2,"CRITICAL",IF(N6<=-0.5,"HIGH",IF(N6<=0.5,"MEDIUM",IF(N6<=1.5,"LOW-MEDIUM","LOW"))))) -> LOW-MEDIUM | P6: =IF(A6="","",IF(G6>=4,22,IF(G6>=3.5,18,IF(G6>=3,14,IF(G6>=2.5,10,IF(G6>=2,7,4)))))) -> 18 | Q6: =IF(A6="","",MAX(2,ROUND(P6*(1-MAX(0,(M6-1.5)*0.15)),0))) -> 14 | R6: =IF(A6="","",MIN(400,IF(M6>=4,300,IF(M6>=3.5,225,IF(M6>=3,150,IF(M6>=2.5,100,IF(M6>=2,50,0))))))) -> 100 | S6: =IF(A6="","",IF('Portfolio Input'!U6<=0.02,30,MIN(50,MAX(5,(1/('Portfolio Input'!U6-0.02))*(1-((1.02)/(1+'Portfolio Input'!U6))^P6)+((1.02)/(1+'Portfolio Input'!U6))^P6*(1/('Portfolio Input'!U6-0.02)))))) -> 13.128651 | T6: =IF(A6="","",IF(('Portfolio Input'!U6+R6/10000)<=0.02,30,MIN(50,MAX(5,(1/(('Portfolio Input'!U6+R6/10000)-0.02))*(1-((1.02)/(1+('Portfolio Input'!U6+R6/10000)))^Q6)+((1.02)/(1+('Portfolio Input'!U6+R6/10000)))^Q6*(1/(('Portfolio Input'!U6+R6/10000)-0.02)))))) -> 11.605063 | U6: =IF(A6="","",IF(S6>0,(S6-T6)/S6*100,0)) -> 11.605063
A7: ='Portfolio Input'!A7 -> GOOGL | B7: =IF('Portfolio Input'!C7="","",IFERROR(VLOOKUP('Portfolio Input'!C7,'Sector Analysis'!$A$4:$O$15,2,FALSE()),"")) -> 3 | C7: =IF('Portfolio Input'!C7="","",IFERROR(VLOOKUP('Portfolio Input'!C7,'Sector Analysis'!$A$4:$O$15,3,FALSE()),"")) -> 5 | D7: =IF('Portfolio Input'!C7="","",IFERROR(VLOOKUP('Portfolio Input'!C7,'Sector Analysis'!$A$4:$O$15,4,FALSE()),"")) -> 4 | E7: =IF('Portfolio Input'!C7="","",IFERROR(VLOOKUP('Portfolio Input'!C7,'Sector Analysis'!$A$4:$O$15,5,FALSE()),"")) -> 2 | F7: =IF('Portfolio Input'!C7="","",IFERROR(VLOOKUP('Portfolio Input'!C7,'Sector Analysis'!$A$4:$O$15,6,FALSE()),"")) -> 3 | G7: =IF(A7="","",B7*0.25+C7*0.2+D7*0.25+E7*0.15+F7*0.15) -> 3.5 | H7: =IF('Portfolio Input'!C7="","",IFERROR(VLOOKUP('Portfolio Input'!C7,'Sector Analysis'!$A$4:$O$15,8,FALSE()),"")) -> 3 | I7: =IF('Portfolio Input'!C7="","",IFERROR(VLOOKUP('Portfolio Input'!C7,'Sector Analysis'!$A$4:$O$15,9,FALSE()),"")) -> 3 | J7: =IF('Portfolio Input'!C7="","",IFERROR(VLOOKUP('Portfolio Input'!C7,'Sector Analysis'!$A$4:$O$15,10,FALSE()),"")) -> 4 | K7: =IF('Portfolio Input'!C7="","",IFERROR(VLOOKUP('Portfolio Input'!C7,'Sector Analysis'!$A$4:$O$15,11,FALSE()),"")) -> 3 | L7: =IF('Portfolio Input'!C7="","",IFERROR(VLOOKUP('Portfolio Input'!C7,'Sector Analysis'!$A$4:$O$15,12,FALSE()),"")) -> 4 | M7: =IF(A7="","",H7*0.25+I7*0.25+J7*0.15+K7*0.2+L7*0.15) -> 3.3 | N7: =IF(A7="","",G7-M7) -> 0.2 | O7: =IF(A7="","",IF(N7<=-2,"CRITICAL",IF(N7<=-0.5,"HIGH",IF(N7<=0.5,"MEDIUM",IF(N7<=1.5,"LOW-MEDIUM","LOW"))))) -> MEDIUM | P7: =IF(A7="","",IF(G7>=4,22,IF(G7>=3.5,18,IF(G7>=3,14,IF(G7>=2.5,10,IF(G7>=2,7,4)))))) -> 18 | Q7: =IF(A7="","",MAX(2,ROUND(P7*(1-MAX(0,(M7-1.5)*0.15)),0))) -> 13 | R7: =IF(A7="","",MIN(400,IF(M7>=4,300,IF(M7>=3.5,225,IF(M7>=3,150,IF(M7>=2.5,100,IF(M7>=2,50,0))))))) -> 150 | S7: =IF(A7="","",IF('Portfolio Input'!U7<=0.02,30,MIN(50,MAX(5,(1/('Portfolio Input'!U7-0.02))*(1-((1.02)/(1+'Portfolio Input'!U7))^P7)+((1.02)/(1+'Portfolio Input'!U7))^P7*(1/('Portfolio Input'!U7-0.02)))))) -> 12.777079 | T7: =IF(A7="","",IF(('Portfolio Input'!U7+R7/10000)<=0.02,30,MIN(50,MAX(5,(1/(('Portfolio Input'!U7+R7/10000)-0.02))*(1-((1.02)/(1+('Portfolio Input'!U7+R7/10000)))^Q7)+((1.02)/(1+('Portfolio Input'!U7+R7/10000)))^Q7*(1/(('Portfolio Input'!U7+R7/10000)-0.02)))))) -> 10.722118 | U7: =IF(A7="","",IF(S7>0,(S7-T7)/S7*100,0)) -> 16.083178
A8: ='Portfolio Input'!A8 -> NVDA | B8: =IF('Portfolio Input'!C8="","",IFERROR(VLOOKUP('Portfolio Input'!C8,'Sector Analysis'!$A$4:$O$15,2,FALSE()),"")) -> 4 | C8: =IF('Portfolio Input'!C8="","",IFERROR(VLOOKUP('Portfolio Input'!C8,'Sector Analysis'!$A$4:$O$15,3,FALSE()),"")) -> 4 | D8: =IF('Portfolio Input'!C8="","",IFERROR(VLOOKUP('Portfolio Input'!C8,'Sector Analysis'!$A$4:$O$15,4,FALSE()),"")) -> 4 | E8: =IF('Portfolio Input'!C8="","",IFERROR(VLOOKUP('Portfolio Input'!C8,'Sector Analysis'!$A$4:$O$15,5,FALSE()),"")) -> 3 | F8: =IF('Portfolio Input'!C8="","",IFERROR(VLOOKUP('Portfolio Input'!C8,'Sector Analysis'!$A$4:$O$15,6,FALSE()),"")) -> 2 | G8: =IF(A8="","",B8*0.25+C8*0.2+D8*0.25+E8*0.15+F8*0.15) -> 3.55 | H8: =IF('Portfolio Input'!C8="","",IFERROR(VLOOKUP('Portfolio Input'!C8,'Sector Analysis'!$A$4:$O$15,8,FALSE()),"")) -> 3 | I8: =IF('Portfolio Input'!C8="","",IFERROR(VLOOKUP('Portfolio Input'!C8,'Sector Analysis'!$A$4:$O$15,9,FALSE()),"")) -> 2 | J8: =IF('Portfolio Input'!C8="","",IFERROR(VLOOKUP('Portfolio Input'!C8,'Sector Analysis'!$A$4:$O$15,10,FALSE()),"")) -> 3 | K8: =IF('Portfolio Input'!C8="","",IFERROR(VLOOKUP('Portfolio Input'!C8,'Sector Analysis'!$A$4:$O$15,11,FALSE()),"")) -> 4 | L8: =IF('Portfolio Input'!C8="","",IFERROR(VLOOKUP('Portfolio Input'!C8,'Sector Analysis'!$A$4:$O$15,12,FALSE()),"")) -> 3 | M8: =IF(A8="","",H8*0.25+I8*0.25+J8*0.15+K8*0.2+L8*0.15) -> 2.95 | N8: =IF(A8="","",G8-M8) -> 0.6 | O8: =IF(A8="","",IF(N8<=-2,"CRITICAL",IF(N8<=-0.5,"HIGH",IF(N8<=0.5,"MEDIUM",IF(N8<=1.5,"LOW-MEDIUM","LOW"))))) -> LOW-MEDIUM | P8: =IF(A8="","",IF(G8>=4,22,IF(G8>=3.5,18,IF(G8>=3,14,IF(G8>=2.5,10,IF(G8>=2,7,4)))))) -> 18 | Q8: =IF(A8="","",MAX(2,ROUND(P8*(1-MAX(0,(M8-1.5)*0.15)),0))) -> 14 | R8: =IF(A8="","",MIN(400,IF(M8>=4,300,IF(M8>=3.5,225,IF(M8>=3,150,IF(M8>=2.5,100,IF(M8>=2,50,0))))))) -> 100 | S8: =IF(A8="","",IF('Portfolio Input'!U8<=0.02,30,MIN(50,MAX(5,(1/('Portfolio Input'!U8-0.02))*(1-((1.02)/(1+'Portfolio Input'!U8))^P8)+((1.02)/(1+'Portfolio Input'!U8))^P8*(1/('Portfolio Input'!U8-0.02)))))) -> 7.2339066 | T8: =IF(A8="","",IF(('Portfolio Input'!U8+R8/10000)<=0.02,30,MIN(50,MAX(5,(1/(('Portfolio Input'!U8+R8/10000)-0.02))*(1-((1.02)/(1+('Portfolio Input'!U8+R8/10000)))^Q8)+((1.02)/(1+('Portfolio Input'!U8+R8/10000)))^Q8*(1/(('Portfolio Input'!U8+R8/10000)-0.02)))))) -> 6.7459136 | U8: =IF(A8="","",IF(S8>0,(S8-T8)/S8*100,0)) -> 6.7459136
A9: ='Portfolio Input'!A9 -> AMZN | B9: =IF('Portfolio Input'!C9="","",IFERROR(VLOOKUP('Portfolio Input'!C9,'Sector Analysis'!$A$4:$O$15,2,FALSE()),"")) -> 2 | C9: =IF('Portfolio Input'!C9="","",IFERROR(VLOOKUP('Portfolio Input'!C9,'Sector Analysis'!$A$4:$O$15,3,FALSE()),"")) -> 2 | D9: =IF('Portfolio Input'!C9="","",IFERROR(VLOOKUP('Portfolio Input'!C9,'Sector Analysis'!$A$4:$O$15,4,FALSE()),"")) -> 3 | E9: =IF('Portfolio Input'!C9="","",IFERROR(VLOOKUP('Portfolio Input'!C9,'Sector Analysis'!$A$4:$O$15,5,FALSE()),"")) -> 2 | F9: =IF('Portfolio Input'!C9="","",IFERROR(VLOOKUP('Portfolio Input'!C9,'Sector Analysis'!$A$4:$O$15,6,FALSE()),"")) -> 1 | G9: =IF(A9="","",B9*0.25+C9*0.2+D9*0.25+E9*0.15+F9*0.15) -> 2.1 | H9: =IF('Portfolio Input'!C9="","",IFERROR(VLOOKUP('Portfolio Input'!C9,'Sector Analysis'!$A$4:$O$15,8,FALSE()),"")) -> 3 | I9: =IF('Portfolio Input'!C9="","",IFERROR(VLOOKUP('Portfolio Input'!C9,'Sector Analysis'!$A$4:$O$15,9,FALSE()),"")) -> 4 | J9: =IF('Portfolio Input'!C9="","",IFERROR(VLOOKUP('Portfolio Input'!C9,'Sector Analysis'!$A$4:$O$15,10,FALSE()),"")) -> 3 | K9: =IF('Portfolio Input'!C9="","",IFERROR(VLOOKUP('Portfolio Input'!C9,'Sector Analysis'!$A$4:$O$15,11,FALSE()),"")) -> 3 | L9: =IF('Portfolio Input'!C9="","",IFERROR(VLOOKUP('Portfolio Input'!C9,'Sector Analysis'!$A$4:$O$15,12,FALSE()),"")) -> 3 | M9: =IF(A9="","",H9*0.25+I9*0.25+J9*0.15+K9*0.2+L9*0.15) -> 3.25 | N9: =IF(A9="","",G9-M9) -> -1.15 | O9: =IF(A9="","",IF(N9<=-2,"CRITICAL",IF(N9<=-0.5,"HIGH",IF(N9<=0.5,"MEDIUM",IF(N9<=1.5,"LOW-MEDIUM","LOW"))))) -> HIGH | P9: =IF(A9="","",IF(G9>=4,22,IF(G9>=3.5,18,IF(G9>=3,14,IF(G9>=2.5,10,IF(G9>=2,7,4)))))) -> 7 | Q9: =IF(A9="","",MAX(2,ROUND(P9*(1-MAX(0,(M9-1.5)*0.15)),0))) -> 5 | R9: =IF(A9="","",MIN(400,IF(M9>=4,300,IF(M9>=3.5,225,IF(M9>=3,150,IF(M9>=2.5,100,IF(M9>=2,50,0))))))) -> 150 | S9: =IF(A9="","",IF('Portfolio Input'!U9<=0.02,30,MIN(50,MAX(5,(1/('Portfolio Input'!U9-0.02))*(1-((1.02)/(1+'Portfolio Input'!U9))^P9)+((1.02)/(1+'Portfolio Input'!U9))^P9*(1/('Portfolio Input'!U9-0.02)))))) -> 10.409476 | T9: =IF(A9="","",IF(('Portfolio Input'!U9+R9/10000)<=0.02,30,MIN(50,MAX(5,(1/(('Portfolio Input'!U9+R9/10000)-0.02))*(1-((1.02)/(1+('Portfolio Input'!U9+R9/10000)))^Q9)+((1.02)/(1+('Portfolio Input'!U9+R9/10000)))^Q9*(1/(('Portfolio Input'!U9+R9/10000)-0.02)))))) -> 9.0036303 | U9: =IF(A9="","",IF(S9>0,(S9-T9)/S9*100,0)) -> 13.505445
A10: ='Portfolio Input'!A10 -> META | B10: =IF('Portfolio Input'!C10="","",IFERROR(VLOOKUP('Portfolio Input'!C10,'Sector Analysis'!$A$4:$O$15,2,FALSE()),"")) -> 3 | C10: =IF('Portfolio Input'!C10="","",IFERROR(VLOOKUP('Portfolio Input'!C10,'Sector Analysis'!$A$4:$O$15,3,FALSE()),"")) -> 5 | D10: =IF('Portfolio Input'!C10="","",IFERROR(VLOOKUP('Portfolio Input'!C10,'Sector Analysis'!$A$4:$O$15,4,FALSE()),"")) -> 4 | E10: =IF('Portfolio Input'!C10="","",IFERROR(VLOOKUP('Portfolio Input'!C10,'Sector Analysis'!$A$4:$O$15,5,FALSE()),"")) -> 2 | F10: =IF('Portfolio Input'!C10="","",IFERROR(VLOOKUP('Portfolio Input'!C10,'Sector Analysis'!$A$4:$O$15,6,FALSE()),"")) -> 3 | G10: =IF(A10="","",B10*0.25+C10*0.2+D10*0.25+E10*0.15+F10*0.15) -> 3.5 | H10: =IF('Portfolio Input'!C10="","",IFERROR(VLOOKUP('Portfolio Input'!C10,'Sector Analysis'!$A$4:$O$15,8,FALSE()),"")) -> 3 | I10: =IF('Portfolio Input'!C10="","",IFERROR(VLOOKUP('Portfolio Input'!C10,'Sector Analysis'!$A$4:$O$15,9,FALSE()),"")) -> 3 | J10: =IF('Portfolio Input'!C10="","",IFERROR(VLOOKUP('Portfolio Input'!C10,'Sector Analysis'!$A$4:$O$15,10,FALSE()),"")) -> 4 | K10: =IF('Portfolio Input'!C10="","",IFERROR(VLOOKUP('Portfolio Input'!C10,'Sector Analysis'!$A$4:$O$15,11,FALSE()),"")) -> 3 | L10: =IF('Portfolio Input'!C10="","",IFERROR(VLOOKUP('Portfolio Input'!C10,'Sector Analysis'!$A$4:$O$15,12,FALSE()),"")) -> 4 | M10: =IF(A10="","",H10*0.25+I10*0.25+J10*0.15+K10*0.2+L10*0.15) -> 3.3 | N10: =IF(A10="","",G10-M10) -> 0.2 | O10: =IF(A10="","",IF(N10<=-2,"CRITICAL",IF(N10<=-0.5,"HIGH",IF(N10<=0.5,"MEDIUM",IF(N10<=1.5,"LOW-MEDIUM","LOW"))))) -> MEDIUM | P10: =IF(A10="","",IF(G10>=4,22,IF(G10>=3.5,18,IF(G10>=3,14,IF(G10>=2.5,10,IF(G10>=2,7,4)))))) -> 18 | Q10: =IF(A10="","",MAX(2,ROUND(P10*(1-MAX(0,(M10-1.5)*0.15)),0))) -> 13 | R10: =IF(A10="","",MIN(400,IF(M10>=4,300,IF(M10>=3.5,225,IF(M10>=3,150,IF(M10>=2.5,100,IF(M10>=2,50,0))))))) -> 150 | S10: =IF(A10="","",IF('Portfolio Input'!U10<=0.02,30,MIN(50,MAX(5,(1/('Portfolio Input'!U10-0.02))*(1-((1.02)/(1+'Portfolio Input'!U10))^P10)+((1.02)/(1+'Portfolio Input'!U10))^P10*(1/('Portfolio Input'!U10-0.02)))))) -> 11.192864 | T10: =IF(A10="","",IF(('Portfolio Input'!U10+R10/10000)<=0.02,30,MIN(50,MAX(5,(1/(('Portfolio Input'!U10+R10/10000)-0.02))*(1-((1.02)/(1+('Portfolio Input'!U10+R10/10000)))^Q10)+((1.02)/(1+('Portfolio Input'!U10+R10/10000)))^Q10*(1/(('Portfolio Input'!U10+R10/10000)-0.02)))))) -> 9.5838097 | U10: =IF(A10="","",IF(S10>0,(S10-T10)/S10*100,0)) -> 14.375714
A11: ='Portfolio Input'!A11 -> V | B11: =IF('Portfolio Input'!C11="","",IFERROR(VLOOKUP('Portfolio Input'!C11,'Sector Analysis'!$A$4:$O$15,2,FALSE()),"")) -> 3 | C11: =IF('Portfolio Input'!C11="","",IFERROR(VLOOKUP('Portfolio Input'!C11,'Sector Analysis'!$A$4:$O$15,3,FALSE()),"")) -> 2 | D11: =IF('Portfolio Input'!C11="","",IFERROR(VLOOKUP('Portfolio Input'!C11,'Sector Analysis'!$A$4:$O$15,4,FALSE()),"")) -> 3 | E11: =IF('Portfolio Input'!C11="","",IFERROR(VLOOKUP('Portfolio Input'!C11,'Sector Analysis'!$A$4:$O$15,5,FALSE()),"")) -> 3 | F11: =IF('Portfolio Input'!C11="","",IFERROR(VLOOKUP('Portfolio Input'!C11,'Sector Analysis'!$A$4:$O$15,6,FALSE()),"")) -> 3 | G11: =IF(A11="","",B11*0.25+C11*0.2+D11*0.25+E11*0.15+F11*0.15) -> 2.8 | H11: =IF('Portfolio Input'!C11="","",IFERROR(VLOOKUP('Portfolio Input'!C11,'Sector Analysis'!$A$4:$O$15,8,FALSE()),"")) -> 5 | I11: =IF('Portfolio Input'!C11="","",IFERROR(VLOOKUP('Portfolio Input'!C11,'Sector Analysis'!$A$4:$O$15,9,FALSE()),"")) -> 4 | J11: =IF('Portfolio Input'!C11="","",IFERROR(VLOOKUP('Portfolio Input'!C11,'Sector Analysis'!$A$4:$O$15,10,FALSE()),"")) -> 3 | K11: =IF('Portfolio Input'!C11="","",IFERROR(VLOOKUP('Portfolio Input'!C11,'Sector Analysis'!$A$4:$O$15,11,FALSE()),"")) -> 4 | L11: =IF('Portfolio Input'!C11="","",IFERROR(VLOOKUP('Portfolio Input'!C11,'Sector Analysis'!$A$4:$O$15,12,FALSE()),"")) -> 4 | M11: =IF(A11="","",H11*0.25+I11*0.25+J11*0.15+K11*0.2+L11*0.15) -> 4.1 | N11: =IF(A11="","",G11-M11) -> -1.3 | O11: =IF(A11="","",IF(N11<=-2,"CRITICAL",IF(N11<=-0.5,"HIGH",IF(N11<=0.5,"MEDIUM",IF(N11<=1.5,"LOW-MEDIUM","LOW"))))) -> HIGH | P11: =IF(A11="","",IF(G11>=4,22,IF(G11>=3.5,18,IF(G11>=3,14,IF(G11>=2.5,10,IF(G11>=2,7,4)))))) -> 10 | Q11: =IF(A11="","",MAX(2,ROUND(P11*(1-MAX(0,(M11-1.5)*0.15)),0))) -> 6 | R11: =IF(A11="","",MIN(400,IF(M11>=4,300,IF(M11>=3.5,225,IF(M11>=3,150,IF(M11>=2.5,100,IF(M11>=2,50,0))))))) -> 300 | S11: =IF(A11="","",IF('Portfolio Input'!U11<=0.02,30,MIN(50,MAX(5,(1/('Portfolio Input'!U11-0.02))*(1-((1.02)/(1+'Portfolio Input'!U11))^P11)+((1.02)/(1+'Portfolio Input'!U11))^P11*(1/('Portfolio Input'!U11-0.02)))))) -> 15.920202 | T11: =IF(A11="","",IF(('Portfolio Input'!U11+R11/10000)<=0.02,30,MIN(50,MAX(5,(1/(('Portfolio Input'!U11+R11/10000)-0.02))*(1-((1.02)/(1+('Portfolio Input'!U11+R11/10000)))^Q11)+((1.02)/(1+('Portfolio Input'!U11+R11/10000)))^Q11*(1/(('Portfolio Input'!U11+R11/10000)-0.02)))))) -> 10.774321 | U11: =IF(A11="","",IF(S11>0,(S11-T11)/S11*100,0)) -> 32.322964
A12: ='Portfolio Input'!A12 -> MA | B12: =IF('Portfolio Input'!C12="","",IFERROR(VLOOKUP('Portfolio Input'!C12,'Sector Analysis'!$A$4:$O$15,2,FALSE()),"")) -> 3 | C12: =IF('Portfolio Input'!C12="","",IFERROR(VLOOKUP('Portfolio Input'!C12,'Sector Analysis'!$A$4:$O$15,3,FALSE()),"")) -> 2 | D12: =IF('Portfolio Input'!C12="","",IFERROR(VLOOKUP('Portfolio Input'!C12,'Sector Analysis'!$A$4:$O$15,4,FALSE()),"")) -> 3 | E12: =IF('Portfolio Input'!C12="","",IFERROR(VLOOKUP('Portfolio Input'!C12,'Sector Analysis'!$A$4:$O$15,5,FALSE()),"")) -> 3 | F12: =IF('Portfolio Input'!C12="","",IFERROR(VLOOKUP('Portfolio Input'!C12,'Sector Analysis'!$A$4:$O$15,6,FALSE()),"")) -> 3 | G12: =IF(A12="","",B12*0.25+C12*0.2+D12*0.25+E12*0.15+F12*0.15) -> 2.8 | H12: =IF('Portfolio Input'!C12="","",IFERROR(VLOOKUP('Portfolio Input'!C12,'Sector Analysis'!$A$4:$O$15,8,FALSE()),"")) -> 5 | I12: =IF('Portfolio Input'!C12="","",IFERROR(VLOOKUP('Portfolio Input'!C12,'Sector Analysis'!$A$4:$O$15,9,FALSE()),"")) -> 4 | J12: =IF('Portfolio Input'!C12="","",IFERROR(VLOOKUP('Portfolio Input'!C12,'Sector Analysis'!$A$4:$O$15,10,FALSE()),"")) -> 3 | K12: =IF('Portfolio Input'!C12="","",IFERROR(VLOOKUP('Portfolio Input'!C12,'Sector Analysis'!$A$4:$O$15,11,FALSE()),"")) -> 4 | L12: =IF('Portfolio Input'!C12="","",IFERROR(VLOOKUP('Portfolio Input'!C12,'Sector Analysis'!$A$4:$O$15,12,FALSE()),"")) -> 4 | M12: =IF(A12="","",H12*0.25+I12*0.25+J12*0.15+K12*0.2+L12*0.15) -> 4.1 | N12: =IF(A12="","",G12-M12) -> -1.3 | O12: =IF(A12="","",IF(N12<=-2,"CRITICAL",IF(N12<=-0.5,"HIGH",IF(N12<=0.5,"MEDIUM",IF(N12<=1.5,"LOW-MEDIUM","LOW"))))) -> HIGH | P12: =IF(A12="","",IF(G12>=4,22,IF(G12>=3.5,18,IF(G12>=3,14,IF(G12>=2.5,10,IF(G12>=2,7,4)))))) -> 10 | Q12: =IF(A12="","",MAX(2,ROUND(P12*(1-MAX(0,(M12-1.5)*0.15)),0))) -> 6 | R12: =IF(A12="","",MIN(400,IF(M12>=4,300,IF(M12>=3.5,225,IF(M12>=3,150,IF(M12>=2.5,100,IF(M12>=2,50,0))))))) -> 300 | S12: =IF(A12="","",IF('Portfolio Input'!U12<=0.02,30,MIN(50,MAX(5,(1/('Portfolio Input'!U12-0.02))*(1-((1.02)/(1+'Portfolio Input'!U12))^P12)+((1.02)/(1+'Portfolio Input'!U12))^P12*(1/('Portfolio Input'!U12-0.02)))))) -> 15.560357 | T12: =IF(A12="","",IF(('Portfolio Input'!U12+R12/10000)<=0.02,30,MIN(50,MAX(5,(1/(('Portfolio Input'!U12+R12/10000)-0.02))*(1-((1.02)/(1+('Portfolio Input'!U12+R12/10000)))^Q12)+((1.02)/(1+('Portfolio Input'!U12+R12/10000)))^Q12*(1/(('Portfolio Input'!U12+R12/10000)-0.02)))))) -> 10.608293 | U12: =IF(A12="","",IF(S12>0,(S12-T12)/S12*100,0)) -> 31.824878
A13: ='Portfolio Input'!A13 -> ACN | B13: =IF('Portfolio Input'!C13="","",IFERROR(VLOOKUP('Portfolio Input'!C13,'Sector Analysis'!$A$4:$O$15,2,FALSE()),"")) -> 4 | C13: =IF('Portfolio Input'!C13="","",IFERROR(VLOOKUP('Portfolio Input'!C13,'Sector Analysis'!$A$4:$O$15,3,FALSE()),"")) -> 4 | D13: =IF('Portfolio Input'!C13="","",IFERROR(VLOOKUP('Portfolio Input'!C13,'Sector Analysis'!$A$4:$O$15,4,FALSE()),"")) -> 4 | E13: =IF('Portfolio Input'!C13="","",IFERROR(VLOOKUP('Portfolio Input'!C13,'Sector Analysis'!$A$4:$O$15,5,FALSE()),"")) -> 3 | F13: =IF('Portfolio Input'!C13="","",IFERROR(VLOOKUP('Portfolio Input'!C13,'Sector Analysis'!$A$4:$O$15,6,FALSE()),"")) -> 2 | G13: =IF(A13="","",B13*0.25+C13*0.2+D13*0.25+E13*0.15+F13*0.15) -> 3.55 | H13: =IF('Portfolio Input'!C13="","",IFERROR(VLOOKUP('Portfolio Input'!C13,'Sector Analysis'!$A$4:$O$15,8,FALSE()),"")) -> 3 | I13: =IF('Portfolio Input'!C13="","",IFERROR(VLOOKUP('Portfolio Input'!C13,'Sector Analysis'!$A$4:$O$15,9,FALSE()),"")) -> 2 | J13: =IF('Portfolio Input'!C13="","",IFERROR(VLOOKUP('Portfolio Input'!C13,'Sector Analysis'!$A$4:$O$15,10,FALSE()),"")) -> 3 | K13: =IF('Portfolio Input'!C13="","",IFERROR(VLOOKUP('Portfolio Input'!C13,'Sector Analysis'!$A$4:$O$15,11,FALSE()),"")) -> 4 | L13: =IF('Portfolio Input'!C13="","",IFERROR(VLOOKUP('Portfolio Input'!C13,'Sector Analysis'!$A$4:$O$15,12,FALSE()),"")) -> 3 | M13: =IF(A13="","",H13*0.25+I13*0.25+J13*0.15+K13*0.2+L13*0.15) -> 2.95 | N13: =IF(A13="","",G13-M13) -> 0.6 | O13: =IF(A13="","",IF(N13<=-2,"CRITICAL",IF(N13<=-0.5,"HIGH",IF(N13<=0.5,"MEDIUM",IF(N13<=1.5,"LOW-MEDIUM","LOW"))))) -> LOW-MEDIUM | P13: =IF(A13="","",IF(G13>=4,22,IF(G13>=3.5,18,IF(G13>=3,14,IF(G13>=2.5,10,IF(G13>=2,7,4)))))) -> 18 | Q13: =IF(A13="","",MAX(2,ROUND(P13*(1-MAX(0,(M13-1.5)*0.15)),0))) -> 14 | R13: =IF(A13="","",MIN(400,IF(M13>=4,300,IF(M13>=3.5,225,IF(M13>=3,150,IF(M13>=2.5,100,IF(M13>=2,50,0))))))) -> 100 | S13: =IF(A13="","",IF('Portfolio Input'!U13<=0.02,30,MIN(50,MAX(5,(1/('Portfolio Input'!U13-0.02))*(1-((1.02)/(1+'Portfolio Input'!U13))^P13)+((1.02)/(1+'Portfolio Input'!U13))^P13*(1/('Portfolio Input'!U13-0.02)))))) -> 18.14123 | T13: =IF(A13="","",IF(('Portfolio Input'!U13+R13/10000)<=0.02,30,MIN(50,MAX(5,(1/(('Portfolio Input'!U13+R13/10000)-0.02))*(1-((1.02)/(1+('Portfolio Input'!U13+R13/10000)))^Q13)+((1.02)/(1+('Portfolio Input'!U13+R13/10000)))^Q13*(1/(('Portfolio Input'!U13+R13/10000)-0.02)))))) -> 15.355545 | U13: =IF(A13="","",IF(S13>0,(S13-T13)/S13*100,0)) -> 15.355545
A14: ='Portfolio Input'!A14 -> CRM | B14: =IF('Portfolio Input'!C14="","",IFERROR(VLOOKUP('Portfolio Input'!C14,'Sector Analysis'!$A$4:$O$15,2,FALSE()),"")) -> 4 | C14: =IF('Portfolio Input'!C14="","",IFERROR(VLOOKUP('Portfolio Input'!C14,'Sector Analysis'!$A$4:$O$15,3,FALSE()),"")) -> 4 | D14: =IF('Portfolio Input'!C14="","",IFERROR(VLOOKUP('Portfolio Input'!C14,'Sector Analysis'!$A$4:$O$15,4,FALSE()),"")) -> 4 | E14: =IF('Portfolio Input'!C14="","",IFERROR(VLOOKUP('Portfolio Input'!C14,'Sector Analysis'!$A$4:$O$15,5,FALSE()),"")) -> 3 | F14: =IF('Portfolio Input'!C14="","",IFERROR(VLOOKUP('Portfolio Input'!C14,'Sector Analysis'!$A$4:$O$15,6,FALSE()),"")) -> 2 | G14: =IF(A14="","",B14*0.25+C14*0.2+D14*0.25+E14*0.15+F14*0.15) -> 3.55 | H14: =IF('Portfolio Input'!C14="","",IFERROR(VLOOKUP('Portfolio Input'!C14,'Sector Analysis'!$A$4:$O$15,8,FALSE()),"")) -> 3 | I14: =IF('Portfolio Input'!C14="","",IFERROR(VLOOKUP('Portfolio Input'!C14,'Sector Analysis'!$A$4:$O$15,9,FALSE()),"")) -> 2 | J14: =IF('Portfolio Input'!C14="","",IFERROR(VLOOKUP('Portfolio Input'!C14,'Sector Analysis'!$A$4:$O$15,10,FALSE()),"")) -> 3 | K14: =IF('Portfolio Input'!C14="","",IFERROR(VLOOKUP('Portfolio Input'!C14,'Sector Analysis'!$A$4:$O$15,11,FALSE()),"")) -> 4 | L14: =IF('Portfolio Input'!C14="","",IFERROR(VLOOKUP('Portfolio Input'!C14,'Sector Analysis'!$A$4:$O$15,12,FALSE()),"")) -> 3 | M14: =IF(A14="","",H14*0.25+I14*0.25+J14*0.15+K14*0.2+L14*0.15) -> 2.95 | N14: =IF(A14="","",G14-M14) -> 0.6 | O14: =IF(A14="","",IF(N14<=-2,"CRITICAL",IF(N14<=-0.5,"HIGH",IF(N14<=0.5,"MEDIUM",IF(N14<=1.5,"LOW-MEDIUM","LOW"))))) -> LOW-MEDIUM | P14: =IF(A14="","",IF(G14>=4,22,IF(G14>=3.5,18,IF(G14>=3,14,IF(G14>=2.5,10,IF(G14>=2,7,4)))))) -> 18 | Q14: =IF(A14="","",MAX(2,ROUND(P14*(1-MAX(0,(M14-1.5)*0.15)),0))) -> 14 | R14: =IF(A14="","",MIN(400,IF(M14>=4,300,IF(M14>=3.5,225,IF(M14>=3,150,IF(M14>=2.5,100,IF(M14>=2,50,0))))))) -> 100 | S14: =IF(A14="","",IF('Portfolio Input'!U14<=0.02,30,MIN(50,MAX(5,(1/('Portfolio Input'!U14-0.02))*(1-((1.02)/(1+'Portfolio Input'!U14))^P14)+((1.02)/(1+'Portfolio Input'!U14))^P14*(1/('Portfolio Input'!U14-0.02)))))) -> 10.900632 | T14: =IF(A14="","",IF(('Portfolio Input'!U14+R14/10000)<=0.02,30,MIN(50,MAX(5,(1/(('Portfolio Input'!U14+R14/10000)-0.02))*(1-((1.02)/(1+('Portfolio Input'!U14+R14/10000)))^Q14)+((1.02)/(1+('Portfolio Input'!U14+R14/10000)))^Q14*(1/(('Portfolio Input'!U14+R14/10000)-0.02)))))) -> 9.8291885 | U14: =IF(A14="","",IF(S14>0,(S14-T14)/S14*100,0)) -> 9.8291885
A15: ='Portfolio Input'!A15 -> ADBE | B15: =IF('Portfolio Input'!C15="","",IFERROR(VLOOKUP('Portfolio Input'!C15,'Sector Analysis'!$A$4:$O$15,2,FALSE()),"")) -> 4 | C15: =IF('Portfolio Input'!C15="","",IFERROR(VLOOKUP('Portfolio Input'!C15,'Sector Analysis'!$A$4:$O$15,3,FALSE()),"")) -> 4 | D15: =IF('Portfolio Input'!C15="","",IFERROR(VLOOKUP('Portfolio Input'!C15,'Sector Analysis'!$A$4:$O$15,4,FALSE()),"")) -> 4 | E15: =IF('Portfolio Input'!C15="","",IFERROR(VLOOKUP('Portfolio Input'!C15,'Sector Analysis'!$A$4:$O$15,5,FALSE()),"")) -> 3 | F15: =IF('Portfolio Input'!C15="","",IFERROR(VLOOKUP('Portfolio Input'!C15,'Sector Analysis'!$A$4:$O$15,6,FALSE()),"")) -> 2 | G15: =IF(A15="","",B15*0.25+C15*0.2+D15*0.25+E15*0.15+F15*0.15) -> 3.55 | H15: =IF('Portfolio Input'!C15="","",IFERROR(VLOOKUP('Portfolio Input'!C15,'Sector Analysis'!$A$4:$O$15,8,FALSE()),"")) -> 3 | I15: =IF('Portfolio Input'!C15="","",IFERROR(VLOOKUP('Portfolio Input'!C15,'Sector Analysis'!$A$4:$O$15,9,FALSE()),"")) -> 2 | J15: =IF('Portfolio Input'!C15="","",IFERROR(VLOOKUP('Portfolio Input'!C15,'Sector Analysis'!$A$4:$O$15,10,FALSE()),"")) -> 3 | K15: =IF('Portfolio Input'!C15="","",IFERROR(VLOOKUP('Portfolio Input'!C15,'Sector Analysis'!$A$4:$O$15,11,FALSE()),"")) -> 4 | L15: =IF('Portfolio Input'!C15="","",IFERROR(VLOOKUP('Portfolio Input'!C15,'Sector Analysis'!$A$4:$O$15,12,FALSE()),"")) -> 3 | M15: =IF(A15="","",H15*0.25+I15*0.25+J15*0.15+K15*0.2+L15*0.15) -> 2.95 | N15: =IF(A15="","",G15-M15) -> 0.6 | O15: =IF(A15="","",IF(N15<=-2,"CRITICAL",IF(N15<=-0.5,"HIGH",IF(N15<=0.5,"MEDIUM",IF(N15<=1.5,"LOW-MEDIUM","LOW"))))) -> LOW-MEDIUM | P15: =IF(A15="","",IF(G15>=4,22,IF(G15>=3.5,18,IF(G15>=3,14,IF(G15>=2.5,10,IF(G15>=2,7,4)))))) -> 18 | Q15: =IF(A15="","",MAX(2,ROUND(P15*(1-MAX(0,(M15-1.5)*0.15)),0))) -> 14 | R15: =IF(A15="","",MIN(400,IF(M15>=4,300,IF(M15>=3.5,225,IF(M15>=3,150,IF(M15>=2.5,100,IF(M15>=2,50,0))))))) -> 100 | S15: =IF(A15="","",IF('Portfolio Input'!U15<=0.02,30,MIN(50,MAX(5,(1/('Portfolio Input'!U15-0.02))*(1-((1.02)/(1+'Portfolio Input'!U15))^P15)+((1.02)/(1+'Portfolio Input'!U15))^P15*(1/('Portfolio Input'!U15-0.02)))))) -> 13.264089 | T15: =IF(A15="","",IF(('Portfolio Input'!U15+R15/10000)<=0.02,30,MIN(50,MAX(5,(1/(('Portfolio Input'!U15+R15/10000)-0.02))*(1-((1.02)/(1+('Portfolio Input'!U15+R15/10000)))^Q15)+((1.02)/(1+('Portfolio Input'!U15+R15/10000)))^Q15*(1/(('Portfolio Input'!U15+R15/10000)-0.02)))))) -> 11.710763 | U15: =IF(A15="","",IF(S15>0,(S15-T15)/S15*100,0)) -> 11.710763
A16: ='Portfolio Input'!A16 -> NOW | B16: =IF('Portfolio Input'!C16="","",IFERROR(VLOOKUP('Portfolio Input'!C16,'Sector Analysis'!$A$4:$O$15,2,FALSE()),"")) -> 4 | C16: =IF('Portfolio Input'!C16="","",IFERROR(VLOOKUP('Portfolio Input'!C16,'Sector Analysis'!$A$4:$O$15,3,FALSE()),"")) -> 4 | D16: =IF('Portfolio Input'!C16="","",IFERROR(VLOOKUP('Portfolio Input'!C16,'Sector Analysis'!$A$4:$O$15,4,FALSE()),"")) -> 4 | E16: =IF('Portfolio Input'!C16="","",IFERROR(VLOOKUP('Portfolio Input'!C16,'Sector Analysis'!$A$4:$O$15,5,FALSE()),"")) -> 3 | F16: =IF('Portfolio Input'!C16="","",IFERROR(VLOOKUP('Portfolio Input'!C16,'Sector Analysis'!$A$4:$O$15,6,FALSE()),"")) -> 2 | G16: =IF(A16="","",B16*0.25+C16*0.2+D16*0.25+E16*0.15+F16*0.15) -> 3.55 | H16: =IF('Portfolio Input'!C16="","",IFERROR(VLOOKUP('Portfolio Input'!C16,'Sector Analysis'!$A$4:$O$15,8,FALSE()),"")) -> 3 | I16: =IF('Portfolio Input'!C16="","",IFERROR(VLOOKUP('Portfolio Input'!C16,'Sector Analysis'!$A$4:$O$15,9,FALSE()),"")) -> 2 | J16: =IF('Portfolio Input'!C16="","",IFERROR(VLOOKUP('Portfolio Input'!C16,'Sector Analysis'!$A$4:$O$15,10,FALSE()),"")) -> 3 | K16: =IF('Portfolio Input'!C16="","",IFERROR(VLOOKUP('Portfolio Input'!C16,'Sector Analysis'!$A$4:$O$15,11,FALSE()),"")) -> 4 | L16: =IF('Portfolio Input'!C16="","",IFERROR(VLOOKUP('Portfolio Input'!C16,'Sector Analysis'!$A$4:$O$15,12,FALSE()),"")) -> 3 | M16: =IF(A16="","",H16*0.25+I16*0.25+J16*0.15+K16*0.2+L16*0.15) -> 2.95 | N16: =IF(A16="","",G16-M16) -> 0.6 | O16: =IF(A16="","",IF(N16<=-2,"CRITICAL",IF(N16<=-0.5,"HIGH",IF(N16<=0.5,"MEDIUM",IF(N16<=1.5,"LOW-MEDIUM","LOW"))))) -> LOW-MEDIUM | P16: =IF(A16="","",IF(G16>=4,22,IF(G16>=3.5,18,IF(G16>=3,14,IF(G16>=2.5,10,IF(G16>=2,7,4)))))) -> 18 | Q16: =IF(A16="","",MAX(2,ROUND(P16*(1-MAX(0,(M16-1.5)*0.15)),0))) -> 14 | R16: =IF(A16="","",MIN(400,IF(M16>=4,300,IF(M16>=3.5,225,IF(M16>=3,150,IF(M16>=2.5,100,IF(M16>=2,50,0))))))) -> 100 | S16: =IF(A16="","",IF('Portfolio Input'!U16<=0.02,30,MIN(50,MAX(5,(1/('Portfolio Input'!U16-0.02))*(1-((1.02)/(1+'Portfolio Input'!U16))^P16)+((1.02)/(1+'Portfolio Input'!U16))^P16*(1/('Portfolio Input'!U16-0.02)))))) -> 10.476765 | T16: =IF(A16="","",IF(('Portfolio Input'!U16+R16/10000)<=0.02,30,MIN(50,MAX(5,(1/(('Portfolio Input'!U16+R16/10000)-0.02))*(1-((1.02)/(1+('Portfolio Input'!U16+R16/10000)))^Q16)+((1.02)/(1+('Portfolio Input'!U16+R16/10000)))^Q16*(1/(('Portfolio Input'!U16+R16/10000)-0.02)))))) -> 9.4832294 | U16: =IF(A16="","",IF(S16>0,(S16-T16)/S16*100,0)) -> 9.4832294
... A24: ='Portfolio Input'!A24 -> NEE | B24: =IF('Portfolio Input'!C24="","",IFERROR(VLOOKUP('Portfolio Input'!C24,'Sector Analysis'!$A$4:$O$15,2,FALSE()),"")) -> 2 | C24: =IF('Portfolio Input'!C24="","",IFERROR(VLOOKUP('Portfolio Input'!C24,'Sector Analysis'!$A$4:$O$15,3,FALSE()),"")) -> 1 | D24: =IF('Portfolio Input'!C24="","",IFERROR(VLOOKUP('Portfolio Input'!C24,'Sector Analysis'!$A$4:$O$15,4,FALSE()),"")) -> 3 | E24: =IF('Portfolio Input'!C24="","",IFERROR(VLOOKUP('Portfolio Input'!C24,'Sector Analysis'!$A$4:$O$15,5,FALSE()),"")) -> 3 | F24: =IF('Portfolio Input'!C24="","",IFERROR(VLOOKUP('Portfolio Input'!C24,'Sector Analysis'!$A$4:$O$15,6,FALSE()),"")) -> 5 | G24: =IF(A24="","",B24*0.25+C24*0.2+D24*0.25+E24*0.15+F24*0.15) -> 2.65 | H24: =IF('Portfolio Input'!C24="","",IFERROR(VLOOKUP('Portfolio Input'!C24,'Sector Analysis'!$A$4:$O$15,8,FALSE()),"")) -> 1 | I24: =IF('Portfolio Input'!C24="","",IFERROR(VLOOKUP('Portfolio Input'!C24,'Sector Analysis'!$A$4:$O$15,9,FALSE()),"")) -> 1 | J24: =IF('Portfolio Input'!C24="","",IFERROR(VLOOKUP('Portfolio Input'!C24,'Sector Analysis'!$A$4:$O$15,10,FALSE()),"")) -> 1 | K24: =IF('Portfolio Input'!C24="","",IFERROR(VLOOKUP('Portfolio Input'!C24,'Sector Analysis'!$A$4:$O$15,11,FALSE()),"")) -> 1 | L24: =IF('Portfolio Input'!C24="","",IFERROR(VLOOKUP('Portfolio Input'!C24,'Sector Analysis'!$A$4:$O$15,12,FALSE()),"")) -> 1 | M24: =IF(A24="","",H24*0.25+I24*0.25+J24*0.15+K24*0.2+L24*0.15) -> 1 | N24: =IF(A24="","",G24-M24) -> 1.65 | O24: =IF(A24="","",IF(N24<=-2,"CRITICAL",IF(N24<=-0.5,"HIGH",IF(N24<=0.5,"MEDIUM",IF(N24<=1.5,"LOW-MEDIUM","LOW"))))) -> LOW | P24: =IF(A24="","",IF(G24>=4,22,IF(G24>=3.5,18,IF(G24>=3,14,IF(G24>=2.5,10,IF(G24>=2,7,4)))))) -> 10 | Q24: =IF(A24="","",MAX(2,ROUND(P24*(1-MAX(0,(M24-1.5)*0.15)),0))) -> 10 | R24: =IF(A24="","",MIN(400,IF(M24>=4,300,IF(M24>=3.5,225,IF(M24>=3,150,IF(M24>=2.5,100,IF(M24>=2,50,0))))))) -> 0 | S24: =IF(A24="","",IF('Portfolio Input'!U24<=0.02,30,MIN(50,MAX(5,(1/('Portfolio Input'!U24-0.02))*(1-((1.02)/(1+'Portfolio Input'!U24))^P24)+((1.02)/(1+'Portfolio Input'!U24))^P24*(1/('Portfolio Input'!U24-0.02)))))) -> 22.638433 | T24: =IF(A24="","",IF(('Portfolio Input'!U24+R24/10000)<=0.02,30,MIN(50,MAX(5,(1/(('Portfolio Input'!U24+R24/10000)-0.02))*(1-((1.02)/(1+('Portfolio Input'!U24+R24/10000)))^Q24)+((1.02)/(1+('Portfolio Input'!U24+R24/10000)))^Q24*(1/(('Portfolio Input'!U24+R24/10000)-0.02)))))) -> 22.638433 | U24: =IF(A24="","",IF(S24>0,(S24-T24)/S24*100,0)) -> 0
A25: ='Portfolio Input'!A25 -> GAP | B25: =IF('Portfolio Input'!C25="","",IFERROR(VLOOKUP('Portfolio Input'!C25,'Sector Analysis'!$A$4:$O$15,2,FALSE()),"")) -> 2 | C25: =IF('Portfolio Input'!C25="","",IFERROR(VLOOKUP('Portfolio Input'!C25,'Sector Analysis'!$A$4:$O$15,3,FALSE()),"")) -> 2 | D25: =IF('Portfolio Input'!C25="","",IFERROR(VLOOKUP('Portfolio Input'!C25,'Sector Analysis'!$A$4:$O$15,4,FALSE()),"")) -> 3 | E25: =IF('Portfolio Input'!C25="","",IFERROR(VLOOKUP('Portfolio Input'!C25,'Sector Analysis'!$A$4:$O$15,5,FALSE()),"")) -> 2 | F25: =IF('Portfolio Input'!C25="","",IFERROR(VLOOKUP('Portfolio Input'!C25,'Sector Analysis'!$A$4:$O$15,6,FALSE()),"")) -> 1 | G25: =IF(OR(A25="", A25=0),"",B25*0.25+C25*0.2+D25*0.25+E25*0.15+F25*0.15) -> 2.1 | H25: =IF('Portfolio Input'!C25="","",IFERROR(VLOOKUP('Portfolio Input'!C25,'Sector Analysis'!$A$4:$O$15,8,FALSE()),"")) -> 3 | I25: =IF('Portfolio Input'!C25="","",IFERROR(VLOOKUP('Portfolio Input'!C25,'Sector Analysis'!$A$4:$O$15,9,FALSE()),"")) -> 4 | J25: =IF('Portfolio Input'!C25="","",IFERROR(VLOOKUP('Portfolio Input'!C25,'Sector Analysis'!$A$4:$O$15,10,FALSE()),"")) -> 3 | K25: =IF('Portfolio Input'!C25="","",IFERROR(VLOOKUP('Portfolio Input'!C25,'Sector Analysis'!$A$4:$O$15,11,FALSE()),"")) -> 3 | L25: =IF('Portfolio Input'!C25="","",IFERROR(VLOOKUP('Portfolio Input'!C25,'Sector Analysis'!$A$4:$O$15,12,FALSE()),"")) -> 3 | M25: =IF(A25="","",H25*0.25+I25*0.25+J25*0.15+K25*0.2+L25*0.15) -> 3.25 | N25: =IF(A25="","",G25-M25) -> -1.15 | O25: =IF(A25="","",IF(N25<=-2,"CRITICAL",IF(N25<=-0.5,"HIGH",IF(N25<=0.5,"MEDIUM",IF(N25<=1.5,"LOW-MEDIUM","LOW"))))) -> HIGH | P25: =IF(A25="","",IF(G25>=4,22,IF(G25>=3.5,18,IF(G25>=3,14,IF(G25>=2.5,10,IF(G25>=2,7,4)))))) -> 7 | Q25: =IF(A25="","",MAX(2,ROUND(P25*(1-MAX(0,(M25-1.5)*0.15)),0))) -> 5 | R25: =IF(A25="","",MIN(400,IF(M25>=4,300,IF(M25>=3.5,225,IF(M25>=3,150,IF(M25>=2.5,100,IF(M25>=2,50,0))))))) -> 150 | S25: =IF(A25="","",IF('Portfolio Input'!U25<=0.02,30,MIN(50,MAX(5,(1/('Portfolio Input'!U25-0.02))*(1-((1.02)/(1+'Portfolio Input'!U25))^P25)+((1.02)/(1+'Portfolio Input'!U25))^P25*(1/('Portfolio Input'!U25-0.02)))))) -> 11.497744 | T25: =IF(A25="","",IF(('Portfolio Input'!U25+R25/10000)<=0.02,30,MIN(50,MAX(5,(1/(('Portfolio Input'!U25+R25/10000)-0.02))*(1-((1.02)/(1+('Portfolio Input'!U25+R25/10000)))^Q25)+((1.02)/(1+('Portfolio Input'!U25+R25/10000)))^Q25*(1/(('Portfolio Input'!U25+R25/10000)-0.02)))))) -> 9.8064609 | U25: =IF(A25="","",IF(S25>0,(S25-T25)/S25*100,0)) -> 14.709691
A26: ='Portfolio Input'!A26 -> 0 | B26: =IF('Portfolio Input'!C26="","",IFERROR(VLOOKUP('Portfolio Input'!C26,'Sector Analysis'!$A$4:$O$15,2,FALSE()),"")) | C26: =IF('Portfolio Input'!C26="","",IFERROR(VLOOKUP('Portfolio Input'!C26,'Sector Analysis'!$A$4:$O$15,3,FALSE()),"")) | D26: =IF('Portfolio Input'!C26="","",IFERROR(VLOOKUP('Portfolio Input'!C26,'Sector Analysis'!$A$4:$O$15,4,FALSE()),"")) | E26: =IF('Portfolio Input'!C26="","",IFERROR(VLOOKUP('Portfolio Input'!C26,'Sector Analysis'!$A$4:$O$15,5,FALSE()),"")) | F26: =IF('Portfolio Input'!C26="","",IFERROR(VLOOKUP('Portfolio Input'!C26,'Sector Analysis'!$A$4:$O$15,6,FALSE()),"")) | G26: =IF(OR(A26="", A26=0),"",B26*0.25+C26*0.2+D26*0.25+E26*0.15+F26*0.15) | H26: =IF('Portfolio Input'!C26="","",IFERROR(VLOOKUP('Portfolio Input'!C26,'Sector Analysis'!$A$4:$O$15,8,FALSE()),"")) | I26: =IF('Portfolio Input'!C26="","",IFERROR(VLOOKUP('Portfolio Input'!C26,'Sector Analysis'!$A$4:$O$15,9,FALSE()),"")) | J26: =IF('Portfolio Input'!C26="","",IFERROR(VLOOKUP('Portfolio Input'!C26,'Sector Analysis'!$A$4:$O$15,10,FALSE()),"")) | K26: =IF('Portfolio Input'!C26="","",IFERROR(VLOOKUP('Portfolio Input'!C26,'Sector Analysis'!$A$4:$O$15,11,FALSE()),"")) | L26: =IF('Portfolio Input'!C26="","",IFERROR(VLOOKUP('Portfolio Input'!C26,'Sector Analysis'!$A$4:$O$15,12,FALSE()),"")) | M26: =IF(A26="","",H26*0.25+I26*0.25+J26*0.15+K26*0.2+L26*0.15) -> #VALUE! | N26: =IF(A26="","",G26-M26) -> #VALUE! | O26: =IF(A26="","",IF(N26<=-2,"CRITICAL",IF(N26<=-0.5,"HIGH",IF(N26<=0.5,"MEDIUM",IF(N26<=1.5,"LOW-MEDIUM","LOW"))))) -> #VALUE! | P26: =IF(A26="","",IF(G26>=4,22,IF(G26>=3.5,18,IF(G26>=3,14,IF(G26>=2.5,10,IF(G26>=2,7,4)))))) -> 22 | Q26: =IF(A26="","",MAX(2,ROUND(P26*(1-MAX(0,(M26-1.5)*0.15)),0))) -> #VALUE! | R26: =IF(A26="","",MIN(400,IF(M26>=4,300,IF(M26>=3.5,225,IF(M26>=3,150,IF(M26>=2.5,100,IF(M26>=2,50,0))))))) -> #VALUE! | S26: =IF(A26="","",IF('Portfolio Input'!U26<=0.02,30,MIN(50,MAX(5,(1/('Portfolio Input'!U26-0.02))*(1-((1.02)/(1+'Portfolio Input'!U26))^P26)+((1.02)/(1+'Portfolio Input'!U26))^P26*(1/('Portfolio Input'!U26-0.02)))))) -> #VALUE! | T26: =IF(A26="","",IF(('Portfolio Input'!U26+R26/10000)<=0.02,30,MIN(50,MAX(5,(1/(('Portfolio Input'!U26+R26/10000)-0.02))*(1-((1.02)/(1+('Portfolio Input'!U26+R26/10000)))^Q26)+((1.02)/(1+('Portfolio Input'!U26+R26/10000)))^Q26*(1/(('Portfolio Input'!U26+R26/10000)-0.02)))))) -> #VALUE! | U26: =IF(A26="","",IF(S26>0,(S26-T26)/S26*100,0)) -> #VALUE!
A27: ='Portfolio Input'!A27 -> 0 | B27: =IF('Portfolio Input'!C27="","",IFERROR(VLOOKUP('Portfolio Input'!C27,'Sector Analysis'!$A$4:$O$15,2,FALSE()),"")) | C27: =IF('Portfolio Input'!C27="","",IFERROR(VLOOKUP('Portfolio Input'!C27,'Sector Analysis'!$A$4:$O$15,3,FALSE()),"")) | D27: =IF('Portfolio Input'!C27="","",IFERROR(VLOOKUP('Portfolio Input'!C27,'Sector Analysis'!$A$4:$O$15,4,FALSE()),"")) | E27: =IF('Portfolio Input'!C27="","",IFERROR(VLOOKUP('Portfolio Input'!C27,'Sector Analysis'!$A$4:$O$15,5,FALSE()),"")) | F27: =IF('Portfolio Input'!C27="","",IFERROR(VLOOKUP('Portfolio Input'!C27,'Sector Analysis'!$A$4:$O$15,6,FALSE()),"")) | G27: =IF(OR(A27="", A27=0),"",B27*0.25+C27*0.2+D27*0.25+E27*0.15+F27*0.15) | H27: =IF('Portfolio Input'!C27="","",IFERROR(VLOOKUP('Portfolio Input'!C27,'Sector Analysis'!$A$4:$O$15,8,FALSE()),"")) | I27: =IF('Portfolio Input'!C27="","",IFERROR(VLOOKUP('Portfolio Input'!C27,'Sector Analysis'!$A$4:$O$15,9,FALSE()),"")) | J27: =IF('Portfolio Input'!C27="","",IFERROR(VLOOKUP('Portfolio Input'!C27,'Sector Analysis'!$A$4:$O$15,10,FALSE()),"")) | K27: =IF('Portfolio Input'!C27="","",IFERROR(VLOOKUP('Portfolio Input'!C27,'Sector Analysis'!$A$4:$O$15,11,FALSE()),"")) | L27: =IF('Portfolio Input'!C27="","",IFERROR(VLOOKUP('Portfolio Input'!C27,'Sector Analysis'!$A$4:$O$15,12,FALSE()),"")) | M27: =IF(A27="","",H27*0.25+I27*0.25+J27*0.15+K27*0.2+L27*0.15) -> #VALUE! | N27: =IF(A27="","",G27-M27) -> #VALUE! | O27: =IF(A27="","",IF(N27<=-2,"CRITICAL",IF(N27<=-0.5,"HIGH",IF(N27<=0.5,"MEDIUM",IF(N27<=1.5,"LOW-MEDIUM","LOW"))))) -> #VALUE! | P27: =IF(A27="","",IF(G27>=4,22,IF(G27>=3.5,18,IF(G27>=3,14,IF(G27>=2.5,10,IF(G27>=2,7,4)))))) -> 22 | Q27: =IF(A27="","",MAX(2,ROUND(P27*(1-MAX(0,(M27-1.5)*0.15)),0))) -> #VALUE! | R27: =IF(A27="","",MIN(400,IF(M27>=4,300,IF(M27>=3.5,225,IF(M27>=3,150,IF(M27>=2.5,100,IF(M27>=2,50,0))))))) -> #VALUE! | S27: =IF(A27="","",IF('Portfolio Input'!U27<=0.02,30,MIN(50,MAX(5,(1/('Portfolio Input'!U27-0.02))*(1-((1.02)/(1+'Portfolio Input'!U27))^P27)+((1.02)/(1+'Portfolio Input'!U27))^P27*(1/('Portfolio Input'!U27-0.02)))))) -> #VALUE! | T27: =IF(A27="","",IF(('Portfolio Input'!U27+R27/10000)<=0.02,30,MIN(50,MAX(5,(1/(('Portfolio Input'!U27+R27/10000)-0.02))*(1-((1.02)/(1+('Portfolio Input'!U27+R27/10000)))^Q27)+((1.02)/(1+('Portfolio Input'!U27+R27/10000)))^Q27*(1/(('Portfolio Input'!U27+R27/10000)-0.02)))))) -> #VALUE! | U27: =IF(A27="","",IF(S27>0,(S27-T27)/S27*100,0)) -> #VALUE!
A28: ='Portfolio Input'!A28 -> 0 | B28: =IF('Portfolio Input'!C28="","",IFERROR(VLOOKUP('Portfolio Input'!C28,'Sector Analysis'!$A$4:$O$15,2,FALSE()),"")) | C28: =IF('Portfolio Input'!C28="","",IFERROR(VLOOKUP('Portfolio Input'!C28,'Sector Analysis'!$A$4:$O$15,3,FALSE()),"")) | D28: =IF('Portfolio Input'!C28="","",IFERROR(VLOOKUP('Portfolio Input'!C28,'Sector Analysis'!$A$4:$O$15,4,FALSE()),"")) | E28: =IF('Portfolio Input'!C28="","",IFERROR(VLOOKUP('Portfolio Input'!C28,'Sector Analysis'!$A$4:$O$15,5,FALSE()),"")) | F28: =IF('Portfolio Input'!C28="","",IFERROR(VLOOKUP('Portfolio Input'!C28,'Sector Analysis'!$A$4:$O$15,6,FALSE()),"")) | G28: =IF(OR(A28="", A28=0),"",B28*0.25+C28*0.2+D28*0.25+E28*0.15+F28*0.15) | H28: =IF('Portfolio Input'!C28="","",IFERROR(VLOOKUP('Portfolio Input'!C28,'Sector Analysis'!$A$4:$O$15,8,FALSE()),"")) | I28: =IF('Portfolio Input'!C28="","",IFERROR(VLOOKUP('Portfolio Input'!C28,'Sector Analysis'!$A$4:$O$15,9,FALSE()),"")) | J28: =IF('Portfolio Input'!C28="","",IFERROR(VLOOKUP('Portfolio Input'!C28,'Sector Analysis'!$A$4:$O$15,10,FALSE()),"")) | K28: =IF('Portfolio Input'!C28="","",IFERROR(VLOOKUP('Portfolio Input'!C28,'Sector Analysis'!$A$4:$O$15,11,FALSE()),"")) | L28: =IF('Portfolio Input'!C28="","",IFERROR(VLOOKUP('Portfolio Input'!C28,'Sector Analysis'!$A$4:$O$15,12,FALSE()),"")) | M28: =IF(A28="","",H28*0.25+I28*0.25+J28*0.15+K28*0.2+L28*0.15) -> #VALUE! | N28: =IF(A28="","",G28-M28) -> #VALUE! | O28: =IF(A28="","",IF(N28<=-2,"CRITICAL",IF(N28<=-0.5,"HIGH",IF(N28<=0.5,"MEDIUM",IF(N28<=1.5,"LOW-MEDIUM","LOW"))))) -> #VALUE! | P28: =IF(A28="","",IF(G28>=4,22,IF(G28>=3.5,18,IF(G28>=3,14,IF(G28>=2.5,10,IF(G28>=2,7,4)))))) -> 22 | Q28: =IF(A28="","",MAX(2,ROUND(P28*(1-MAX(0,(M28-1.5)*0.15)),0))) -> #VALUE! | R28: =IF(A28="","",MIN(400,IF(M28>=4,300,IF(M28>=3.5,225,IF(M28>=3,150,IF(M28>=2.5,100,IF(M28>=2,50,0))))))) -> #VALUE! | S28: =IF(A28="","",IF('Portfolio Input'!U28<=0.02,30,MIN(50,MAX(5,(1/('Portfolio Input'!U28-0.02))*(1-((1.02)/(1+'Portfolio Input'!U28))^P28)+((1.02)/(1+'Portfolio Input'!U28))^P28*(1/('Portfolio Input'!U28-0.02)))))) -> #VALUE! | T28: =IF(A28="","",IF(('Portfolio Input'!U28+R28/10000)<=0.02,30,MIN(50,MAX(5,(1/(('Portfolio Input'!U28+R28/10000)-0.02))*(1-((1.02)/(1+('Portfolio Input'!U28+R28/10000)))^Q28)+((1.02)/(1+('Portfolio Input'!U28+R28/10000)))^Q28*(1/(('Portfolio Input'!U28+R28/10000)-0.02)))))) -> #VALUE! | U28: =IF(A28="","",IF(S28>0,(S28-T28)/S28*100,0)) -> #VALUE!
A29: ='Portfolio Input'!A29 -> 0 | B29: =IF('Portfolio Input'!C29="","",IFERROR(VLOOKUP('Portfolio Input'!C29,'Sector Analysis'!$A$4:$O$15,2,FALSE()),"")) | C29: =IF('Portfolio Input'!C29="","",IFERROR(VLOOKUP('Portfolio Input'!C29,'Sector Analysis'!$A$4:$O$15,3,FALSE()),"")) | D29: =IF('Portfolio Input'!C29="","",IFERROR(VLOOKUP('Portfolio Input'!C29,'Sector Analysis'!$A$4:$O$15,4,FALSE()),"")) | E29: =IF('Portfolio Input'!C29="","",IFERROR(VLOOKUP('Portfolio Input'!C29,'Sector Analysis'!$A$4:$O$15,5,FALSE()),"")) | F29: =IF('Portfolio Input'!C29="","",IFERROR(VLOOKUP('Portfolio Input'!C29,'Sector Analysis'!$A$4:$O$15,6,FALSE()),"")) | G29: =IF(OR(A29="", A29=0),"",B29*0.25+C29*0.2+D29*0.25+E29*0.15+F29*0.15) | H29: =IF('Portfolio Input'!C29="","",IFERROR(VLOOKUP('Portfolio Input'!C29,'Sector Analysis'!$A$4:$O$15,8,FALSE()),"")) | I29: =IF('Portfolio Input'!C29="","",IFERROR(VLOOKUP('Portfolio Input'!C29,'Sector Analysis'!$A$4:$O$15,9,FALSE()),"")) | J29: =IF('Portfolio Input'!C29="","",IFERROR(VLOOKUP('Portfolio Input'!C29,'Sector Analysis'!$A$4:$O$15,10,FALSE()),"")) | K29: =IF('Portfolio Input'!C29="","",IFERROR(VLOOKUP('Portfolio Input'!C29,'Sector Analysis'!$A$4:$O$15,11,FALSE()),"")) | L29: =IF('Portfolio Input'!C29="","",IFERROR(VLOOKUP('Portfolio Input'!C29,'Sector Analysis'!$A$4:$O$15,12,FALSE()),"")) | M29: =IF(A29="","",H29*0.25+I29*0.25+J29*0.15+K29*0.2+L29*0.15) -> #VALUE! | N29: =IF(A29="","",G29-M29) -> #VALUE! | O29: =IF(A29="","",IF(N29<=-2,"CRITICAL",IF(N29<=-0.5,"HIGH",IF(N29<=0.5,"MEDIUM",IF(N29<=1.5,"LOW-MEDIUM","LOW"))))) -> #VALUE! | P29: =IF(A29="","",IF(G29>=4,22,IF(G29>=3.5,18,IF(G29>=3,14,IF(G29>=2.5,10,IF(G29>=2,7,4)))))) -> 22 | Q29: =IF(A29="","",MAX(2,ROUND(P29*(1-MAX(0,(M29-1.5)*0.15)),0))) -> #VALUE! | R29: =IF(A29="","",MIN(400,IF(M29>=4,300,IF(M29>=3.5,225,IF(M29>=3,150,IF(M29>=2.5,100,IF(M29>=2,50,0))))))) -> #VALUE! | S29: =IF(A29="","",IF('Portfolio Input'!U29<=0.02,30,MIN(50,MAX(5,(1/('Portfolio Input'!U29-0.02))*(1-((1.02)/(1+'Portfolio Input'!U29))^P29)+((1.02)/(1+'Portfolio Input'!U29))^P29*(1/('Portfolio Input'!U29-0.02)))))) -> #VALUE! | T29: =IF(A29="","",IF(('Portfolio Input'!U29+R29/10000)<=0.02,30,MIN(50,MAX(5,(1/(('Portfolio Input'!U29+R29/10000)-0.02))*(1-((1.02)/(1+('Portfolio Input'!U29+R29/10000)))^Q29)+((1.02)/(1+('Portfolio Input'!U29+R29/10000)))^Q29*(1/(('Portfolio Input'!U29+R29/10000)-0.02)))))) -> #VALUE! | U29: =IF(A29="","",IF(S29>0,(S29-T29)/S29*100,0)) -> #VALUE!
A30: ='Portfolio Input'!A30 -> 0 | B30: =IF('Portfolio Input'!C30="","",IFERROR(VLOOKUP('Portfolio Input'!C30,'Sector Analysis'!$A$4:$O$15,2,FALSE()),"")) | C30: =IF('Portfolio Input'!C30="","",IFERROR(VLOOKUP('Portfolio Input'!C30,'Sector Analysis'!$A$4:$O$15,3,FALSE()),"")) | D30: =IF('Portfolio Input'!C30="","",IFERROR(VLOOKUP('Portfolio Input'!C30,'Sector Analysis'!$A$4:$O$15,4,FALSE()),"")) | E30: =IF('Portfolio Input'!C30="","",IFERROR(VLOOKUP('Portfolio Input'!C30,'Sector Analysis'!$A$4:$O$15,5,FALSE()),"")) | F30: =IF('Portfolio Input'!C30="","",IFERROR(VLOOKUP('Portfolio Input'!C30,'Sector Analysis'!$A$4:$O$15,6,FALSE()),"")) | G30: =IF(OR(A30="", A30=0),"",B30*0.25+C30*0.2+D30*0.25+E30*0.15+F30*0.15) | H30: =IF('Portfolio Input'!C30="","",IFERROR(VLOOKUP('Portfolio Input'!C30,'Sector Analysis'!$A$4:$O$15,8,FALSE()),"")) | I30: =IF('Portfolio Input'!C30="","",IFERROR(VLOOKUP('Portfolio Input'!C30,'Sector Analysis'!$A$4:$O$15,9,FALSE()),"")) | J30: =IF('Portfolio Input'!C30="","",IFERROR(VLOOKUP('Portfolio Input'!C30,'Sector Analysis'!$A$4:$O$15,10,FALSE()),"")) | K30: =IF('Portfolio Input'!C30="","",IFERROR(VLOOKUP('Portfolio Input'!C30,'Sector Analysis'!$A$4:$O$15,11,FALSE()),"")) | L30: =IF('Portfolio Input'!C30="","",IFERROR(VLOOKUP('Portfolio Input'!C30,'Sector Analysis'!$A$4:$O$15,12,FALSE()),"")) | M30: =IF(A30="","",H30*0.25+I30*0.25+J30*0.15+K30*0.2+L30*0.15) -> #VALUE! | N30: =IF(A30="","",G30-M30) -> #VALUE! | O30: =IF(A30="","",IF(N30<=-2,"CRITICAL",IF(N30<=-0.5,"HIGH",IF(N30<=0.5,"MEDIUM",IF(N30<=1.5,"LOW-MEDIUM","LOW"))))) -> #VALUE! | P30: =IF(A30="","",IF(G30>=4,22,IF(G30>=3.5,18,IF(G30>=3,14,IF(G30>=2.5,10,IF(G30>=2,7,4)))))) -> 22 | Q30: =IF(A30="","",MAX(2,ROUND(P30*(1-MAX(0,(M30-1.5)*0.15)),0))) -> #VALUE! | R30: =IF(A30="","",MIN(400,IF(M30>=4,300,IF(M30>=3.5,225,IF(M30>=3,150,IF(M30>=2.5,100,IF(M30>=2,50,0))))))) -> #VALUE! | S30: =IF(A30="","",IF('Portfolio Input'!U30<=0.02,30,MIN(50,MAX(5,(1/('Portfolio Input'!U30-0.02))*(1-((1.02)/(1+'Portfolio Input'!U30))^P30)+((1.02)/(1+'Portfolio Input'!U30))^P30*(1/('Portfolio Input'!U30-0.02)))))) -> #VALUE! | T30: =IF(A30="","",IF(('Portfolio Input'!U30+R30/10000)<=0.02,30,MIN(50,MAX(5,(1/(('Portfolio Input'!U30+R30/10000)-0.02))*(1-((1.02)/(1+('Portfolio Input'!U30+R30/10000)))^Q30)+((1.02)/(1+('Portfolio Input'!U30+R30/10000)))^Q30*(1/(('Portfolio Input'!U30+R30/10000)-0.02)))))) -> #VALUE! | U30: =IF(A30="","",IF(S30>0,(S30-T30)/S30*100,0)) -> #VALUE!
A31: ='Portfolio Input'!A31 -> 0 | B31: =IF('Portfolio Input'!C31="","",IFERROR(VLOOKUP('Portfolio Input'!C31,'Sector Analysis'!$A$4:$O$15,2,FALSE()),"")) | C31: =IF('Portfolio Input'!C31="","",IFERROR(VLOOKUP('Portfolio Input'!C31,'Sector Analysis'!$A$4:$O$15,3,FALSE()),"")) | D31: =IF('Portfolio Input'!C31="","",IFERROR(VLOOKUP('Portfolio Input'!C31,'Sector Analysis'!$A$4:$O$15,4,FALSE()),"")) | E31: =IF('Portfolio Input'!C31="","",IFERROR(VLOOKUP('Portfolio Input'!C31,'Sector Analysis'!$A$4:$O$15,5,FALSE()),"")) | F31: =IF('Portfolio Input'!C31="","",IFERROR(VLOOKUP('Portfolio Input'!C31,'Sector Analysis'!$A$4:$O$15,6,FALSE()),"")) | G31: =IF(OR(A31="", A31=0),"",B31*0.25+C31*0.2+D31*0.25+E31*0.15+F31*0.15) | H31: =IF('Portfolio Input'!C31="","",IFERROR(VLOOKUP('Portfolio Input'!C31,'Sector Analysis'!$A$4:$O$15,8,FALSE()),"")) | I31: =IF('Portfolio Input'!C31="","",IFERROR(VLOOKUP('Portfolio Input'!C31,'Sector Analysis'!$A$4:$O$15,9,FALSE()),"")) | J31: =IF('Portfolio Input'!C31="","",IFERROR(VLOOKUP('Portfolio Input'!C31,'Sector Analysis'!$A$4:$O$15,10,FALSE()),"")) | K31: =IF('Portfolio Input'!C31="","",IFERROR(VLOOKUP('Portfolio Input'!C31,'Sector Analysis'!$A$4:$O$15,11,FALSE()),"")) | L31: =IF('Portfolio Input'!C31="","",IFERROR(VLOOKUP('Portfolio Input'!C31,'Sector Analysis'!$A$4:$O$15,12,FALSE()),"")) | M31: =IF(A31="","",H31*0.25+I31*0.25+J31*0.15+K31*0.2+L31*0.15) -> #VALUE! | N31: =IF(A31="","",G31-M31) -> #VALUE! | O31: =IF(A31="","",IF(N31<=-2,"CRITICAL",IF(N31<=-0.5,"HIGH",IF(N31<=0.5,"MEDIUM",IF(N31<=1.5,"LOW-MEDIUM","LOW"))))) -> #VALUE! | P31: =IF(A31="","",IF(G31>=4,22,IF(G31>=3.5,18,IF(G31>=3,14,IF(G31>=2.5,10,IF(G31>=2,7,4)))))) -> 22 | Q31: =IF(A31="","",MAX(2,ROUND(P31*(1-MAX(0,(M31-1.5)*0.15)),0))) -> #VALUE! | R31: =IF(A31="","",MIN(400,IF(M31>=4,300,IF(M31>=3.5,225,IF(M31>=3,150,IF(M31>=2.5,100,IF(M31>=2,50,0))))))) -> #VALUE! | S31: =IF(A31="","",IF('Portfolio Input'!U31<=0.02,30,MIN(50,MAX(5,(1/('Portfolio Input'!U31-0.02))*(1-((1.02)/(1+'Portfolio Input'!U31))^P31)+((1.02)/(1+'Portfolio Input'!U31))^P31*(1/('Portfolio Input'!U31-0.02)))))) -> #VALUE! | T31: =IF(A31="","",IF(('Portfolio Input'!U31+R31/10000)<=0.02,30,MIN(50,MAX(5,(1/(('Portfolio Input'!U31+R31/10000)-0.02))*(1-((1.02)/(1+('Portfolio Input'!U31+R31/10000)))^Q31)+((1.02)/(1+('Portfolio Input'!U31+R31/10000)))^Q31*(1/(('Portfolio Input'!U31+R31/10000)-0.02)))))) -> #VALUE! | U31: =IF(A31="","",IF(S31>0,(S31-T31)/S31*100,0)) -> #VALUE!
A32: ='Portfolio Input'!A32 -> 0 | B32: =IF('Portfolio Input'!C32="","",IFERROR(VLOOKUP('Portfolio Input'!C32,'Sector Analysis'!$A$4:$O$15,2,FALSE()),"")) | C32: =IF('Portfolio Input'!C32="","",IFERROR(VLOOKUP('Portfolio Input'!C32,'Sector Analysis'!$A$4:$O$15,3,FALSE()),"")) | D32: =IF('Portfolio Input'!C32="","",IFERROR(VLOOKUP('Portfolio Input'!C32,'Sector Analysis'!$A$4:$O$15,4,FALSE()),"")) | E32: =IF('Portfolio Input'!C32="","",IFERROR(VLOOKUP('Portfolio Input'!C32,'Sector Analysis'!$A$4:$O$15,5,FALSE()),"")) | F32: =IF('Portfolio Input'!C32="","",IFERROR(VLOOKUP('Portfolio Input'!C32,'Sector Analysis'!$A$4:$O$15,6,FALSE()),"")) | G32: =IF(OR(A32="", A32=0),"",B32*0.25+C32*0.2+D32*0.25+E32*0.15+F32*0.15) | H32: =IF('Portfolio Input'!C32="","",IFERROR(VLOOKUP('Portfolio Input'!C32,'Sector Analysis'!$A$4:$O$15,8,FALSE()),"")) | I32: =IF('Portfolio Input'!C32="","",IFERROR(VLOOKUP('Portfolio Input'!C32,'Sector Analysis'!$A$4:$O$15,9,FALSE()),"")) | J32: =IF('Portfolio Input'!C32="","",IFERROR(VLOOKUP('Portfolio Input'!C32,'Sector Analysis'!$A$4:$O$15,10,FALSE()),"")) | K32: =IF('Portfolio Input'!C32="","",IFERROR(VLOOKUP('Portfolio Input'!C32,'Sector Analysis'!$A$4:$O$15,11,FALSE()),"")) | L32: =IF('Portfolio Input'!C32="","",IFERROR(VLOOKUP('Portfolio Input'!C32,'Sector Analysis'!$A$4:$O$15,12,FALSE()),"")) | M32: =IF(A32="","",H32*0.25+I32*0.25+J32*0.15+K32*0.2+L32*0.15) -> #VALUE! | N32: =IF(A32="","",G32-M32) -> #VALUE! | O32: =IF(A32="","",IF(N32<=-2,"CRITICAL",IF(N32<=-0.5,"HIGH",IF(N32<=0.5,"MEDIUM",IF(N32<=1.5,"LOW-MEDIUM","LOW"))))) -> #VALUE! | P32: =IF(A32="","",IF(G32>=4,22,IF(G32>=3.5,18,IF(G32>=3,14,IF(G32>=2.5,10,IF(G32>=2,7,4)))))) -> 22 | Q32: =IF(A32="","",MAX(2,ROUND(P32*(1-MAX(0,(M32-1.5)*0.15)),0))) -> #VALUE! | R32: =IF(A32="","",MIN(400,IF(M32>=4,300,IF(M32>=3.5,225,IF(M32>=3,150,IF(M32>=2.5,100,IF(M32>=2,50,0))))))) -> #VALUE! | S32: =IF(A32="","",IF('Portfolio Input'!U32<=0.02,30,MIN(50,MAX(5,(1/('Portfolio Input'!U32-0.02))*(1-((1.02)/(1+'Portfolio Input'!U32))^P32)+((1.02)/(1+'Portfolio Input'!U32))^P32*(1/('Portfolio Input'!U32-0.02)))))) -> #VALUE! | T32: =IF(A32="","",IF(('Portfolio Input'!U32+R32/10000)<=0.02,30,MIN(50,MAX(5,(1/(('Portfolio Input'!U32+R32/10000)-0.02))*(1-((1.02)/(1+('Portfolio Input'!U32+R32/10000)))^Q32)+((1.02)/(1+('Portfolio Input'!U32+R32/10000)))^Q32*(1/(('Portfolio Input'!U32+R32/10000)-0.02)))))) -> #VALUE! | U32: =IF(A32="","",IF(S32>0,(S32-T32)/S32*100,0)) -> #VALUE!
A33: ='Portfolio Input'!A33 -> 0 | B33: =IF('Portfolio Input'!C33="","",IFERROR(VLOOKUP('Portfolio Input'!C33,'Sector Analysis'!$A$4:$O$15,2,FALSE()),"")) | C33: =IF('Portfolio Input'!C33="","",IFERROR(VLOOKUP('Portfolio Input'!C33,'Sector Analysis'!$A$4:$O$15,3,FALSE()),"")) | D33: =IF('Portfolio Input'!C33="","",IFERROR(VLOOKUP('Portfolio Input'!C33,'Sector Analysis'!$A$4:$O$15,4,FALSE()),"")) | E33: =IF('Portfolio Input'!C33="","",IFERROR(VLOOKUP('Portfolio Input'!C33,'Sector Analysis'!$A$4:$O$15,5,FALSE()),"")) | F33: =IF('Portfolio Input'!C33="","",IFERROR(VLOOKUP('Portfolio Input'!C33,'Sector Analysis'!$A$4:$O$15,6,FALSE()),"")) | G33: =IF(OR(A33="", A33=0),"",B33*0.25+C33*0.2+D33*0.25+E33*0.15+F33*0.15) | H33: =IF('Portfolio Input'!C33="","",IFERROR(VLOOKUP('Portfolio Input'!C33,'Sector Analysis'!$A$4:$O$15,8,FALSE()),"")) | I33: =IF('Portfolio Input'!C33="","",IFERROR(VLOOKUP('Portfolio Input'!C33,'Sector Analysis'!$A$4:$O$15,9,FALSE()),"")) | J33: =IF('Portfolio Input'!C33="","",IFERROR(VLOOKUP('Portfolio Input'!C33,'Sector Analysis'!$A$4:$O$15,10,FALSE()),"")) | K33: =IF('Portfolio Input'!C33="","",IFERROR(VLOOKUP('Portfolio Input'!C33,'Sector Analysis'!$A$4:$O$15,11,FALSE()),"")) | L33: =IF('Portfolio Input'!C33="","",IFERROR(VLOOKUP('Portfolio Input'!C33,'Sector Analysis'!$A$4:$O$15,12,FALSE()),"")) | M33: =IF(A33="","",H33*0.25+I33*0.25+J33*0.15+K33*0.2+L33*0.15) -> #VALUE! | N33: =IF(A33="","",G33-M33) -> #VALUE! | O33: =IF(A33="","",IF(N33<=-2,"CRITICAL",IF(N33<=-0.5,"HIGH",IF(N33<=0.5,"MEDIUM",IF(N33<=1.5,"LOW-MEDIUM","LOW"))))) -> #VALUE! | P33: =IF(A33="","",IF(G33>=4,22,IF(G33>=3.5,18,IF(G33>=3,14,IF(G33>=2.5,10,IF(G33>=2,7,4)))))) -> 22 | Q33: =IF(A33="","",MAX(2,ROUND(P33*(1-MAX(0,(M33-1.5)*0.15)),0))) -> #VALUE! | R33: =IF(A33="","",MIN(400,IF(M33>=4,300,IF(M33>=3.5,225,IF(M33>=3,150,IF(M33>=2.5,100,IF(M33>=2,50,0))))))) -> #VALUE! | S33: =IF(A33="","",IF('Portfolio Input'!U33<=0.02,30,MIN(50,MAX(5,(1/('Portfolio Input'!U33-0.02))*(1-((1.02)/(1+'Portfolio Input'!U33))^P33)+((1.02)/(1+'Portfolio Input'!U33))^P33*(1/('Portfolio Input'!U33-0.02)))))) -> #VALUE! | T33: =IF(A33="","",IF(('Portfolio Input'!U33+R33/10000)<=0.02,30,MIN(50,MAX(5,(1/(('Portfolio Input'!U33+R33/10000)-0.02))*(1-((1.02)/(1+('Portfolio Input'!U33+R33/10000)))^Q33)+((1.02)/(1+('Portfolio Input'!U33+R33/10000)))^Q33*(1/(('Portfolio Input'!U33+R33/10000)-0.02)))))) -> #VALUE! | U33: =IF(A33="","",IF(S33>0,(S33-T33)/S33*100,0)) -> #VALUE!
A34: ='Portfolio Input'!A34 -> 0 | B34: =IF('Portfolio Input'!C34="","",IFERROR(VLOOKUP('Portfolio Input'!C34,'Sector Analysis'!$A$4:$O$15,2,FALSE()),"")) | C34: =IF('Portfolio Input'!C34="","",IFERROR(VLOOKUP('Portfolio Input'!C34,'Sector Analysis'!$A$4:$O$15,3,FALSE()),"")) | D34: =IF('Portfolio Input'!C34="","",IFERROR(VLOOKUP('Portfolio Input'!C34,'Sector Analysis'!$A$4:$O$15,4,FALSE()),"")) | E34: =IF('Portfolio Input'!C34="","",IFERROR(VLOOKUP('Portfolio Input'!C34,'Sector Analysis'!$A$4:$O$15,5,FALSE()),"")) | F34: =IF('Portfolio Input'!C34="","",IFERROR(VLOOKUP('Portfolio Input'!C34,'Sector Analysis'!$A$4:$O$15,6,FALSE()),"")) | G34: =IF(OR(A34="", A34=0),"",B34*0.25+C34*0.2+D34*0.25+E34*0.15+F34*0.15) | H34: =IF('Portfolio Input'!C34="","",IFERROR(VLOOKUP('Portfolio Input'!C34,'Sector Analysis'!$A$4:$O$15,8,FALSE()),"")) | I34: =IF('Portfolio Input'!C34="","",IFERROR(VLOOKUP('Portfolio Input'!C34,'Sector Analysis'!$A$4:$O$15,9,FALSE()),"")) | J34: =IF('Portfolio Input'!C34="","",IFERROR(VLOOKUP('Portfolio Input'!C34,'Sector Analysis'!$A$4:$O$15,10,FALSE()),"")) | K34: =IF('Portfolio Input'!C34="","",IFERROR(VLOOKUP('Portfolio Input'!C34,'Sector Analysis'!$A$4:$O$15,11,FALSE()),"")) | L34: =IF('Portfolio Input'!C34="","",IFERROR(VLOOKUP('Portfolio Input'!C34,'Sector Analysis'!$A$4:$O$15,12,FALSE()),"")) | M34: =IF(A34="","",H34*0.25+I34*0.25+J34*0.15+K34*0.2+L34*0.15) -> #VALUE! | N34: =IF(A34="","",G34-M34) -> #VALUE! | O34: =IF(A34="","",IF(N34<=-2,"CRITICAL",IF(N34<=-0.5,"HIGH",IF(N34<=0.5,"MEDIUM",IF(N34<=1.5,"LOW-MEDIUM","LOW"))))) -> #VALUE! | P34: =IF(A34="","",IF(G34>=4,22,IF(G34>=3.5,18,IF(G34>=3,14,IF(G34>=2.5,10,IF(G34>=2,7,4)))))) -> 22 | Q34: =IF(A34="","",MAX(2,ROUND(P34*(1-MAX(0,(M34-1.5)*0.15)),0))) -> #VALUE! | R34: =IF(A34="","",MIN(400,IF(M34>=4,300,IF(M34>=3.5,225,IF(M34>=3,150,IF(M34>=2.5,100,IF(M34>=2,50,0))))))) -> #VALUE! | S34: =IF(A34="","",IF('Portfolio Input'!U34<=0.02,30,MIN(50,MAX(5,(1/('Portfolio Input'!U34-0.02))*(1-((1.02)/(1+'Portfolio Input'!U34))^P34)+((1.02)/(1+'Portfolio Input'!U34))^P34*(1/('Portfolio Input'!U34-0.02)))))) -> #VALUE! | T34: =IF(A34="","",IF(('Portfolio Input'!U34+R34/10000)<=0.02,30,MIN(50,MAX(5,(1/(('Portfolio Input'!U34+R34/10000)-0.02))*(1-((1.02)/(1+('Portfolio Input'!U34+R34/10000)))^Q34)+((1.02)/(1+('Portfolio Input'!U34+R34/10000)))^Q34*(1/(('Portfolio Input'!U34+R34/10000)-0.02)))))) -> #VALUE! | U34: =IF(A34="","",IF(S34>0,(S34-T34)/S34*100,0)) -> #VALUE!
A35: ='Portfolio Input'!A35 -> 0 | B35: =IF('Portfolio Input'!C35="","",IFERROR(VLOOKUP('Portfolio Input'!C35,'Sector Analysis'!$A$4:$O$15,2,FALSE()),"")) | C35: =IF('Portfolio Input'!C35="","",IFERROR(VLOOKUP('Portfolio Input'!C35,'Sector Analysis'!$A$4:$O$15,3,FALSE()),"")) | D35: =IF('Portfolio Input'!C35="","",IFERROR(VLOOKUP('Portfolio Input'!C35,'Sector Analysis'!$A$4:$O$15,4,FALSE()),"")) | E35: =IF('Portfolio Input'!C35="","",IFERROR(VLOOKUP('Portfolio Input'!C35,'Sector Analysis'!$A$4:$O$15,5,FALSE()),"")) | F35: =IF('Portfolio Input'!C35="","",IFERROR(VLOOKUP('Portfolio Input'!C35,'Sector Analysis'!$A$4:$O$15,6,FALSE()),"")) | G35: =IF(OR(A35="", A35=0),"",B35*0.25+C35*0.2+D35*0.25+E35*0.15+F35*0.15) | H35: =IF('Portfolio Input'!C35="","",IFERROR(VLOOKUP('Portfolio Input'!C35,'Sector Analysis'!$A$4:$O$15,8,FALSE()),"")) | I35: =IF('Portfolio Input'!C35="","",IFERROR(VLOOKUP('Portfolio Input'!C35,'Sector Analysis'!$A$4:$O$15,9,FALSE()),"")) | J35: =IF('Portfolio Input'!C35="","",IFERROR(VLOOKUP('Portfolio Input'!C35,'Sector Analysis'!$A$4:$O$15,10,FALSE()),"")) | K35: =IF('Portfolio Input'!C35="","",IFERROR(VLOOKUP('Portfolio Input'!C35,'Sector Analysis'!$A$4:$O$15,11,FALSE()),"")) | L35: =IF('Portfolio Input'!C35="","",IFERROR(VLOOKUP('Portfolio Input'!C35,'Sector Analysis'!$A$4:$O$15,12,FALSE()),"")) | M35: =IF(A35="","",H35*0.25+I35*0.25+J35*0.15+K35*0.2+L35*0.15) -> #VALUE! | N35: =IF(A35="","",G35-M35) -> #VALUE! | O35: =IF(A35="","",IF(N35<=-2,"CRITICAL",IF(N35<=-0.5,"HIGH",IF(N35<=0.5,"MEDIUM",IF(N35<=1.5,"LOW-MEDIUM","LOW"))))) -> #VALUE! | P35: =IF(A35="","",IF(G35>=4,22,IF(G35>=3.5,18,IF(G35>=3,14,IF(G35>=2.5,10,IF(G35>=2,7,4)))))) -> 22 | Q35: =IF(A35="","",MAX(2,ROUND(P35*(1-MAX(0,(M35-1.5)*0.15)),0))) -> #VALUE! | R35: =IF(A35="","",MIN(400,IF(M35>=4,300,IF(M35>=3.5,225,IF(M35>=3,150,IF(M35>=2.5,100,IF(M35>=2,50,0))))))) -> #VALUE! | S35: =IF(A35="","",IF('Portfolio Input'!U35<=0.02,30,MIN(50,MAX(5,(1/('Portfolio Input'!U35-0.02))*(1-((1.02)/(1+'Portfolio Input'!U35))^P35)+((1.02)/(1+'Portfolio Input'!U35))^P35*(1/('Portfolio Input'!U35-0.02)))))) -> #VALUE! | T35: =IF(A35="","",IF(('Portfolio Input'!U35+R35/10000)<=0.02,30,MIN(50,MAX(5,(1/(('Portfolio Input'!U35+R35/10000)-0.02))*(1-((1.02)/(1+('Portfolio Input'!U35+R35/10000)))^Q35)+((1.02)/(1+('Portfolio Input'!U35+R35/10000)))^Q35*(1/(('Portfolio Input'!U35+R35/10000)-0.02)))))) -> #VALUE! | U35: =IF(A35="","",IF(S35>0,(S35-T35)/S35*100,0)) -> #VALUE!
A36: ='Portfolio Input'!A36 -> 0 | B36: =IF('Portfolio Input'!C36="","",IFERROR(VLOOKUP('Portfolio Input'!C36,'Sector Analysis'!$A$4:$O$15,2,FALSE()),"")) | C36: =IF('Portfolio Input'!C36="","",IFERROR(VLOOKUP('Portfolio Input'!C36,'Sector Analysis'!$A$4:$O$15,3,FALSE()),"")) | D36: =IF('Portfolio Input'!C36="","",IFERROR(VLOOKUP('Portfolio Input'!C36,'Sector Analysis'!$A$4:$O$15,4,FALSE()),"")) | E36: =IF('Portfolio Input'!C36="","",IFERROR(VLOOKUP('Portfolio Input'!C36,'Sector Analysis'!$A$4:$O$15,5,FALSE()),"")) | F36: =IF('Portfolio Input'!C36="","",IFERROR(VLOOKUP('Portfolio Input'!C36,'Sector Analysis'!$A$4:$O$15,6,FALSE()),"")) | G36: =IF(OR(A36="", A36=0),"",B36*0.25+C36*0.2+D36*0.25+E36*0.15+F36*0.15) | H36: =IF('Portfolio Input'!C36="","",IFERROR(VLOOKUP('Portfolio Input'!C36,'Sector Analysis'!$A$4:$O$15,8,FALSE()),"")) | I36: =IF('Portfolio Input'!C36="","",IFERROR(VLOOKUP('Portfolio Input'!C36,'Sector Analysis'!$A$4:$O$15,9,FALSE()),"")) | J36: =IF('Portfolio Input'!C36="","",IFERROR(VLOOKUP('Portfolio Input'!C36,'Sector Analysis'!$A$4:$O$15,10,FALSE()),"")) | K36: =IF('Portfolio Input'!C36="","",IFERROR(VLOOKUP('Portfolio Input'!C36,'Sector Analysis'!$A$4:$O$15,11,FALSE()),"")) | L36: =IF('Portfolio Input'!C36="","",IFERROR(VLOOKUP('Portfolio Input'!C36,'Sector Analysis'!$A$4:$O$15,12,FALSE()),"")) | M36: =IF(A36="","",H36*0.25+I36*0.25+J36*0.15+K36*0.2+L36*0.15) -> #VALUE! | N36: =IF(A36="","",G36-M36) -> #VALUE! | O36: =IF(A36="","",IF(N36<=-2,"CRITICAL",IF(N36<=-0.5,"HIGH",IF(N36<=0.5,"MEDIUM",IF(N36<=1.5,"LOW-MEDIUM","LOW"))))) -> #VALUE! | P36: =IF(A36="","",IF(G36>=4,22,IF(G36>=3.5,18,IF(G36>=3,14,IF(G36>=2.5,10,IF(G36>=2,7,4)))))) -> 22 | Q36: =IF(A36="","",MAX(2,ROUND(P36*(1-MAX(0,(M36-1.5)*0.15)),0))) -> #VALUE! | R36: =IF(A36="","",MIN(400,IF(M36>=4,300,IF(M36>=3.5,225,IF(M36>=3,150,IF(M36>=2.5,100,IF(M36>=2,50,0))))))) -> #VALUE! | S36: =IF(A36="","",IF('Portfolio Input'!U36<=0.02,30,MIN(50,MAX(5,(1/('Portfolio Input'!U36-0.02))*(1-((1.02)/(1+'Portfolio Input'!U36))^P36)+((1.02)/(1+'Portfolio Input'!U36))^P36*(1/('Portfolio Input'!U36-0.02)))))) -> #VALUE! | T36: =IF(A36="","",IF(('Portfolio Input'!U36+R36/10000)<=0.02,30,MIN(50,MAX(5,(1/(('Portfolio Input'!U36+R36/10000)-0.02))*(1-((1.02)/(1+('Portfolio Input'!U36+R36/10000)))^Q36)+((1.02)/(1+('Portfolio Input'!U36+R36/10000)))^Q36*(1/(('Portfolio Input'!U36+R36/10000)-0.02)))))) -> #VALUE! | U36: =IF(A36="","",IF(S36>0,(S36-T36)/S36*100,0)) -> #VALUE!
... A54: ='Portfolio Input'!A54 -> 0 | B54: =IF('Portfolio Input'!C54="","",IFERROR(VLOOKUP('Portfolio Input'!C54,'Sector Analysis'!$A$4:$O$15,2,FALSE()),"")) | C54: =IF('Portfolio Input'!C54="","",IFERROR(VLOOKUP('Portfolio Input'!C54,'Sector Analysis'!$A$4:$O$15,3,FALSE()),"")) | D54: =IF('Portfolio Input'!C54="","",IFERROR(VLOOKUP('Portfolio Input'!C54,'Sector Analysis'!$A$4:$O$15,4,FALSE()),"")) | E54: =IF('Portfolio Input'!C54="","",IFERROR(VLOOKUP('Portfolio Input'!C54,'Sector Analysis'!$A$4:$O$15,5,FALSE()),"")) | F54: =IF('Portfolio Input'!C54="","",IFERROR(VLOOKUP('Portfolio Input'!C54,'Sector Analysis'!$A$4:$O$15,6,FALSE()),"")) | G54: =IF(OR(A54="", A54=0),"",B54*0.25+C54*0.2+D54*0.25+E54*0.15+F54*0.15) | H54: =IF('Portfolio Input'!C54="","",IFERROR(VLOOKUP('Portfolio Input'!C54,'Sector Analysis'!$A$4:$O$15,8,FALSE()),"")) | I54: =IF('Portfolio Input'!C54="","",IFERROR(VLOOKUP('Portfolio Input'!C54,'Sector Analysis'!$A$4:$O$15,9,FALSE()),"")) | J54: =IF('Portfolio Input'!C54="","",IFERROR(VLOOKUP('Portfolio Input'!C54,'Sector Analysis'!$A$4:$O$15,10,FALSE()),"")) | K54: =IF('Portfolio Input'!C54="","",IFERROR(VLOOKUP('Portfolio Input'!C54,'Sector Analysis'!$A$4:$O$15,11,FALSE()),"")) | L54: =IF('Portfolio Input'!C54="","",IFERROR(VLOOKUP('Portfolio Input'!C54,'Sector Analysis'!$A$4:$O$15,12,FALSE()),"")) | M54: =IF(A54="","",H54*0.25+I54*0.25+J54*0.15+K54*0.2+L54*0.15) -> #VALUE! | N54: =IF(A54="","",G54-M54) -> #VALUE! | O54: =IF(A54="","",IF(N54<=-2,"CRITICAL",IF(N54<=-0.5,"HIGH",IF(N54<=0.5,"MEDIUM",IF(N54<=1.5,"LOW-MEDIUM","LOW"))))) -> #VALUE! | P54: =IF(A54="","",IF(G54>=4,22,IF(G54>=3.5,18,IF(G54>=3,14,IF(G54>=2.5,10,IF(G54>=2,7,4)))))) -> 22 | Q54: =IF(A54="","",MAX(2,ROUND(P54*(1-MAX(0,(M54-1.5)*0.15)),0))) -> #VALUE! | R54: =IF(A54="","",MIN(400,IF(M54>=4,300,IF(M54>=3.5,225,IF(M54>=3,150,IF(M54>=2.5,100,IF(M54>=2,50,0))))))) -> #VALUE! | S54: =IF(A54="","",IF('Portfolio Input'!U54<=0.02,30,MIN(50,MAX(5,(1/('Portfolio Input'!U54-0.02))*(1-((1.02)/(1+'Portfolio Input'!U54))^P54)+((1.02)/(1+'Portfolio Input'!U54))^P54*(1/('Portfolio Input'!U54-0.02)))))) -> #VALUE! | T54: =IF(A54="","",IF(('Portfolio Input'!U54+R54/10000)<=0.02,30,MIN(50,MAX(5,(1/(('Portfolio Input'!U54+R54/10000)-0.02))*(1-((1.02)/(1+('Portfolio Input'!U54+R54/10000)))^Q54)+((1.02)/(1+('Portfolio Input'!U54+R54/10000)))^Q54*(1/(('Portfolio Input'!U54+R54/10000)-0.02)))))) -> #VALUE! | U54: =IF(A54="","",IF(S54>0,(S54-T54)/S54*100,0)) -> #VALUE!

Sheet Business Model Risk
A1: Business Model Risk — Westwood Research AI Moat Decay Framework
A2: Scores START BLANK for new tickers. Fill in manually based on your research. For pre-loaded tickers, values are pre-filled.
A3: TIP: Use the Methodology & Wiki tab for definitions of each field. The webapp (moat_westwood.html) auto-fills these via Claude API.
A4: Ticker | B4: System Type | C4: Capital | D4: Value Delivery | E4: Vertical/Horiz | F4: Margin Structure | G4: WR Moat Tier | H4: Buy vs Build (1-5) | I4: JTBD Density (1-5) | J4: Moat Decay Rate | K4: Notes | L4: Composite Risk
A5: ='Portfolio Input'!A5 -> AAPL | B5: System of Record | C5: Medium | D5: Physical Product | E5: Deep Vertical | F5: Physical/Reg Premium | G5: Judgment Moat | H5: 2 | I5: 5 | J5: 10+ Years | L5: =IF(A5="","",IF(G5="Judgment Moat",1,IF(G5="Action Moat",2,IF(G5="Metadata Moat",3,IF(G5="Speed Moat",4,5))))*0.4+H5*0.3+(6-I5)*0.3) -> 1.3
A6: ='Portfolio Input'!A6 -> MSFT | B6: System of Record | C6: Asset-Light | D6: Workflow Automation | E6: Horizontal | F6: Value-Add Software | G6: Action Moat | H6: 3 | I6: 5 | J6: 5-10 Years | L6: =IF(A6="","",IF(G6="Judgment Moat",1,IF(G6="Action Moat",2,IF(G6="Metadata Moat",3,IF(G6="Speed Moat",4,5))))*0.4+H6*0.3+(6-I6)*0.3) -> 2
A7: ='Portfolio Input'!A7 -> GOOGL | B7: System of Action | C7: Asset-Light | D7: Data Access | E7: Horizontal | F7: Domain Judgment | G7: Judgment Moat | H7: 2 | I7: 5 | J7: 5-10 Years | L7: =IF(A7="","",IF(G7="Judgment Moat",1,IF(G7="Action Moat",2,IF(G7="Metadata Moat",3,IF(G7="Speed Moat",4,5))))*0.4+H7*0.3+(6-I7)*0.3) -> 1.3
A8: ='Portfolio Input'!A8 -> NVDA | B8: Physical/Regulatory | C8: Heavy | D8: Physical Product | E8: Infrastructure | F8: Physical/Reg Premium | G8: Judgment Moat | H8: 1 | I8: 4 | J8: 10+ Years | L8: =IF(A8="","",IF(G8="Judgment Moat",1,IF(G8="Action Moat",2,IF(G8="Metadata Moat",3,IF(G8="Speed Moat",4,5))))*0.4+H8*0.3+(6-I8)*0.3) -> 1.3
A9: ='Portfolio Input'!A9 -> AMZN | L9: =IF(A9="","",IF(G9="Judgment Moat",1,IF(G9="Action Moat",2,IF(G9="Metadata Moat",3,IF(G9="Speed Moat",4,5))))*0.4+H9*0.3+(6-I9)*0.3) -> 3.8
A10: ='Portfolio Input'!A10 -> META | L10: =IF(A10="","",IF(G10="Judgment Moat",1,IF(G10="Action Moat",2,IF(G10="Metadata Moat",3,IF(G10="Speed Moat",4,5))))*0.4+H10*0.3+(6-I10)*0.3) -> 3.8
A11: ='Portfolio Input'!A11 -> V | B11: System of Record | C11: Asset-Light | D11: Platform/Marketplace | E11: Infrastructure | F11: Physical/Reg Premium | G11: Action Moat | H11: 2 | I11: 5 | J11: 10+ Years | L11: =IF(A11="","",IF(G11="Judgment Moat",1,IF(G11="Action Moat",2,IF(G11="Metadata Moat",3,IF(G11="Speed Moat",4,5))))*0.4+H11*0.3+(6-I11)*0.3) -> 1.7
A12: ='Portfolio Input'!A12 -> MA | L12: =IF(A12="","",IF(G12="Judgment Moat",1,IF(G12="Action Moat",2,IF(G12="Metadata Moat",3,IF(G12="Speed Moat",4,5))))*0.4+H12*0.3+(6-I12)*0.3) -> 3.8
A13: ='Portfolio Input'!A13 -> ACN | B13: System of Action | C13: Asset-Light | D13: Workflow Automation | E13: Horizontal | F13: Value-Add Software | G13: Speed Moat | H13: 5 | I13: 2 | J13: Months | L13: =IF(A13="","",IF(G13="Judgment Moat",1,IF(G13="Action Moat",2,IF(G13="Metadata Moat",3,IF(G13="Speed Moat",4,5))))*0.4+H13*0.3+(6-I13)*0.3) -> 4.3
A14: ='Portfolio Input'!A14 -> CRM | B14: System of Record | C14: Asset-Light | D14: Workflow Automation | E14: Horizontal | F14: LLM Wrapper | G14: Speed Moat | H14: 4 | I14: 2 | J14: 1-2 Years | L14: =IF(A14="","",IF(G14="Judgment Moat",1,IF(G14="Action Moat",2,IF(G14="Metadata Moat",3,IF(G14="Speed Moat",4,5))))*0.4+H14*0.3+(6-I14)*0.3) -> 4
A15: ='Portfolio Input'!A15 -> ADBE | L15: =IF(A15="","",IF(G15="Judgment Moat",1,IF(G15="Action Moat",2,IF(G15="Metadata Moat",3,IF(G15="Speed Moat",4,5))))*0.4+H15*0.3+(6-I15)*0.3) -> 3.8
A16: ='Portfolio Input'!A16 -> NOW | L16: =IF(A16="","",IF(G16="Judgment Moat",1,IF(G16="Action Moat",2,IF(G16="Metadata Moat",3,IF(G16="Speed Moat",4,5))))*0.4+H16*0.3+(6-I16)*0.3) -> 3.8
A17: ='Portfolio Input'!A17 -> WU | B17: System of Action | C17: Medium | D17: Workflow Automation | E17: Horizontal | F17: LLM Wrapper | G17: No Durable Moat | H17: 5 | I17: 1 | J17: Months | L17: =IF(A17="","",IF(G17="Judgment Moat",1,IF(G17="Action Moat",2,IF(G17="Metadata Moat",3,IF(G17="Speed Moat",4,5))))*0.4+H17*0.3+(6-I17)*0.3) -> 5
A18: ='Portfolio Input'!A18 -> INFY | L18: =IF(A18="","",IF(G18="Judgment Moat",1,IF(G18="Action Moat",2,IF(G18="Metadata Moat",3,IF(G18="Speed Moat",4,5))))*0.4+H18*0.3+(6-I18)*0.3) -> 3.8
A19: ='Portfolio Input'!A19 -> UNH | L19: =IF(A19="","",IF(G19="Judgment Moat",1,IF(G19="Action Moat",2,IF(G19="Metadata Moat",3,IF(G19="Speed Moat",4,5))))*0.4+H19*0.3+(6-I19)*0.3) -> 3.8
A20: ='Portfolio Input'!A20 -> JPM | L20: =IF(A20="","",IF(G20="Judgment Moat",1,IF(G20="Action Moat",2,IF(G20="Metadata Moat",3,IF(G20="Speed Moat",4,5))))*0.4+H20*0.3+(6-I20)*0.3) -> 3.8
A21: ='Portfolio Input'!A21 -> BLK | L21: =IF(A21="","",IF(G21="Judgment Moat",1,IF(G21="Action Moat",2,IF(G21="Metadata Moat",3,IF(G21="Speed Moat",4,5))))*0.4+H21*0.3+(6-I21)*0.3) -> 3.8
A22: ='Portfolio Input'!A22 -> LLY | L22: =IF(A22="","",IF(G22="Judgment Moat",1,IF(G22="Action Moat",2,IF(G22="Metadata Moat",3,IF(G22="Speed Moat",4,5))))*0.4+H22*0.3+(6-I22)*0.3) -> 3.8
A23: ='Portfolio Input'!A23 -> XOM | L23: =IF(A23="","",IF(G23="Judgment Moat",1,IF(G23="Action Moat",2,IF(G23="Metadata Moat",3,IF(G23="Speed Moat",4,5))))*0.4+H23*0.3+(6-I23)*0.3) -> 3.8
A24: ='Portfolio Input'!A24 -> NEE | L24: =IF(A24="","",IF(G24="Judgment Moat",1,IF(G24="Action Moat",2,IF(G24="Metadata Moat",3,IF(G24="Speed Moat",4,5))))*0.4+H24*0.3+(6-I24)*0.3) -> 3.8
A25: ='Portfolio Input'!A25 -> GAP | L25: =IF(A25="","",IF(G25="Judgment Moat",1,IF(G25="Action Moat",2,IF(G25="Metadata Moat",3,IF(G25="Speed Moat",4,5))))*0.4+H25*0.3+(6-I25)*0.3) -> 3.8
A26: ='Portfolio Input'!A26 -> 0 | L26: =IF(A26="","",IF(G26="Judgment Moat",1,IF(G26="Action Moat",2,IF(G26="Metadata Moat",3,IF(G26="Speed Moat",4,5))))*0.4+H26*0.3+(6-I26)*0.3) -> 3.8
A27: ='Portfolio Input'!A27 -> 0 | L27: =IF(A27="","",IF(G27="Judgment Moat",1,IF(G27="Action Moat",2,IF(G27="Metadata Moat",3,IF(G27="Speed Moat",4,5))))*0.4+H27*0.3+(6-I27)*0.3) -> 3.8
A28: ='Portfolio Input'!A28 -> 0 | L28: =IF(A28="","",IF(G28="Judgment Moat",1,IF(G28="Action Moat",2,IF(G28="Metadata Moat",3,IF(G28="Speed Moat",4,5))))*0.4+H28*0.3+(6-I28)*0.3) -> 3.8
A29: ='Portfolio Input'!A29 -> 0 | L29: =IF(A29="","",IF(G29="Judgment Moat",1,IF(G29="Action Moat",2,IF(G29="Metadata Moat",3,IF(G29="Speed Moat",4,5))))*0.4+H29*0.3+(6-I29)*0.3) -> 3.8
... A54: ='Portfolio Input'!A54 -> 0 | L54: =IF(A54="","",IF(G54="Judgment Moat",1,IF(G54="Action Moat",2,IF(G54="Metadata Moat",3,IF(G54="Speed Moat",4,5))))*0.4+H54*0.3+(6-I54)*0.3) -> 3.8

Sheet Portfolio Dashboard
A1: Portfolio AI Disruption Risk Dashboard
A2: All auto-calculated. Add tickers in Portfolio Input → score in Moat Scoring & BM Risk → this updates.
A4: # Companies | B4: Avg Moat | C4: Avg AI Risk | D4: Avg Net | E4: Avg Haircut % | F4: # CRITICAL | G4: # HIGH | H4: # MEDIUM | I4: # LOW-MED | J4: # LOW
A5: =COUNTA('Moat Scoring'!A5:A54)-COUNTBLANK('Moat Scoring'!A5:A54) -> 50 | B5: =IFERROR(AVERAGE('Moat Scoring'!G5:G54),0) -> 3.0619048 | C5: =IFERROR(AVERAGE('Moat Scoring'!M5:M54),0) -> 0 | D5: =IFERROR(AVERAGE('Moat Scoring'!N5:N54),0) -> 0 | E5: =IFERROR(AVERAGE('Moat Scoring'!U5:U54),0) -> 0 | F5: =COUNTIF('Moat Scoring'!O5:O54,"CRITICAL") -> 0 | G5: =COUNTIF('Moat Scoring'!O5:O54,"HIGH") -> 7 | H5: =COUNTIF('Moat Scoring'!O5:O54,"MEDIUM") -> 2 | I5: =COUNTIF('Moat Scoring'!O5:O54,"LOW-MEDIUM") -> 11 | J5: =COUNTIF('Moat Scoring'!O5:O54,"LOW") -> 1
A7: Company Detail
A8: Ticker | B8: Company | C8: Sector | D8: Sub-Industry | E8: Moat | F8: AI Risk | G8: Net | H8: Tier | I8: WR Tier | J8: CAP | K8: Adj CAP | L8: WACC+bp | M8: Adj P/E | N8: Haircut %
A9: ='Portfolio Input'!A5 -> AAPL | B9: ='Portfolio Input'!B5 -> APPLE INC | C9: ='Portfolio Input'!C5 -> Information Technology | D9: ='Portfolio Input'!D5 -> Technology Hardware, Storage & | E9: ='Moat Scoring'!G5 -> 3.55 | F9: ='Moat Scoring'!M5 -> 2.95 | G9: ='Moat Scoring'!N5 -> 0.6 | H9: ='Moat Scoring'!O5 -> LOW-MEDIUM | I9: ='Business Model Risk'!G5 -> Judgment Moat | J9: ='Moat Scoring'!P5 -> 18 | K9: ='Moat Scoring'!Q5 -> 14 | L9: ='Moat Scoring'!R5 -> 100 | M9: ='Moat Scoring'!T5 -> 11.0502 | N9: ='Moat Scoring'!U5 -> 11.0502
A10: ='Portfolio Input'!A6 -> MSFT | B10: ='Portfolio Input'!B6 -> MICROSOFT CORP | C10: ='Portfolio Input'!C6 -> Information Technology | D10: ='Portfolio Input'!D6 -> Systems Software | E10: ='Moat Scoring'!G6 -> 3.55 | F10: ='Moat Scoring'!M6 -> 2.95 | G10: ='Moat Scoring'!N6 -> 0.6 | H10: ='Moat Scoring'!O6 -> LOW-MEDIUM | I10: ='Business Model Risk'!G6 -> Action Moat | J10: ='Moat Scoring'!P6 -> 18 | K10: ='Moat Scoring'!Q6 -> 14 | L10: ='Moat Scoring'!R6 -> 100 | M10: ='Moat Scoring'!T6 -> 11.605063 | N10: ='Moat Scoring'!U6 -> 11.605063
A11: ='Portfolio Input'!A7 -> GOOGL | B11: ='Portfolio Input'!B7 -> ALPHABET INC-CL A | C11: ='Portfolio Input'!C7 -> Communication Services | D11: ='Portfolio Input'!D7 -> Interactive Media & Services | E11: ='Moat Scoring'!G7 -> 3.5 | F11: ='Moat Scoring'!M7 -> 3.3 | G11: ='Moat Scoring'!N7 -> 0.2 | H11: ='Moat Scoring'!O7 -> MEDIUM | I11: ='Business Model Risk'!G7 -> Judgment Moat | J11: ='Moat Scoring'!P7 -> 18 | K11: ='Moat Scoring'!Q7 -> 13 | L11: ='Moat Scoring'!R7 -> 150 | M11: ='Moat Scoring'!T7 -> 10.722118 | N11: ='Moat Scoring'!U7 -> 16.083178
A12: ='Portfolio Input'!A8 -> NVDA | B12: ='Portfolio Input'!B8 -> NVIDIA CORP | C12: ='Portfolio Input'!C8 -> Information Technology | D12: ='Portfolio Input'!D8 -> Semiconductors | E12: ='Moat Scoring'!G8 -> 3.55 | F12: ='Moat Scoring'!M8 -> 2.95 | G12: ='Moat Scoring'!N8 -> 0.6 | H12: ='Moat Scoring'!O8 -> LOW-MEDIUM | I12: ='Business Model Risk'!G8 -> Judgment Moat | J12: ='Moat Scoring'!P8 -> 18 | K12: ='Moat Scoring'!Q8 -> 14 | L12: ='Moat Scoring'!R8 -> 100 | M12: ='Moat Scoring'!T8 -> 6.7459136 | N12: ='Moat Scoring'!U8 -> 6.7459136
A13: ='Portfolio Input'!A9 -> AMZN | B13: ='Portfolio Input'!B9 -> AMAZON.COM INC | C13: ='Portfolio Input'!C9 -> Consumer Discretionary | D13: ='Portfolio Input'!D9 -> Broadline Retail | E13: ='Moat Scoring'!G9 -> 2.1 | F13: ='Moat Scoring'!M9 -> 3.25 | G13: ='Moat Scoring'!N9 -> -1.15 | H13: ='Moat Scoring'!O9 -> HIGH | I13: ='Business Model Risk'!G9 -> 0 | J13: ='Moat Scoring'!P9 -> 7 | K13: ='Moat Scoring'!Q9 -> 5 | L13: ='Moat Scoring'!R9 -> 150 | M13: ='Moat Scoring'!T9 -> 9.0036303 | N13: ='Moat Scoring'!U9 -> 13.505445
A14: ='Portfolio Input'!A10 -> META | B14: ='Portfolio Input'!B10 -> META PLATFORMS INC-CLASS A | C14: ='Portfolio Input'!C10 -> Communication Services | D14: ='Portfolio Input'!D10 -> Interactive Media & Services | E14: ='Moat Scoring'!G10 -> 3.5 | F14: ='Moat Scoring'!M10 -> 3.3 | G14: ='Moat Scoring'!N10 -> 0.2 | H14: ='Moat Scoring'!O10 -> MEDIUM | I14: ='Business Model Risk'!G10 -> 0 | J14: ='Moat Scoring'!P10 -> 18 | K14: ='Moat Scoring'!Q10 -> 13 | L14: ='Moat Scoring'!R10 -> 150 | M14: ='Moat Scoring'!T10 -> 9.5838097 | N14: ='Moat Scoring'!U10 -> 14.375714
A15: ='Portfolio Input'!A11 -> V | B15: ='Portfolio Input'!B11 -> VISA INC-CLASS A SHARES | C15: ='Portfolio Input'!C11 -> Financials | D15: ='Portfolio Input'!D11 -> Transaction & Payment Processi | E15: ='Moat Scoring'!G11 -> 2.8 | F15: ='Moat Scoring'!M11 -> 4.1 | G15: ='Moat Scoring'!N11 -> -1.3 | H15: ='Moat Scoring'!O11 -> HIGH | I15: ='Business Model Risk'!G11 -> Action Moat | J15: ='Moat Scoring'!P11 -> 10 | K15: ='Moat Scoring'!Q11 -> 6 | L15: ='Moat Scoring'!R11 -> 300 | M15: ='Moat Scoring'!T11 -> 10.774321 | N15: ='Moat Scoring'!U11 -> 32.322964
A16: ='Portfolio Input'!A12 -> MA | B16: ='Portfolio Input'!B12 -> MASTERCARD INC - A | C16: ='Portfolio Input'!C12 -> Financials | D16: ='Portfolio Input'!D12 -> Transaction & Payment Processi | E16: ='Moat Scoring'!G12 -> 2.8 | F16: ='Moat Scoring'!M12 -> 4.1 | G16: ='Moat Scoring'!N12 -> -1.3 | H16: ='Moat Scoring'!O12 -> HIGH | I16: ='Business Model Risk'!G12 -> 0 | J16: ='Moat Scoring'!P12 -> 10 | K16: ='Moat Scoring'!Q12 -> 6 | L16: ='Moat Scoring'!R12 -> 300 | M16: ='Moat Scoring'!T12 -> 10.608293 | N16: ='Moat Scoring'!U12 -> 31.824878
A17: ='Portfolio Input'!A13 -> ACN | B17: ='Portfolio Input'!B13 -> ACCENTURE PLC-CL A | C17: ='Portfolio Input'!C13 -> Information Technology | D17: ='Portfolio Input'!D13 -> IT Consulting & Other Services | E17: ='Moat Scoring'!G13 -> 3.55 | F17: ='Moat Scoring'!M13 -> 2.95 | G17: ='Moat Scoring'!N13 -> 0.6 | H17: ='Moat Scoring'!O13 -> LOW-MEDIUM | I17: ='Business Model Risk'!G13 -> Speed Moat | J17: ='Moat Scoring'!P13 -> 18 | K17: ='Moat Scoring'!Q13 -> 14 | L17: ='Moat Scoring'!R13 -> 100 | M17: ='Moat Scoring'!T13 -> 15.355545 | N17: ='Moat Scoring'!U13 -> 15.355545
A18: ='Portfolio Input'!A14 -> CRM | B18: ='Portfolio Input'!B14 -> SALESFORCE INC | C18: ='Portfolio Input'!C14 -> Information Technology | D18: ='Portfolio Input'!D14 -> Application Software | E18: ='Moat Scoring'!G14 -> 3.55 | F18: ='Moat Scoring'!M14 -> 2.95 | G18: ='Moat Scoring'!N14 -> 0.6 | H18: ='Moat Scoring'!O14 -> LOW-MEDIUM | I18: ='Business Model Risk'!G14 -> Speed Moat | J18: ='Moat Scoring'!P14 -> 18 | K18: ='Moat Scoring'!Q14 -> 14 | L18: ='Moat Scoring'!R14 -> 100 | M18: ='Moat Scoring'!T14 -> 9.8291885 | N18: ='Moat Scoring'!U14 -> 9.8291885
A19: ='Portfolio Input'!A15 -> ADBE | B19: ='Portfolio Input'!B15 -> ADOBE INC | C19: ='Portfolio Input'!C15 -> Information Technology | D19: ='Portfolio Input'!D15 -> Application Software | E19: ='Moat Scoring'!G15 -> 3.55 | F19: ='Moat Scoring'!M15 -> 2.95 | G19: ='Moat Scoring'!N15 -> 0.6 | H19: ='Moat Scoring'!O15 -> LOW-MEDIUM | I19: ='Business Model Risk'!G15 -> 0 | J19: ='Moat Scoring'!P15 -> 18 | K19: ='Moat Scoring'!Q15 -> 14 | L19: ='Moat Scoring'!R15 -> 100 | M19: ='Moat Scoring'!T15 -> 11.710763 | N19: ='Moat Scoring'!U15 -> 11.710763
A20: ='Portfolio Input'!A16 -> NOW | B20: ='Portfolio Input'!B16 -> SERVICENOW INC | C20: ='Portfolio Input'!C16 -> Information Technology | D20: ='Portfolio Input'!D16 -> Systems Software | E20: ='Moat Scoring'!G16 -> 3.55 | F20: ='Moat Scoring'!M16 -> 2.95 | G20: ='Moat Scoring'!N16 -> 0.6 | H20: ='Moat Scoring'!O16 -> LOW-MEDIUM | I20: ='Business Model Risk'!G16 -> 0 | J20: ='Moat Scoring'!P16 -> 18 | K20: ='Moat Scoring'!Q16 -> 14 | L20: ='Moat Scoring'!R16 -> 100 | M20: ='Moat Scoring'!T16 -> 9.4832294 | N20: ='Moat Scoring'!U16 -> 9.4832294
... A58: ='Portfolio Input'!A54 -> 0 | B58: ='Portfolio Input'!B54 | C58: ='Portfolio Input'!C54 | D58: ='Portfolio Input'!D54 | E58: ='Moat Scoring'!G54 | F58: ='Moat Scoring'!M54 -> #VALUE! | G58: ='Moat Scoring'!N54 -> #VALUE! | H58: ='Moat Scoring'!O54 -> #VALUE! | I58: ='Business Model Risk'!G54 -> 0 | J58: ='Moat Scoring'!P54 -> 22 | K58: ='Moat Scoring'!Q54 -> #VALUE! | L58: ='Moat Scoring'!R54 -> #VALUE! | M58: ='Moat Scoring'!T54 -> #VALUE! | N58: ='Moat Scoring'!U54 -> #VALUE!

Sheet Sector Analysis
A1: GICS Sector — AI Disruption Risk
A3: GICS Sector | B3: SC | C3: NE | D3: IA | E3: CA | F3: ES | G3: Moat | H3: LS | I3: VCD | J3: DME | K3: ANC | L3: CIR | M3: AI Risk | N3: Net Moat | O3: Tier
A4: Information Technology | B4: 4 | C4: 4 | D4: 4 | E4: 3 | F4: 2 | G4: =B4*0.25+C4*0.2+D4*0.25+E4*0.15+F4*0.15 -> 3.55 | H4: 3 | I4: 2 | J4: 3 | K4: 4 | L4: 3 | M4: =H4*0.25+I4*0.25+J4*0.15+K4*0.2+L4*0.15 -> 2.95 | N4: =G4-M4 -> 0.6 | O4: =IF(N4<=-2,"CRITICAL",IF(N4<=-0.5,"HIGH",IF(N4<=0.5,"MEDIUM",IF(N4<=1.5,"LOW-MEDIUM","LOW")))) -> LOW-MEDIUM
A5: Communication Services | B5: 3 | C5: 5 | D5: 4 | E5: 2 | F5: 3 | G5: =B5*0.25+C5*0.2+D5*0.25+E5*0.15+F5*0.15 -> 3.5 | H5: 3 | I5: 3 | J5: 4 | K5: 3 | L5: 4 | M5: =H5*0.25+I5*0.25+J5*0.15+K5*0.2+L5*0.15 -> 3.3 | N5: =G5-M5 -> 0.2 | O5: =IF(N5<=-2,"CRITICAL",IF(N5<=-0.5,"HIGH",IF(N5<=0.5,"MEDIUM",IF(N5<=1.5,"LOW-MEDIUM","LOW")))) -> MEDIUM
A6: Health Care | B6: 3 | C6: 1 | D6: 5 | E6: 2 | F6: 3 | G6: =B6*0.25+C6*0.2+D6*0.25+E6*0.15+F6*0.15 -> 2.95 | H6: 2 | I6: 2 | J6: 2 | K6: 3 | L6: 2 | M6: =H6*0.25+I6*0.25+J6*0.15+K6*0.2+L6*0.15 -> 2.2 | N6: =G6-M6 -> 0.75 | O6: =IF(N6<=-2,"CRITICAL",IF(N6<=-0.5,"HIGH",IF(N6<=0.5,"MEDIUM",IF(N6<=1.5,"LOW-MEDIUM","LOW")))) -> LOW-MEDIUM
A7: Financials | B7: 3 | C7: 2 | D7: 3 | E7: 3 | F7: 3 | G7: =B7*0.25+C7*0.2+D7*0.25+E7*0.15+F7*0.15 -> 2.8 | H7: 5 | I7: 4 | J7: 3 | K7: 4 | L7: 4 | M7: =H7*0.25+I7*0.25+J7*0.15+K7*0.2+L7*0.15 -> 4.1 | N7: =G7-M7 -> -1.3 | O7: =IF(N7<=-2,"CRITICAL",IF(N7<=-0.5,"HIGH",IF(N7<=0.5,"MEDIUM",IF(N7<=1.5,"LOW-MEDIUM","LOW")))) -> HIGH
A8: Consumer Staples | B8: 2 | C8: 1 | D8: 4 | E8: 4 | F8: 2 | G8: =B8*0.25+C8*0.2+D8*0.25+E8*0.15+F8*0.15 -> 2.6 | H8: 2 | I8: 2 | J8: 1 | K8: 2 | L8: 1 | M8: =H8*0.25+I8*0.25+J8*0.15+K8*0.2+L8*0.15 -> 1.7 | N8: =G8-M8 -> 0.9 | O8: =IF(N8<=-2,"CRITICAL",IF(N8<=-0.5,"HIGH",IF(N8<=0.5,"MEDIUM",IF(N8<=1.5,"LOW-MEDIUM","LOW")))) -> LOW-MEDIUM
A9: Industrials | B9: 3 | C9: 1 | D9: 3 | E9: 4 | F9: 3 | G9: =B9*0.25+C9*0.2+D9*0.25+E9*0.15+F9*0.15 -> 2.75 | H9: 3 | I9: 2 | J9: 2 | K9: 2 | L9: 2 | M9: =H9*0.25+I9*0.25+J9*0.15+K9*0.2+L9*0.15 -> 2.25 | N9: =G9-M9 -> 0.5 | O9: =IF(N9<=-2,"CRITICAL",IF(N9<=-0.5,"HIGH",IF(N9<=0.5,"MEDIUM",IF(N9<=1.5,"LOW-MEDIUM","LOW")))) -> MEDIUM
A10: Consumer Discretionary | B10: 2 | C10: 2 | D10: 3 | E10: 2 | F10: 1 | G10: =B10*0.25+C10*0.2+D10*0.25+E10*0.15+F10*0.15 -> 2.1 | H10: 3 | I10: 4 | J10: 3 | K10: 3 | L10: 3 | M10: =H10*0.25+I10*0.25+J10*0.15+K10*0.2+L10*0.15 -> 3.25 | N10: =G10-M10 -> -1.15 | O10: =IF(N10<=-2,"CRITICAL",IF(N10<=-0.5,"HIGH",IF(N10<=0.5,"MEDIUM",IF(N10<=1.5,"LOW-MEDIUM","LOW")))) -> HIGH
A11: Energy | B11: 1 | C11: 1 | D11: 2 | E11: 4 | F11: 4 | G11: =B11*0.25+C11*0.2+D11*0.25+E11*0.15+F11*0.15 -> 2.15 | H11: 1 | I11: 1 | J11: 1 | K11: 1 | L11: 1 | M11: =H11*0.25+I11*0.25+J11*0.15+K11*0.2+L11*0.15 -> 1 | N11: =G11-M11 -> 1.15 | O11: =IF(N11<=-2,"CRITICAL",IF(N11<=-0.5,"HIGH",IF(N11<=0.5,"MEDIUM",IF(N11<=1.5,"LOW-MEDIUM","LOW")))) -> LOW-MEDIUM
A12: Utilities | B12: 2 | C12: 1 | D12: 3 | E12: 3 | F12: 5 | G12: =B12*0.25+C12*0.2+D12*0.25+E12*0.15+F12*0.15 -> 2.65 | H12: 1 | I12: 1 | J12: 1 | K12: 1 | L12: 1 | M12: =H12*0.25+I12*0.25+J12*0.15+K12*0.2+L12*0.15 -> 1 | N12: =G12-M12 -> 1.65 | O12: =IF(N12<=-2,"CRITICAL",IF(N12<=-0.5,"HIGH",IF(N12<=0.5,"MEDIUM",IF(N12<=1.5,"LOW-MEDIUM","LOW")))) -> LOW
A13: Real Estate | B13: 2 | C13: 1 | D13: 2 | E13: 2 | F13: 3 | G13: =B13*0.25+C13*0.2+D13*0.25+E13*0.15+F13*0.15 -> 1.95 | H13: 3 | I13: 4 | J13: 2 | K13: 3 | L13: 3 | M13: =H13*0.25+I13*0.25+J13*0.15+K13*0.2+L13*0.15 -> 3.1 | N13: =G13-M13 -> -1.15 | O13: =IF(N13<=-2,"CRITICAL",IF(N13<=-0.5,"HIGH",IF(N13<=0.5,"MEDIUM",IF(N13<=1.5,"LOW-MEDIUM","LOW")))) -> HIGH
A14: Materials | B14: 1 | C14: 1 | D14: 2 | E14: 4 | F14: 3 | G14: =B14*0.25+C14*0.2+D14*0.25+E14*0.15+F14*0.15 -> 2 | H14: 2 | I14: 1 | J14: 1 | K14: 1 | L14: 1 | M14: =H14*0.25+I14*0.25+J14*0.15+K14*0.2+L14*0.15 -> 1.25 | N14: =G14-M14 -> 0.75 | O14: =IF(N14<=-2,"CRITICAL",IF(N14<=-0.5,"HIGH",IF(N14<=0.5,"MEDIUM",IF(N14<=1.5,"LOW-MEDIUM","LOW")))) -> LOW-MEDIUM

Sheet Subsector Analysis
A1: GICS Subsector — AI Disruption Risk Drill-Down
A2: Shows differentiated AI risk within each sector. Semis ≠ SaaS ≠ IT Services.
A3: Sector | B3: Subsector | C3: SC | D3: NE | E3: IA | F3: CA | G3: ES | H3: Moat | I3: LS | J3: VCD | K3: DME | L3: ANC | M3: CIR | N3: AI Risk | O3: Net | P3: Tier | Q3: Examples
A4: Info Tech | B4: Enterprise SaaS | C4: 5 | D4: 3 | E4: 4 | F4: 2 | G4: 2 | H4: =C4*0.25+D4*0.2+E4*0.25+F4*0.15+G4*0.15 -> 3.45 | I4: 4 | J4: 3 | K4: 3 | L4: 5 | M4: 4 | N4: =I4*0.25+J4*0.25+K4*0.15+L4*0.2+M4*0.15 -> 3.8 | O4: =H4-N4 -> -0.35 | P4: =IF(O4<=-2,"CRITICAL",IF(O4<=-0.5,"HIGH",IF(O4<=0.5,"MEDIUM",IF(O4<=1.5,"LOW-MEDIUM","LOW")))) -> MEDIUM | Q4: CRM, WDAY, NOW
A5: Info Tech | B5: Semiconductors | C5: 3 | D5: 2 | E5: 5 | F5: 5 | G5: 4 | H5: =C5*0.25+D5*0.2+E5*0.25+F5*0.15+G5*0.15 -> 3.75 | I5: 1 | J5: 1 | K5: 2 | L5: 2 | M5: 1 | N5: =I5*0.25+J5*0.25+K5*0.15+L5*0.2+M5*0.15 -> 1.35 | O5: =H5-N5 -> 2.4 | P5: =IF(O5<=-2,"CRITICAL",IF(O5<=-0.5,"HIGH",IF(O5<=0.5,"MEDIUM",IF(O5<=1.5,"LOW-MEDIUM","LOW")))) -> LOW | Q5: NVDA, AMD, INTC
A6: Info Tech | B6: IT Services | C6: 3 | D6: 1 | E6: 2 | F6: 2 | G6: 1 | H6: =C6*0.25+D6*0.2+E6*0.25+F6*0.15+G6*0.15 -> 1.9 | I6: 5 | J6: 4 | K6: 2 | L6: 4 | M6: 5 | N6: =I6*0.25+J6*0.25+K6*0.15+L6*0.2+M6*0.15 -> 4.1 | O6: =H6-N6 -> -2.2 | P6: =IF(O6<=-2,"CRITICAL",IF(O6<=-0.5,"HIGH",IF(O6<=0.5,"MEDIUM",IF(O6<=1.5,"LOW-MEDIUM","LOW")))) -> CRITICAL | Q6: ACN, IBM, INFY
A7: Info Tech | B7: Internet / Search | C7: 4 | D7: 5 | E7: 4 | F7: 4 | G7: 3 | H7: =C7*0.25+D7*0.2+E7*0.25+F7*0.15+G7*0.15 -> 4.05 | I7: 2 | J7: 2 | K7: 4 | L7: 4 | M7: 3 | N7: =I7*0.25+J7*0.25+K7*0.15+L7*0.2+M7*0.15 -> 2.85 | O7: =H7-N7 -> 1.2 | P7: =IF(O7<=-2,"CRITICAL",IF(O7<=-0.5,"HIGH",IF(O7<=0.5,"MEDIUM",IF(O7<=1.5,"LOW-MEDIUM","LOW")))) -> LOW-MEDIUM | Q7: GOOGL, META
A8: Info Tech | B8: Hardware / Devices | C8: 4 | D8: 3 | E8: 4 | F8: 3 | G8: 2 | H8: =C8*0.25+D8*0.2+E8*0.25+F8*0.15+G8*0.15 -> 3.35 | I8: 1 | J8: 1 | K8: 2 | L8: 3 | M8: 2 | N8: =I8*0.25+J8*0.25+K8*0.15+L8*0.2+M8*0.15 -> 1.7 | O8: =H8-N8 -> 1.65 | P8: =IF(O8<=-2,"CRITICAL",IF(O8<=-0.5,"HIGH",IF(O8<=0.5,"MEDIUM",IF(O8<=1.5,"LOW-MEDIUM","LOW")))) -> LOW | Q8: AAPL, DELL
A9: Info Tech | B9: Cybersecurity | C9: 4 | D9: 2 | E9: 4 | F9: 2 | G9: 2 | H9: =C9*0.25+D9*0.2+E9*0.25+F9*0.15+G9*0.15 -> 3 | I9: 2 | J9: 2 | K9: 3 | L9: 4 | M9: 3 | N9: =I9*0.25+J9*0.25+K9*0.15+L9*0.2+M9*0.15 -> 2.7 | O9: =H9-N9 -> 0.3 | P9: =IF(O9<=-2,"CRITICAL",IF(O9<=-0.5,"HIGH",IF(O9<=0.5,"MEDIUM",IF(O9<=1.5,"LOW-MEDIUM","LOW")))) -> MEDIUM | Q9: CRWD, PANW
A10: Health Care | B10: Pharma / Biotech | C10: 2 | D10: 1 | E10: 5 | F10: 2 | G10: 3 | H10: =C10*0.25+D10*0.2+E10*0.25+F10*0.15+G10*0.15 -> 2.7 | I10: 1 | J10: 1 | K10: 1 | L10: 2 | M10: 1 | N10: =I10*0.25+J10*0.25+K10*0.15+L10*0.2+M10*0.15 -> 1.2 | O10: =H10-N10 -> 1.5 | P10: =IF(O10<=-2,"CRITICAL",IF(O10<=-0.5,"HIGH",IF(O10<=0.5,"MEDIUM",IF(O10<=1.5,"LOW-MEDIUM","LOW")))) -> LOW-MEDIUM | Q10: LLY, JNJ, PFE
A11: Health Care | B11: Medical Devices | C11: 4 | D11: 1 | E11: 5 | F11: 3 | G11: 3 | H11: =C11*0.25+D11*0.2+E11*0.25+F11*0.15+G11*0.15 -> 3.35 | I11: 1 | J11: 1 | K11: 1 | L11: 2 | M11: 1 | N11: =I11*0.25+J11*0.25+K11*0.15+L11*0.2+M11*0.15 -> 1.2 | O11: =H11-N11 -> 2.15 | P11: =IF(O11<=-2,"CRITICAL",IF(O11<=-0.5,"HIGH",IF(O11<=0.5,"MEDIUM",IF(O11<=1.5,"LOW-MEDIUM","LOW")))) -> LOW | Q11: MDT, SYK, ABT
A12: Health Care | B12: Health IT | C12: 5 | D12: 2 | E12: 3 | F12: 2 | G12: 2 | H12: =C12*0.25+D12*0.2+E12*0.25+F12*0.15+G12*0.15 -> 3 | I12: 4 | J12: 3 | K12: 3 | L12: 4 | M12: 4 | N12: =I12*0.25+J12*0.25+K12*0.15+L12*0.2+M12*0.15 -> 3.6 | O12: =H12-N12 -> -0.6 | P12: =IF(O12<=-2,"CRITICAL",IF(O12<=-0.5,"HIGH",IF(O12<=0.5,"MEDIUM",IF(O12<=1.5,"LOW-MEDIUM","LOW")))) -> HIGH | Q12: VEEV, HIMS
A13: Health Care | B13: Managed Care | C13: 3 | D13: 2 | E13: 3 | F13: 3 | G13: 4 | H13: =C13*0.25+D13*0.2+E13*0.25+F13*0.15+G13*0.15 -> 2.95 | I13: 3 | J13: 3 | K13: 2 | L13: 3 | M13: 3 | N13: =I13*0.25+J13*0.25+K13*0.15+L13*0.2+M13*0.15 -> 2.85 | O13: =H13-N13 -> 0.1 | P13: =IF(O13<=-2,"CRITICAL",IF(O13<=-0.5,"HIGH",IF(O13<=0.5,"MEDIUM",IF(O13<=1.5,"LOW-MEDIUM","LOW")))) -> MEDIUM | Q13: UNH, ELV, CI
A14: Financials | B14: Banks | C14: 4 | D14: 2 | E14: 3 | F14: 3 | G14: 4 | H14: =C14*0.25+D14*0.2+E14*0.25+F14*0.15+G14*0.15 -> 3.2 | I14: 4 | J14: 3 | K14: 2 | L14: 3 | M14: 3 | N14: =I14*0.25+J14*0.25+K14*0.15+L14*0.2+M14*0.15 -> 3.1 | O14: =H14-N14 -> 0.1 | P14: =IF(O14<=-2,"CRITICAL",IF(O14<=-0.5,"HIGH",IF(O14<=0.5,"MEDIUM",IF(O14<=1.5,"LOW-MEDIUM","LOW")))) -> MEDIUM | Q14: JPM, BAC, WFC
A15: Financials | B15: Asset Mgmt | C15: 2 | D15: 1 | E15: 3 | F15: 2 | G15: 2 | H15: =C15*0.25+D15*0.2+E15*0.25+F15*0.15+G15*0.15 -> 2.05 | I15: 3 | J15: 4 | K15: 3 | L15: 4 | M15: 4 | N15: =I15*0.25+J15*0.25+K15*0.15+L15*0.2+M15*0.15 -> 3.6 | O15: =H15-N15 -> -1.55 | P15: =IF(O15<=-2,"CRITICAL",IF(O15<=-0.5,"HIGH",IF(O15<=0.5,"MEDIUM",IF(O15<=1.5,"LOW-MEDIUM","LOW")))) -> HIGH | Q15: BLK, BX, WHG
... A39: Materials | B39: Mining/Metals | C39: 1 | D39: 1 | E39: 1 | F39: 5 | G39: 4 | H39: =C39*0.25+D39*0.2+E39*0.25+F39*0.15+G39*0.15 -> 2.05 | I39: 1 | J39: 1 | K39: 1 | L39: 1 | M39: 1 | N39: =I39*0.25+J39*0.25+K39*0.15+L39*0.2+M39*0.15 -> 1 | O39: =H39-N39 -> 1.05 | P39: =IF(O39<=-2,"CRITICAL",IF(O39<=-0.5,"HIGH",IF(O39<=0.5,"MEDIUM",IF(O39<=1.5,"LOW-MEDIUM","LOW")))) -> LOW-MEDIUM | Q39: FCX, NEM

Sheet Methodology & Wiki
A1: AI Moat Risk Analyzer — Methodology, Framework & Definitions
A4: OVERVIEW
A5: Purpose | B5: Evaluates moat durability under AI disruption | C5: Combines Morningstar moat + AI risk + Westwood Research BM risk
A6: Output | B6: AI-adjusted justified P/E and valuation haircut | C6: Quantifies % of fair value at risk from AI disruption
A8: DATA SOURCES
A9: Bloomberg Terminal | B9: BDP() formulas in Portfolio Input | C9: Live financials: price, beta, margins, multiples
A10: Moat/AI Scores | B10: Manual 1-5 in Moat Scoring tab (blue cells) | C10: Analyst assessment per company
A11: BM Risk | B11: Manual in Business Model Risk tab | C11: Westwood Research framework
A13: MOAT FRAMEWORK (Morningstar 5-Source)
A14: Switching Costs (25%) | B14: Cost of changing providers | C14: 5=extreme lock-in (Oracle ERP, Epic EMR)
A15: Network Effects (20%) | B15: Value increases with users | C15: 5=powerful networks (Visa, Meta)
A16: Intangible Assets (25%) | B16: Patents, brands, licenses | C16: 5=irreplaceable (LLY patents, KO brand)
A17: Cost Advantage (15%) | B17: Structural cost leadership | C17: 5=massive cost moat (XOM, WMT)
A18: Efficient Scale (15%) | B18: Market too small for competition | C18: 5=natural monopoly (utilities, defense)
A19: Formula | B19: SC×0.25 + NE×0.20 + IA×0.25 + CA×0.15 + ES×0.15 | C19: Range 1-5, higher = stronger moat
A21: AI DISRUPTION RISK (5 Dimensions)
A22: Labor Substitution (25%) | B22: Can AI replace the workforce? | C22: 5=highly substitutable (call centers, data entry)
A23: Disintermediation (25%) | B23: Can AI bypass the company? | C23: 5=easily bypassed (travel agents, brokers)
A24: Data Moat Erosion (15%) | B24: Can AI commoditize data? | C24: 5=data becoming commodity
A25: AI-Native Competition (20%) | B25: AI-first startups attacking? | C25: 5=intense AI-native competition
A26: Commodity Intelligence (15%) | B26: Can generic AI replicate it? | C26: 5=easily replicated by LLMs
A27: Formula | B27: LS×0.25 + VCD×0.25 + DME×0.15 + ANC×0.20 + CIR×0.15 | C27: Range 1-5, higher = more risk
A29: WESTWOOD RESEARCH BM RISK
A30: 5. Judgment Moat | B30: Highest durability | C30: Domain expertise AI cannot replicate (surgery, M&A)
A31: 4. Action Moat | B31: High durability | C31: Complex real-world actions (manufacturing, logistics)
A32: 3. Metadata Moat | B32: Medium durability | C32: Proprietary data context layers (Bloomberg, Palantir)
A33: 2. Speed Moat | B33: Low durability | C33: Only first-mover advantage, AI enables fast-followers
A34: 1. No Durable Moat | B34: No durability | C34: AI replicates core value in months
A35: System Type | B35: SoR | SoA | Judgment | Physical/Reg | Hybrid | C35: Role in customer workflow
A36: Buy vs Build (1-5) | B36: How easily could customer build with AI? | C36: 5=trivial to rebuild
A37: JTBD Density (1-5) | B37: How many jobs-to-be-done served? | C37: Higher = harder to displace
A38: Decay Rate | B38: Months | 1-2yr | 3-5yr | 5-10yr | 10+yr | C38: Speed of AI erosion
A39: Composite | B39: WR_Tier×0.4 + BvB×0.3 + (6-JTBD)×0.3 | C39: Range 0-5
A41: VALUATION
A42: Net Moat | B42: Moat - AI Risk - BM_Risk×0.3 | C42: Positive = moat dominates
A43: Tier | B43: CRITICAL≤-2 | HIGH | MEDIUM | LOW-MED | LOW>1.5 | C43: Risk classification
A44: CAP (Mauboussin) | B44: 4-22 years based on moat score | C44: AI erosion: -15%/pt above 1.5
A45: WACC Premium | B45: 0-400bp added to base WACC | C45: AI uncertainty surcharge
A46: Justified P/E | B46: Damodaran DCF: f(WACC, growth, CAP) | C46: AI-Adj uses higher WACC + shorter CAP
A47: Haircut | B47: (Base_PE - Adj_PE) / Base_PE × 100 | C47: % of value at risk
A49: HOW TO USE
A50: Step 1 | B50: Open on Bloomberg Terminal | C50: Bloomberg add-in must be enabled
A51: Step 2 | B51: Enter tickers in Portfolio Input col A | C51: Bloomberg auto-fills all financials
A52: Step 3 | B52: Score in Moat Scoring tab (blue cells) | C52: 1-5 for each moat and AI risk dimension
A53: Step 4 | B53: Score in Business Model Risk tab | C53: System type, WR tier, decay rate, etc.
A54: Step 5 | B54: Review Portfolio Dashboard | C54: Auto-calculates. Sort by Net Moat for risk
A56: NOTE: Claude Add-in | B56: NOT connected to this workbook | C56: Use Claude to research, but enter scores manually in blue cells
A57: NOTE: Web App | B57: moat_westwood.html does auto-scoring | C57: Uses AI API to score companies automatically
A59: AUTO-POPULATE BEHAVIOR
A60: Moat Scoring auto-fills | B60: When you add a ticker in Portfolio Input, Bloomberg fills the GICS Sector | C60: Moat Scoring cols B-F and H-L auto-populate via VLOOKUP from Sector Analysis defaults
A61: Override anytime | B61: Simply type over any auto-populated cell | C61: Your manual value replaces the VLOOKUP formula. This is by design.
A62: Business Model Risk | B62: Does NOT auto-populate — requires manual research | C62: System type, WR tier, decay rate are company-specific. Use webapp for AI-assisted scoring.
A63: Restore defaults | B63: Delete cell contents and re-enter the VLOOKUP formula | C63: Or just leave it — sector defaults are a reasonable starting point.
A64: Sector Analysis tab | B64: Editable sector-level scores that drive the VLOOKUPs | C64: Change a sector score here → all tickers in that sector auto-update (unless manually overridden)

Sheet Bloomberg Setup
A1: Bloomberg Excel API — Setup & Formula Reference
A3: Step 1 | B3: Open workbook on Bloomberg Terminal machine
A4: Step 2 | B4: Bloomberg tab → Enable Bloomberg Add-in
A5: Step 3 | B5: Enter tickers in Portfolio Input col A
A6: Step 4 | B6: Score moat/AI risk in Moat Scoring (blue cells)
A7: Step 5 | B7: Score BM risk in Business Model Risk (blue cells)
A8: Step 6 | B8: Review Portfolio Dashboard — all auto-calculates
A10: BDP Syntax | B10: =_xll.BDP("AAPL US Equity","PX_LAST") -> 259.445
A11: BQL Syntax | B11: =_xll.BQL("get(px_last) for('AAPL US Equity')") -> #N/A Mandatory parameter [FIELDS] not provided
A12: Key Fields | B12: PX_LAST, CUR_MKT_CAP, BETA_RAW_OVERRIDABLE, BEST_PE_RATIO, RETURN_ON_INV_CAPITAL
B13: RETURN_COM_EQY, GROSS_MARGIN, OPER_MARGIN, NET_INCOME_MARGIN, FREE_CASH_FLOW_YIELD
A14: Troubleshoot | B14: If #NAME?: Bloomberg add-in not loaded. File → Options → Add-ins → COM Add-ins
A15: Refresh | B15: Ctrl+Shift+R refreshes all Bloomberg formulas
